Workbook
Name PB: lists!$M$8:$M$11
Name PB_1: lists!$J$3:$J$5
Name PB_2: lists!$J$6:$J$7
Name PB_3: lists!$J$8:$J$10
Name PB_4: lists!$J$11:$J$13

Sheet Raw - F
C1: Date | D1: Course | E1: Code | F1: Jump Type | G1: Type | H1: M/N | J1: Age | K1: Sex | L1: Class | M1: PL | N1: RB | O1: Distance | P1: Distance Category | Q1: RaceValue | R1: Race name | T1: Region | U1: AWT | V1: Rider | W1: SC | X1: Auc | AA1: Age classification | AB1: Sex classification | AC1: Dist rank | AD1: HC inc | AE1: JT inc | AF1: Dist inc | AG1: Sex inc | AH1: Mdn/Nov | AI1: Month inc | AJ1: Class inc | AK1: Region include | AL1: INCLUDE?
A2: =IF(B2="",A1,B2+1) -> 2 | B2: =IF(AND(A1<1,AL2=1),1,IF(AL2=1,A1,"")) -> 1 | C2: 44317 | D2: DONCASTER | E2: Flat | F2: Flat | G2: Hcap | H2: Open | J2: 3yo+ | K2: A | L2: 2 | N2: 86-105 | O2: 6f2y | P2: 6f | Q2: 20000 | R2: DEFENCE HCAP STKS | T2: North | U2: 0 | AA2: =IF(OR(J2="2yo",J2="3yo"),J2,"Other") -> Other | AB2: =IF(K2="F",K2,"A") -> A | AC2: =VLOOKUP(P2,lists!$G:$H,2,FALSE) -> 2 | AD2: =VLOOKUP(G2,lists!$B$2:$C$3,2,FALSE) -> TRUE | AE2: =VLOOKUP(AA2,lists!$B:$C,2,FALSE) -> TRUE | AF2: =IF(AND(AC2>=VLOOKUP(FLAT!$I$1,lists!$G:$H,2,FALSE),AC2<=VLOOKUP(FLAT!$I$2,lists!$G:$H,2,FALSE)),TRUE,FALSE) -> TRUE | AG2: =VLOOKUP(AB2,lists!$B$7:$C$8,2,FALSE) -> TRUE | AH2: =VLOOKUP(IF(H2="","Open",SUBSTITUTE(H2,"/Nov","")),lists!$B$27:$D$29,2,FALSE) -> TRUE | AI2: =IF(FLAT!$I$5="All",TRUE,IF(FLAT!$I$5=TEXT('Raw - F'!C2,"mmm"),TRUE,FALSE)) -> TRUE | AJ2: =VLOOKUP(L2,lists!B:C,2,FALSE) -> TRUE | AK2: =VLOOKUP(T2,lists!$B$23:$D$25,2,FALSE) -> TRUE | AL2: =IF(AND(AD2=TRUE,AE2=TRUE,AF2=TRUE,AG2=TRUE,AH2=TRUE,AI2=TRUE,AJ2=TRUE,AK2=TRUE),1,0) -> 1
A3: =IF(B3="",A2,B3+1) -> 3 | B3: =IF(AND(A2<1,AL3=1),1,IF(AL3=1,A2,"")) -> 2 | C3: 44317 | D3: DONCASTER | E3: Flat | F3: Flat | G3: Hcap | H3: Open | J3: 4yo+ | K3: A | L3: 3 | N3: 71-90 | O3: 6f2y | P3: 6f | Q3: 12000 | R3: DEFENCE HCAP STKS | T3: North | U3: 0 | AA3: =IF(OR(J3="2yo",J3="3yo"),J3,"Other") -> Other | AB3: =IF(K3="F",K3,"A") -> A | AC3: =VLOOKUP(P3,lists!$G:$H,2,FALSE) -> 2 | AD3: =VLOOKUP(G3,lists!$B$2:$C$3,2,FALSE) -> TRUE | AE3: =VLOOKUP(AA3,lists!$B:$C,2,FALSE) -> TRUE | AF3: =IF(AND(AC3>=VLOOKUP(FLAT!$I$1,lists!$G:$H,2,FALSE),AC3<=VLOOKUP(FLAT!$I$2,lists!$G:$H,2,FALSE)),TRUE,FALSE) -> TRUE | AG3: =VLOOKUP(AB3,lists!$B$7:$C$8,2,FALSE) -> TRUE | AH3: =VLOOKUP(IF(H3="","Open",SUBSTITUTE(H3,"/Nov","")),lists!$B$27:$D$29,2,FALSE) -> TRUE | AI3: =IF(FLAT!$I$5="All",TRUE,IF(FLAT!$I$5=TEXT('Raw - F'!C3,"mmm"),TRUE,FALSE)) -> TRUE | AJ3: =VLOOKUP(L3,lists!B:C,2,FALSE) -> TRUE | AK3: =VLOOKUP(T3,lists!$B$23:$D$25,2,FALSE) -> TRUE | AL3: =IF(AND(AD3=TRUE,AE3=TRUE,AF3=TRUE,AG3=TRUE,AH3=TRUE,AI3=TRUE,AJ3=TRUE,AK3=TRUE),1,0) -> 1
A4: =IF(B4="",A3,B4+1) -> 4 | B4: =IF(AND(A3<1,AL4=1),1,IF(AL4=1,A3,"")) -> 3 | C4: 44317 | D4: DONCASTER | E4: Flat | F4: Flat | G4: Hcap | H4: Open | J4: 3yo | K4: A | L4: 3 | N4: 71-90 | O4: 1m | P4: 1m | Q4: 12000 | R4: SKY SPORTS HCAP STKS | T4: North | U4: 0 | AA4: =IF(OR(J4="2yo",J4="3yo"),J4,"Other") -> 3yo | AB4: =IF(K4="F",K4,"A") -> A | AC4: =VLOOKUP(P4,lists!$G:$H,2,FALSE) -> 4 | AD4: =VLOOKUP(G4,lists!$B$2:$C$3,2,FALSE) -> TRUE | AE4: =VLOOKUP(AA4,lists!$B:$C,2,FALSE) -> TRUE | AF4: =IF(AND(AC4>=VLOOKUP(FLAT!$I$1,lists!$G:$H,2,FALSE),AC4<=VLOOKUP(FLAT!$I$2,lists!$G:$H,2,FALSE)),TRUE,FALSE) -> TRUE | AG4: =VLOOKUP(AB4,lists!$B$7:$C$8,2,FALSE) -> TRUE | AH4: =VLOOKUP(IF(H4="","Open",SUBSTITUTE(H4,"/Nov","")),lists!$B$27:$D$29,2,FALSE) -> TRUE | AI4: =IF(FLAT!$I$5="All",TRUE,IF(FLAT!$I$5=TEXT('Raw - F'!C4,"mmm"),TRUE,FALSE)) -> TRUE | AJ4: =VLOOKUP(L4,lists!B:C,2,FALSE) -> TRUE | AK4: =VLOOKUP(T4,lists!$B$23:$D$25,2,FALSE) -> TRUE | AL4: =IF(AND(AD4=TRUE,AE4=TRUE,AF4=TRUE,AG4=TRUE,AH4=TRUE,AI4=TRUE,AJ4=TRUE,AK4=TRUE),1,0) -> 1
A5: =IF(B5="",A4,B5+1) -> 5 | B5: =IF(AND(A4<1,AL5=1),1,IF(AL5=1,A4,"")) -> 4 | C5: 44317 | D5: DONCASTER | E5: Flat | F5: Flat | G5: Hcap | H5: Open | J5: 3yo+ | K5: F | L5: 4 | N5: 66-85 | O5: 1m3f197y | P5: 1m 4f | Q5: 7650 | R5: WATCH SKY HCAP STKS | T5: North | U5: 0 | AA5: =IF(OR(J5="2yo",J5="3yo"),J5,"Other") -> Other | AB5: =IF(K5="F",K5,"A") -> F | AC5: =VLOOKUP(P5,lists!$G:$H,2,FALSE) -> 7 | AD5: =VLOOKUP(G5,lists!$B$2:$C$3,2,FALSE) -> TRUE | AE5: =VLOOKUP(AA5,lists!$B:$C,2,FALSE) -> TRUE | AF5: =IF(AND(AC5>=VLOOKUP(FLAT!$I$1,lists!$G:$H,2,FALSE),AC5<=VLOOKUP(FLAT!$I$2,lists!$G:$H,2,FALSE)),TRUE,FALSE) -> TRUE | AG5: =VLOOKUP(AB5,lists!$B$7:$C$8,2,FALSE) -> TRUE | AH5: =VLOOKUP(IF(H5="","Open",SUBSTITUTE(H5,"/Nov","")),lists!$B$27:$D$29,2,FALSE) -> TRUE | AI5: =IF(FLAT!$I$5="All",TRUE,IF(FLAT!$I$5=TEXT('Raw - F'!C5,"mmm"),TRUE,FALSE)) -> TRUE | AJ5: =VLOOKUP(L5,lists!B:C,2,FALSE) -> TRUE | AK5: =VLOOKUP(T5,lists!$B$23:$D$25,2,FALSE) -> TRUE | AL5: =IF(AND(AD5=TRUE,AE5=TRUE,AF5=TRUE,AG5=TRUE,AH5=TRUE,AI5=TRUE,AJ5=TRUE,AK5=TRUE),1,0) -> 1
A6: =IF(B6="",A5,B6+1) -> 6 | B6: =IF(AND(A5<1,AL6=1),1,IF(AL6=1,A5,"")) -> 5 | C6: 44317 | D6: DONCASTER | E6: Flat | F6: Flat | G6: Hcap | H6: Open | J6: 4yo+ | K6: A | L6: 4 | N6: 66-85 | O6: 2m | P6: 2m+ | Q6: 7650 | R6: DMRC HCAP STKS | S6: C | T6: North | U6: 0 | AA6: =IF(OR(J6="2yo",J6="3yo"),J6,"Other") -> Other | AB6: =IF(K6="F",K6,"A") -> A | AC6: =VLOOKUP(P6,lists!$G:$H,2,FALSE) -> 11 | AD6: =VLOOKUP(G6,lists!$B$2:$C$3,2,FALSE) -> TRUE | AE6: =VLOOKUP(AA6,lists!$B:$C,2,FALSE) -> TRUE | AF6: =IF(AND(AC6>=VLOOKUP(FLAT!$I$1,lists!$G:$H,2,FALSE),AC6<=VLOOKUP(FLAT!$I$2,lists!$G:$H,2,FALSE)),TRUE,FALSE) -> TRUE | AG6: =VLOOKUP(AB6,lists!$B$7:$C$8,2,FALSE) -> TRUE | AH6: =VLOOKUP(IF(H6="","Open",SUBSTITUTE(H6,"/Nov","")),lists!$B$27:$D$29,2,FALSE) -> TRUE | AI6: =IF(FLAT!$I$5="All",TRUE,IF(FLAT!$I$5=TEXT('Raw - F'!C6,"mmm"),TRUE,FALSE)) -> TRUE | AJ6: =VLOOKUP(L6,lists!B:C,2,FALSE) -> TRUE | AK6: =VLOOKUP(T6,lists!$B$23:$D$25,2,FALSE) -> TRUE | AL6: =IF(AND(AD6=TRUE,AE6=TRUE,AF6=TRUE,AG6=TRUE,AH6=TRUE,AI6=TRUE,AJ6=TRUE,AK6=TRUE),1,0) -> 1
A7: =IF(B7="",A6,B7+1) -> 7 | B7: =IF(AND(A6<1,AL7=1),1,IF(AL7=1,A6,"")) -> 6 | C7: 44317 | D7: DONCASTER | E7: Flat | F7: Flat | G7: WFA | H7: Mdn | J7: 2yo | K7: A | L7: 5 | N7: Open | O7: 5f3y | P7: 5f | Q7: 5400 | R7: DMRC EBF NOV STKS | S7: C | T7: North | U7: 0 | Z7: EBF | AA7: =IF(OR(J7="2yo",J7="3yo"),J7,"Other") -> 2yo | AB7: =IF(K7="F",K7,"A") -> A | AC7: =VLOOKUP(P7,lists!$G:$H,2,FALSE) -> 1 | AD7: =VLOOKUP(G7,lists!$B$2:$C$3,2,FALSE) -> TRUE | AE7: =VLOOKUP(AA7,lists!$B:$C,2,FALSE) -> TRUE | AF7: =IF(AND(AC7>=VLOOKUP(FLAT!$I$1,lists!$G:$H,2,FALSE),AC7<=VLOOKUP(FLAT!$I$2,lists!$G:$H,2,FALSE)),TRUE,FALSE) -> TRUE | AG7: =VLOOKUP(AB7,lists!$B$7:$C$8,2,FALSE) -> TRUE | AH7: =VLOOKUP(IF(H7="","Open",SUBSTITUTE(H7,"/Nov","")),lists!$B$27:$D$29,2,FALSE) -> TRUE | AI7: =IF(FLAT!$I$5="All",TRUE,IF(FLAT!$I$5=TEXT('Raw - F'!C7,"mmm"),TRUE,FALSE)) -> TRUE | AJ7: =VLOOKUP(L7,lists!B:C,2,FALSE) -> TRUE | AK7: =VLOOKUP(T7,lists!$B$23:$D$25,2,FALSE) -> TRUE | AL7: =IF(AND(AD7=TRUE,AE7=TRUE,AF7=TRUE,AG7=TRUE,AH7=TRUE,AI7=TRUE,AJ7=TRUE,AK7=TRUE),1,0) -> 1
A8: =IF(B8="",A7,B8+1) -> 8 | B8: =IF(AND(A7<1,AL8=1),1,IF(AL8=1,A7,"")) -> 7 | C8: 44317 | D8: DONCASTER | E8: Flat | F8: Flat | G8: WFA | H8: Nov | J8: 3yo+ | K8: A | L8: 5 | N8: Open | O8: 6f2y | P8: 6f | Q8: 4900 | R8: DEFENCE NOV STKS | T8: North | U8: 0 | AA8: =IF(OR(J8="2yo",J8="3yo"),J8,"Other") -> Other | AB8: =IF(K8="F",K8,"A") -> A | AC8: =VLOOKUP(P8,lists!$G:$H,2,FALSE) -> 2 | AD8: =VLOOKUP(G8,lists!$B$2:$C$3,2,FALSE) -> TRUE | AE8: =VLOOKUP(AA8,lists!$B:$C,2,FALSE) -> TRUE | AF8: =IF(AND(AC8>=VLOOKUP(FLAT!$I$1,lists!$G:$H,2,FALSE),AC8<=VLOOKUP(FLAT!$I$2,lists!$G:$H,2,FALSE)),TRUE,FALSE) -> TRUE | AG8: =VLOOKUP(AB8,lists!$B$7:$C$8,2,FALSE) -> TRUE | AH8: =VLOOKUP(IF(H8="","Open",SUBSTITUTE(H8,"/Nov","")),lists!$B$27:$D$29,2,FALSE) -> TRUE | AI8: =IF(FLAT!$I$5="All",TRUE,IF(FLAT!$I$5=TEXT('Raw - F'!C8,"mmm"),TRUE,FALSE)) -> TRUE | AJ8: =VLOOKUP(L8,lists!B:C,2,FALSE) -> TRUE | AK8: =VLOOKUP(T8,lists!$B$23:$D$25,2,FALSE) -> TRUE | AL8: =IF(AND(AD8=TRUE,AE8=TRUE,AF8=TRUE,AG8=TRUE,AH8=TRUE,AI8=TRUE,AJ8=TRUE,AK8=TRUE),1,0) -> 1
A9: =IF(B9="",A8,B9+1) -> 9 | B9: =IF(AND(A8<1,AL9=1),1,IF(AL9=1,A8,"")) -> 8 | C9: 44317 | D9: GOODWOOD | E9: Flat | F9: Flat | G9: WFA | H9: Open | J9: 3yo+ | K9: F | L9: 1 | M9: 1(Lstd) | N9: Open | O9: 1m | P9: 1m | Q9: 50000 | R9: CONQUEROR STKS | T9: South | U9: 0 | AA9: =IF(OR(J9="2yo",J9="3yo"),J9,"Other") -> Other | AB9: =IF(K9="F",K9,"A") -> F | AC9: =VLOOKUP(P9,lists!$G:$H,2,FALSE) -> 4 | AD9: =VLOOKUP(G9,lists!$B$2:$C$3,2,FALSE) -> TRUE | AE9: =VLOOKUP(AA9,lists!$B:$C,2,FALSE) -> TRUE | AF9: =IF(AND(AC9>=VLOOKUP(FLAT!$I$1,lists!$G:$H,2,FALSE),AC9<=VLOOKUP(FLAT!$I$2,lists!$G:$H,2,FALSE)),TRUE,FALSE) -> TRUE | AG9: =VLOOKUP(AB9,lists!$B$7:$C$8,2,FALSE) -> TRUE | AH9: =VLOOKUP(IF(H9="","Open",SUBSTITUTE(H9,"/Nov","")),lists!$B$27:$D$29,2,FALSE) -> TRUE | AI9: =IF(FLAT!$I$5="All",TRUE,IF(FLAT!$I$5=TEXT('Raw - F'!C9,"mmm"),TRUE,FALSE)) -> TRUE | AJ9: =VLOOKUP(L9,lists!B:C,2,FALSE) -> TRUE | AK9: =VLOOKUP(T9,lists!$B$23:$D$25,2,FALSE) -> TRUE | AL9: =IF(AND(AD9=TRUE,AE9=TRUE,AF9=TRUE,AG9=TRUE,AH9=TRUE,AI9=TRUE,AJ9=TRUE,AK9=TRUE),1,0) -> 1
A10: =IF(B10="",A9,B10+1) -> 10 | B10: =IF(AND(A9<1,AL10=1),1,IF(AL10=1,A9,"")) -> 9 | C10: 44317 | D10: GOODWOOD | E10: Flat | F10: Flat | G10: Hcap | H10: Open | J10: 4yo+ | K10: A | L10: 2 | N10: 81-100 | O10: 7f | P10: 7f | Q10: 50000 | R10: SINGLETON HCAP STKS | T10: South | U10: 0 | AA10: =IF(OR(J10="2yo",J10="3yo"),J10,"Other") -> Other | AB10: =IF(K10="F",K10,"A") -> A | AC10: =VLOOKUP(P10,lists!$G:$H,2,FALSE) -> 3 | AD10: =VLOOKUP(G10,lists!$B$2:$C$3,2,FALSE) -> TRUE | AE10: =VLOOKUP(AA10,lists!$B:$C,2,FALSE) -> TRUE | AF10: =IF(AND(AC10>=VLOOKUP(FLAT!$I$1,lists!$G:$H,2,FALSE),AC10<=VLOOKUP(FLAT!$I$2,lists!$G:$H,2,FALSE)),TRUE,FALSE) -> TRUE | AG10: =VLOOKUP(AB10,lists!$B$7:$C$8,2,FALSE) -> TRUE | AH10: =VLOOKUP(IF(H10="","Open",SUBSTITUTE(H10,"/Nov","")),lists!$B$27:$D$29,2,FALSE) -> TRUE | AI10: =IF(FLAT!$I$5="All",TRUE,IF(FLAT!$I$5=TEXT('Raw - F'!C10,"mmm"),TRUE,FALSE)) -> TRUE | AJ10: =VLOOKUP(L10,lists!B:C,2,FALSE) -> TRUE | AK10: =VLOOKUP(T10,lists!$B$23:$D$25,2,FALSE) -> TRUE | AL10: =IF(AND(AD10=TRUE,AE10=TRUE,AF10=TRUE,AG10=TRUE,AH10=TRUE,AI10=TRUE,AJ10=TRUE,AK10=TRUE),1,0) -> 1
A11: =IF(B11="",A10,B11+1) -> 11 | B11: =IF(AND(A10<1,AL11=1),1,IF(AL11=1,A10,"")) -> 10 | C11: 44317 | D11: GOODWOOD | E11: Flat | F11: Flat | G11: Hcap | H11: Open | J11: 4yo+ | K11: A | L11: 2 | N11: 81-100 | O11: 5f | P11: 5f | Q11: 15000 | R11: FARMER HCAP STKS | T11: South | U11: 0 | AA11: =IF(OR(J11="2yo",J11="3yo"),J11,"Other") -> Other | AB11: =IF(K11="F",K11,"A") -> A | AC11: =VLOOKUP(P11,lists!$G:$H,2,FALSE) -> 1 | AD11: =VLOOKUP(G11,lists!$B$2:$C$3,2,FALSE) -> TRUE | AE11: =VLOOKUP(AA11,lists!$B:$C,2,FALSE) -> TRUE | AF11: =IF(AND(AC11>=VLOOKUP(FLAT!$I$1,lists!$G:$H,2,FALSE),AC11<=VLOOKUP(FLAT!$I$2,lists!$G:$H,2,FALSE)),TRUE,FALSE) -> TRUE | AG11: =VLOOKUP(AB11,lists!$B$7:$C$8,2,FALSE) -> TRUE | AH11: =VLOOKUP(IF(H11="","Open",SUBSTITUTE(H11,"/Nov","")),lists!$B$27:$D$29,2,FALSE) -> TRUE | AI11: =IF(FLAT!$I$5="All",TRUE,IF(FLAT!$I$5=TEXT('Raw - F'!C11,"mmm"),TRUE,FALSE)) -> TRUE | AJ11: =VLOOKUP(L11,lists!B:C,2,FALSE) -> TRUE | AK11: =VLOOKUP(T11,lists!$B$23:$D$25,2,FALSE) -> TRUE | AL11: =IF(AND(AD11=TRUE,AE11=TRUE,AF11=TRUE,AG11=TRUE,AH11=TRUE,AI11=TRUE,AJ11=TRUE,AK11=TRUE),1,0) -> 1
A12: =IF(B12="",A11,B12+1) -> 12 | B12: =IF(AND(A11<1,AL12=1),1,IF(AL12=1,A11,"")) -> 11 | C12: 44317 | D12: GOODWOOD | E12: Flat | F12: Flat | G12: Hcap | H12: Open | J12: 3yo | K12: A | L12: 3 | N12: 71-90 | O12: 7f | P12: 7f | Q12: 11500 | R12: MATERIALS HCAP STKS | T12: South | U12: 0 | AA12: =IF(OR(J12="2yo",J12="3yo"),J12,"Other") -> 3yo | AB12: =IF(K12="F",K12,"A") -> A | AC12: =VLOOKUP(P12,lists!$G:$H,2,FALSE) -> 3 | AD12: =VLOOKUP(G12,lists!$B$2:$C$3,2,FALSE) -> TRUE | AE12: =VLOOKUP(AA12,lists!$B:$C,2,FALSE) -> TRUE | AF12: =IF(AND(AC12>=VLOOKUP(FLAT!$I$1,lists!$G:$H,2,FALSE),AC12<=VLOOKUP(FLAT!$I$2,lists!$G:$H,2,FALSE)),TRUE,FALSE) -> TRUE | AG12: =VLOOKUP(AB12,lists!$B$7:$C$8,2,FALSE) -> TRUE | AH12: =VLOOKUP(IF(H12="","Open",SUBSTITUTE(H12,"/Nov","")),lists!$B$27:$D$29,2,FALSE) -> TRUE | AI12: =IF(FLAT!$I$5="All",TRUE,IF(FLAT!$I$5=TEXT('Raw - F'!C12,"mmm"),TRUE,FALSE)) -> TRUE | AJ12: =VLOOKUP(L12,lists!B:C,2,FALSE) -> TRUE | AK12: =VLOOKUP(T12,lists!$B$23:$D$25,2,FALSE) -> TRUE | AL12: =IF(AND(AD12=TRUE,AE12=TRUE,AF12=TRUE,AG12=TRUE,AH12=TRUE,AI12=TRUE,AJ12=TRUE,AK12=TRUE),1,0) -> 1
A13: =IF(B13="",A12,B13+1) -> 13 | B13: =IF(AND(A12<1,AL13=1),1,IF(AL13=1,A12,"")) -> 12 | C13: 44317 | D13: GOODWOOD | E13: Flat | F13: Flat | G13: WFA | H13: Mdn | J13: 3yo+ | K13: A | L13: 4 | N13: Open | O13: 1m | P13: 1m | Q13: 8000 | R13: ROOF GARDEN MDN STKS | T13: South | U13: 0 | AA13: =IF(OR(J13="2yo",J13="3yo"),J13,"Other") -> Other | AB13: =IF(K13="F",K13,"A") -> A | AC13: =VLOOKUP(P13,lists!$G:$H,2,FALSE) -> 4 | AD13: =VLOOKUP(G13,lists!$B$2:$C$3,2,FALSE) -> TRUE | AE13: =VLOOKUP(AA13,lists!$B:$C,2,FALSE) -> TRUE | AF13: =IF(AND(AC13>=VLOOKUP(FLAT!$I$1,lists!$G:$H,2,FALSE),AC13<=VLOOKUP(FLAT!$I$2,lists!$G:$H,2,FALSE)),TRUE,FALSE) -> TRUE | AG13: =VLOOKUP(AB13,lists!$B$7:$C$8,2,FALSE) -> TRUE | AH13: =VLOOKUP(IF(H13="","Open",SUBSTITUTE(H13,"/Nov","")),lists!$B$27:$D$29,2,FALSE) -> TRUE | AI13: =IF(FLAT!$I$5="All",TRUE,IF(FLAT!$I$5=TEXT('Raw - F'!C13,"mmm"),TRUE,FALSE)) -> TRUE | AJ13: =VLOOKUP(L13,lists!B:C,2,FALSE) -> TRUE | AK13: =VLOOKUP(T13,lists!$B$23:$D$25,2,FALSE) -> TRUE | AL13: =IF(AND(AD13=TRUE,AE13=TRUE,AF13=TRUE,AG13=TRUE,AH13=TRUE,AI13=TRUE,AJ13=TRUE,AK13=TRUE),1,0) -> 1
A14: =IF(B14="",A13,B14+1) -> 14 | B14: =IF(AND(A13<1,AL14=1),1,IF(AL14=1,A13,"")) -> 13 | C14: 44317 | D14: GOODWOOD | E14: Flat | F14: Flat | G14: Hcap | H14: Open | J14: 3yo | K14: A | L14: 5 | N14: 51-70 | O14: 1m1f197y | P14: 1m 2f | Q14: 8000 | R14: LONG VIEW HCAP STKS | T14: South | U14: 0 | AA14: =IF(OR(J14="2yo",J14="3yo"),J14,"Other") -> 3yo | AB14: =IF(K14="F",K14,"A") -> A | AC14: =VLOOKUP(P14,lists!$G:$H,2,FALSE) -> 5 | AD14: =VLOOKUP(G14,lists!$B$2:$C$3,2,FALSE) -> TRUE | AE14: =VLOOKUP(AA14,lists!$B:$C,2,FALSE) -> TRUE | AF14: =IF(AND(AC14>=VLOOKUP(FLAT!$I$1,lists!$G:$H,2,FALSE),AC14<=VLOOKUP(FLAT!$I$2,lists!$G:$H,2,FALSE)),TRUE,FALSE) -> TRUE | AG14: =VLOOKUP(AB14,lists!$B$7:$C$8,2,FALSE) -> TRUE | AH14: =VLOOKUP(IF(H14="","Open",SUBSTITUTE(H14,"/Nov","")),lists!$B$27:$D$29,2,FALSE) -> TRUE | AI14: =IF(FLAT!$I$5="All",TRUE,IF(FLAT!$I$5=TEXT('Raw - F'!C14,"mmm"),TRUE,FALSE)) -> TRUE | AJ14: =VLOOKUP(L14,lists!B:C,2,FALSE) -> TRUE | AK14: =VLOOKUP(T14,lists!$B$23:$D$25,2,FALSE) -> TRUE | AL14: =IF(AND(AD14=TRUE,AE14=TRUE,AF14=TRUE,AG14=TRUE,AH14=TRUE,AI14=TRUE,AJ14=TRUE,AK14=TRUE),1,0) -> 1
A15: =IF(B15="",A14,B15+1) -> 15 | B15: =IF(AND(A14<1,AL15=1),1,IF(AL15=1,A14,"")) -> 14 | C15: 44317 | D15: GOODWOOD | E15: Flat | F15: Flat | G15: Hcap | H15: Open | J15: 4yo+ | K15: A | L15: 5 | N15: 56-75 | O15: 1m6f | P15: 2m+ | Q15: 8000 | R15: DOUBLE TRIGGER HCAP | T15: South | U15: 0 | AA15: =IF(OR(J15="2yo",J15="3yo"),J15,"Other") -> Other | AB15: =IF(K15="F",K15,"A") -> A | AC15: =VLOOKUP(P15,lists!$G:$H,2,FALSE) -> 11 | AD15: =VLOOKUP(G15,lists!$B$2:$C$3,2,FALSE) -> TRUE | AE15: =VLOOKUP(AA15,lists!$B:$C,2,FALSE) -> TRUE | AF15: =IF(AND(AC15>=VLOOKUP(FLAT!$I$1,lists!$G:$H,2,FALSE),AC15<=VLOOKUP(FLAT!$I$2,lists!$G:$H,2,FALSE)),TRUE,FALSE) -> TRUE | AG15: =VLOOKUP(AB15,lists!$B$7:$C$8,2,FALSE) -> TRUE | AH15: =VLOOKUP(IF(H15="","Open",SUBSTITUTE(H15,"/Nov","")),lists!$B$27:$D$29,2,FALSE) -> TRUE | AI15: =IF(FLAT!$I$5="All",TRUE,IF(FLAT!$I$5=TEXT('Raw - F'!C15,"mmm"),TRUE,FALSE)) -> TRUE | AJ15: =VLOOKUP(L15,lists!B:C,2,FALSE) -> TRUE | AK15: =VLOOKUP(T15,lists!$B$23:$D$25,2,FALSE) -> TRUE | AL15: =IF(AND(AD15=TRUE,AE15=TRUE,AF15=TRUE,AG15=TRUE,AH15=TRUE,AI15=TRUE,AJ15=TRUE,AK15=TRUE),1,0) -> 1
A16: =IF(B16="",A15,B16+1) -> 16 | B16: =IF(AND(A15<1,AL16=1),1,IF(AL16=1,A15,"")) -> 15 | C16: 44317 | D16: NEWMARKET | E16: Flat | F16: Flat | G16: WFA | H16: Open | J16: 3yo | K16: C | L16: 1 | M16: 1(G1) | N16: Open | O16: 1m | P16: 1m | Q16: 375000 | R16: 2000 GUINEAS STKS | T16: Midlands | U16: 0 | AA16: =IF(OR(J16="2yo",J16="3yo"),J16,"Other") -> 3yo | AB16: =IF(K16="F",K16,"A") -> A | AC16: =VLOOKUP(P16,lists!$G:$H,2,FALSE) -> 4 | AD16: =VLOOKUP(G16,lists!$B$2:$C$3,2,FALSE) -> TRUE | AE16: =VLOOKUP(AA16,lists!$B:$C,2,FALSE) -> TRUE | AF16: =IF(AND(AC16>=VLOOKUP(FLAT!$I$1,lists!$G:$H,2,FALSE),AC16<=VLOOKUP(FLAT!$I$2,lists!$G:$H,2,FALSE)),TRUE,FALSE) -> TRUE | AG16: =VLOOKUP(AB16,lists!$B$7:$C$8,2,FALSE) -> TRUE | AH16: =VLOOKUP(IF(H16="","Open",SUBSTITUTE(H16,"/Nov","")),lists!$B$27:$D$29,2,FALSE) -> TRUE | AI16: =IF(FLAT!$I$5="All",TRUE,IF(FLAT!$I$5=TEXT('Raw - F'!C16,"mmm"),TRUE,FALSE)) -> TRUE | AJ16: =VLOOKUP(L16,lists!B:C,2,FALSE) -> TRUE | AK16: =VLOOKUP(T16,lists!$B$23:$D$25,2,FALSE) -> TRUE | AL16: =IF(AND(AD16=TRUE,AE16=TRUE,AF16=TRUE,AG16=TRUE,AH16=TRUE,AI16=TRUE,AJ16=TRUE,AK16=TRUE),1,0) -> 1
A17: =IF(B17="",A16,B17+1) -> 17 | B17: =IF(AND(A16<1,AL17=1),1,IF(AL17=1,A16,"")) -> 16 | C17: 44317 | D17: NEWMARKET | E17: Flat | F17: Flat | G17: WFA | H17: Open | J17: 4yo+ | K17: A | L17: 1 | M17: 1(G2) | N17: Open | O17: 1m4f | P17: 1m 4f | Q17: 75000 | R17: JOCKEY CLUB STKS | T17: Midlands | U17: 0 | AA17: =IF(OR(J17="2yo",J17="3yo"),J17,"Other") -> Other | AB17: =IF(K17="F",K17,"A") -> A | AC17: =VLOOKUP(P17,lists!$G:$H,2,FALSE) -> 7 | AD17: =VLOOKUP(G17,lists!$B$2:$C$3,2,FALSE) -> TRUE | AE17: =VLOOKUP(AA17,lists!$B:$C,2,FALSE) -> TRUE | AF17: =IF(AND(AC17>=VLOOKUP(FLAT!$I$1,lists!$G:$H,2,FALSE),AC17<=VLOOKUP(FLAT!$I$2,lists!$G:$H,2,FALSE)),TRUE,FALSE) -> TRUE | AG17: =VLOOKUP(AB17,lists!$B$7:$C$8,2,FALSE) -> TRUE | AH17: =VLOOKUP(IF(H17="","Open",SUBSTITUTE(H17,"/Nov","")),lists!$B$27:$D$29,2,FALSE) -> TRUE | AI17: =IF(FLAT!$I$5="All",TRUE,IF(FLAT!$I$5=TEXT('Raw - F'!C17,"mmm"),TRUE,FALSE)) -> TRUE | AJ17: =VLOOKUP(L17,lists!B:C,2,FALSE) -> TRUE | AK17: =VLOOKUP(T17,lists!$B$23:$D$25,2,FALSE) -> TRUE | AL17: =IF(AND(AD17=TRUE,AE17=TRUE,AF17=TRUE,AG17=TRUE,AH17=TRUE,AI17=TRUE,AJ17=TRUE,AK17=TRUE),1,0) -> 1
A18: =IF(B18="",A17,B18+1) -> 18 | B18: =IF(AND(A17<1,AL18=1),1,IF(AL18=1,A17,"")) -> 17 | C18: 44317 | D18: NEWMARKET | E18: Flat | F18: Flat | G18: WFA | H18: Open | J18: 3yo+ | K18: A | L18: 1 | M18: 1(G3) | N18: Open | O18: 5f | P18: 5f | Q18: 60000 | R18: PALACE HOUSE STKS | T18: Midlands | U18: 0 | AA18: =IF(OR(J18="2yo",J18="3yo"),J18,"Other") -> Other | AB18: =IF(K18="F",K18,"A") -> A | AC18: =VLOOKUP(P18,lists!$G:$H,2,FALSE) -> 1 | AD18: =VLOOKUP(G18,lists!$B$2:$C$3,2,FALSE) -> TRUE | AE18: =VLOOKUP(AA18,lists!$B:$C,2,FALSE) -> TRUE | AF18: =IF(AND(AC18>=VLOOKUP(FLAT!$I$1,lists!$G:$H,2,FALSE),AC18<=VLOOKUP(FLAT!$I$2,lists!$G:$H,2,FALSE)),TRUE,FALSE) -> TRUE | AG18: =VLOOKUP(AB18,lists!$B$7:$C$8,2,FALSE) -> TRUE | AH18: =VLOOKUP(IF(H18="","Open",SUBSTITUTE(H18,"/Nov","")),lists!$B$27:$D$29,2,FALSE) -> TRUE | AI18: =IF(FLAT!$I$5="All",TRUE,IF(FLAT!$I$5=TEXT('Raw - F'!C18,"mmm"),TRUE,FALSE)) -> TRUE | AJ18: =VLOOKUP(L18,lists!B:C,2,FALSE) -> TRUE | AK18: =VLOOKUP(T18,lists!$B$23:$D$25,2,FALSE) -> TRUE | AL18: =IF(AND(AD18=TRUE,AE18=TRUE,AF18=TRUE,AG18=TRUE,AH18=TRUE,AI18=TRUE,AJ18=TRUE,AK18=TRUE),1,0) -> 1
A19: =IF(B19="",A18,B19+1) -> 19 | B19: =IF(AND(A18<1,AL19=1),1,IF(AL19=1,A18,"")) -> 18 | C19: 44317 | D19: NEWMARKET | E19: Flat | F19: Flat | G19: WFA | H19: Open | J19: 3yo | K19: C | L19: 1 | M19: 1(Lstd) | N19: Open | O19: 1m2f | P19: 1m 2f | Q19: 50000 | R19: NEWMARKET STKS | T19: Midlands | U19: 0 | AA19: =IF(OR(J19="2yo",J19="3yo"),J19,"Other") -> 3yo | AB19: =IF(K19="F",K19,"A") -> A | AC19: =VLOOKUP(P19,lists!$G:$H,2,FALSE) -> 5 | AD19: =VLOOKUP(G19,lists!$B$2:$C$3,2,FALSE) -> TRUE | AE19: =VLOOKUP(AA19,lists!$B:$C,2,FALSE) -> TRUE | AF19: =IF(AND(AC19>=VLOOKUP(FLAT!$I$1,lists!$G:$H,2,FALSE),AC19<=VLOOKUP(FLAT!$I$2,lists!$G:$H,2,FALSE)),TRUE,FALSE) -> TRUE | AG19: =VLOOKUP(AB19,lists!$B$7:$C$8,2,FALSE) -> TRUE | AH19: =VLOOKUP(IF(H19="","Open",SUBSTITUTE(H19,"/Nov","")),lists!$B$27:$D$29,2,FALSE) -> TRUE | AI19: =IF(FLAT!$I$5="All",TRUE,IF(FLAT!$I$5=TEXT('Raw - F'!C19,"mmm"),TRUE,FALSE)) -> TRUE | AJ19: =VLOOKUP(L19,lists!B:C,2,FALSE) -> TRUE | AK19: =VLOOKUP(T19,lists!$B$23:$D$25,2,FALSE) -> TRUE | AL19: =IF(AND(AD19=TRUE,AE19=TRUE,AF19=TRUE,AG19=TRUE,AH19=TRUE,AI19=TRUE,AJ19=TRUE,AK19=TRUE),1,0) -> 1
A20: =IF(B20="",A19,B20+1) -> 20 | B20: =IF(AND(A19<1,AL20=1),1,IF(AL20=1,A19,"")) -> 19 | C20: 44317 | D20: NEWMARKET | E20: Flat | F20: Flat | G20: Hcap | H20: Open | J20: 3yo+ | K20: A | L20: 2 | N20: Open | O20: 1m1f | P20: 1m 1f | Q20: 50000 | R20: SUFFOLK HCAP STKS | T20: Midlands | U20: 0 | AA20: =IF(OR(J20="2yo",J20="3yo"),J20,"Other") -> Other | AB20: =IF(K20="F",K20,"A") -> A | AC20: =VLOOKUP(P20,lists!$G:$H,2,FALSE) -> 5 | AD20: =VLOOKUP(G20,lists!$B$2:$C$3,2,FALSE) -> TRUE | AE20: =VLOOKUP(AA20,lists!$B:$C,2,FALSE) -> TRUE | AF20: =IF(AND(AC20>=VLOOKUP(FLAT!$I$1,lists!$G:$H,2,FALSE),AC20<=VLOOKUP(FLAT!$I$2,lists!$G:$H,2,FALSE)),TRUE,FALSE) -> TRUE | AG20: =VLOOKUP(AB20,lists!$B$7:$C$8,2,FALSE) -> TRUE | AH20: =VLOOKUP(IF(H20="","Open",SUBSTITUTE(H20,"/Nov","")),lists!$B$27:$D$29,2,FALSE) -> TRUE | AI20: =IF(FLAT!$I$5="All",TRUE,IF(FLAT!$I$5=TEXT('Raw - F'!C20,"mmm"),TRUE,FALSE)) -> TRUE | AJ20: =VLOOKUP(L20,lists!B:C,2,FALSE) -> TRUE | AK20: =VLOOKUP(T20,lists!$B$23:$D$25,2,FALSE) -> TRUE | AL20: =IF(AND(AD20=TRUE,AE20=TRUE,AF20=TRUE,AG20=TRUE,AH20=TRUE,AI20=TRUE,AJ20=TRUE,AK20=TRUE),1,0) -> 1
A21: =IF(B21="",A20,B21+1) -> 21 | B21: =IF(AND(A20<1,AL21=1),1,IF(AL21=1,A20,"")) -> 20 | C21: 44317 | D21: NEWMARKET | E21: Flat | F21: Flat | G21: Hcap | H21: Open | J21: 4yo+ | K21: A | L21: 2 | N21: Open | O21: 6f | P21: 6f | Q21: 50000 | R21: DISCOVER HCAP STKS | T21: Midlands | U21: 0 | AA21: =IF(OR(J21="2yo",J21="3yo"),J21,"Other") -> Other | AB21: =IF(K21="F",K21,"A") -> A | AC21: =VLOOKUP(P21,lists!$G:$H,2,FALSE) -> 2 | AD21: =VLOOKUP(G21,lists!$B$2:$C$3,2,FALSE) -> TRUE | AE21: =VLOOKUP(AA21,lists!$B:$C,2,FALSE) -> TRUE | AF21: =IF(AND(AC21>=VLOOKUP(FLAT!$I$1,lists!$G:$H,2,FALSE),AC21<=VLOOKUP(FLAT!$I$2,lists!$G:$H,2,FALSE)),TRUE,FALSE) -> TRUE | AG21: =VLOOKUP(AB21,lists!$B$7:$C$8,2,FALSE) -> TRUE | AH21: =VLOOKUP(IF(H21="","Open",SUBSTITUTE(H21,"/Nov","")),lists!$B$27:$D$29,2,FALSE) -> TRUE | AI21: =IF(FLAT!$I$5="All",TRUE,IF(FLAT!$I$5=TEXT('Raw - F'!C21,"mmm"),TRUE,FALSE)) -> TRUE | AJ21: =VLOOKUP(L21,lists!B:C,2,FALSE) -> TRUE | AK21: =VLOOKUP(T21,lists!$B$23:$D$25,2,FALSE) -> TRUE | AL21: =IF(AND(AD21=TRUE,AE21=TRUE,AF21=TRUE,AG21=TRUE,AH21=TRUE,AI21=TRUE,AJ21=TRUE,AK21=TRUE),1,0) -> 1
A22: =IF(B22="",A21,B22+1) -> 22 | B22: =IF(AND(A21<1,AL22=1),1,IF(AL22=1,A21,"")) -> 21 | C22: 44317 | D22: NEWMARKET | E22: Flat | F22: Flat | G22: Hcap | H22: Open | J22: 3yo | K22: A | L22: 2 | N22: 81-100 | O22: 1m | P22: 1m | Q22: 25000 | R22: DISCOVER HCAP STKS | T22: Midlands | U22: 0 | AA22: =IF(OR(J22="2yo",J22="3yo"),J22,"Other") -> 3yo | AB22: =IF(K22="F",K22,"A") -> A | AC22: =VLOOKUP(P22,lists!$G:$H,2,FALSE) -> 4 | AD22: =VLOOKUP(G22,lists!$B$2:$C$3,2,FALSE) -> TRUE | AE22: =VLOOKUP(AA22,lists!$B:$C,2,FALSE) -> TRUE | AF22: =IF(AND(AC22>=VLOOKUP(FLAT!$I$1,lists!$G:$H,2,FALSE),AC22<=VLOOKUP(FLAT!$I$2,lists!$G:$H,2,FALSE)),TRUE,FALSE) -> TRUE | AG22: =VLOOKUP(AB22,lists!$B$7:$C$8,2,FALSE) -> TRUE | AH22: =VLOOKUP(IF(H22="","Open",SUBSTITUTE(H22,"/Nov","")),lists!$B$27:$D$29,2,FALSE) -> TRUE | AI22: =IF(FLAT!$I$5="All",TRUE,IF(FLAT!$I$5=TEXT('Raw - F'!C22,"mmm"),TRUE,FALSE)) -> TRUE | AJ22: =VLOOKUP(L22,lists!B:C,2,FALSE) -> TRUE | AK22: =VLOOKUP(T22,lists!$B$23:$D$25,2,FALSE) -> TRUE | AL22: =IF(AND(AD22=TRUE,AE22=TRUE,AF22=TRUE,AG22=TRUE,AH22=TRUE,AI22=TRUE,AJ22=TRUE,AK22=TRUE),1,0) -> 1
A23: =IF(B23="",A22,B23+1) -> 23 | B23: =IF(AND(A22<1,AL23=1),1,IF(AL23=1,A22,"")) -> 22 | C23: 44317 | D23: NEWMARKET | E23: Flat | F23: Flat | G23: Hcap | H23: Open | J23: 3yo | K23: A | L23: 2 | N23: 81-100 | O23: 6f | P23: 6f | Q23: 25000 | R23: HOME HCAP STKS | T23: Midlands | U23: 0 | AA23: =IF(OR(J23="2yo",J23="3yo"),J23,"Other") -> 3yo | AB23: =IF(K23="F",K23,"A") -> A | AC23: =VLOOKUP(P23,lists!$G:$H,2,FALSE) -> 2 | AD23: =VLOOKUP(G23,lists!$B$2:$C$3,2,FALSE) -> TRUE | AE23: =VLOOKUP(AA23,lists!$B:$C,2,FALSE) -> TRUE | AF23: =IF(AND(AC23>=VLOOKUP(FLAT!$I$1,lists!$G:$H,2,FALSE),AC23<=VLOOKUP(FLAT!$I$2,lists!$G:$H,2,FALSE)),TRUE,FALSE) -> TRUE | AG23: =VLOOKUP(AB23,lists!$B$7:$C$8,2,FALSE) -> TRUE | AH23: =VLOOKUP(IF(H23="","Open",SUBSTITUTE(H23,"/Nov","")),lists!$B$27:$D$29,2,FALSE) -> TRUE | AI23: =IF(FLAT!$I$5="All",TRUE,IF(FLAT!$I$5=TEXT('Raw - F'!C23,"mmm"),TRUE,FALSE)) -> TRUE | AJ23: =VLOOKUP(L23,lists!B:C,2,FALSE) -> TRUE | AK23: =VLOOKUP(T23,lists!$B$23:$D$25,2,FALSE) -> TRUE | AL23: =IF(AND(AD23=TRUE,AE23=TRUE,AF23=TRUE,AG23=TRUE,AH23=TRUE,AI23=TRUE,AJ23=TRUE,AK23=TRUE),1,0) -> 1
A24: =IF(B24="",A23,B24+1) -> 24 | B24: =IF(AND(A23<1,AL24=1),1,IF(AL24=1,A23,"")) -> 23 | C24: 44317 | D24: THIRSK | E24: Flat | F24: Flat | G24: Hcap | H24: Open | J24: 4yo+ | K24: A | L24: 2 | N24: 81-100 | O24: 7f218y | P24: 1m | Q24: 30000 | R24: HUNT CUP HCAP STKS | T24: North | U24: 0 | AA24: =IF(OR(J24="2yo",J24="3yo"),J24,"Other") -> Other | AB24: =IF(K24="F",K24,"A") -> A | AC24: =VLOOKUP(P24,lists!$G:$H,2,FALSE) -> 4 | AD24: =VLOOKUP(G24,lists!$B$2:$C$3,2,FALSE) -> TRUE | AE24: =VLOOKUP(AA24,lists!$B:$C,2,FALSE) -> TRUE | AF24: =IF(AND(AC24>=VLOOKUP(FLAT!$I$1,lists!$G:$H,2,FALSE),AC24<=VLOOKUP(FLAT!$I$2,lists!$G:$H,2,FALSE)),TRUE,FALSE) -> TRUE | AG24: =VLOOKUP(AB24,lists!$B$7:$C$8,2,FALSE) -> TRUE | AH24: =VLOOKUP(IF(H24="","Open",SUBSTITUTE(H24,"/Nov","")),lists!$B$27:$D$29,2,FALSE) -> TRUE | AI24: =IF(FLAT!$I$5="All",TRUE,IF(FLAT!$I$5=TEXT('Raw - F'!C24,"mmm"),TRUE,FALSE)) -> TRUE | AJ24: =VLOOKUP(L24,lists!B:C,2,FALSE) -> TRUE | AK24: =VLOOKUP(T24,lists!$B$23:$D$25,2,FALSE) -> TRUE | AL24: =IF(AND(AD24=TRUE,AE24=TRUE,AF24=TRUE,AG24=TRUE,AH24=TRUE,AI24=TRUE,AJ24=TRUE,AK24=TRUE),1,0) -> 1
A25: =IF(B25="",A24,B25+1) -> 25 | B25: =IF(AND(A24<1,AL25=1),1,IF(AL25=1,A24,"")) -> 24 | C25: 44317 | D25: THIRSK | E25: Flat | F25: Flat | G25: Hcap | H25: Open | J25: 4yo+ | K25: A | L25: 4 | N25: 61-80 | O25: 6f | P25: 6f | Q25: 7650 | R25: GLAMPING HCAP STKS | T25: North | U25: 0 | AA25: =IF(OR(J25="2yo",J25="3yo"),J25,"Other") -> Other | AB25: =IF(K25="F",K25,"A") -> A | AC25: =VLOOKUP(P25,lists!$G:$H,2,FALSE) -> 2 | AD25: =VLOOKUP(G25,lists!$B$2:$C$3,2,FALSE) -> TRUE | AE25: =VLOOKUP(AA25,lists!$B:$C,2,FALSE) -> TRUE | AF25: =IF(AND(AC25>=VLOOKUP(FLAT!$I$1,lists!$G:$H,2,FALSE),AC25<=VLOOKUP(FLAT!$I$2,lists!$G:$H,2,FALSE)),TRUE,FALSE) -> TRUE | AG25: =VLOOKUP(AB25,lists!$B$7:$C$8,2,FALSE) -> TRUE | AH25: =VLOOKUP(IF(H25="","Open",SUBSTITUTE(H25,"/Nov","")),lists!$B$27:$D$29,2,FALSE) -> TRUE | AI25: =IF(FLAT!$I$5="All",TRUE,IF(FLAT!$I$5=TEXT('Raw - F'!C25,"mmm"),TRUE,FALSE)) -> TRUE | AJ25: =VLOOKUP(L25,lists!B:C,2,FALSE) -> TRUE | AK25: =VLOOKUP(T25,lists!$B$23:$D$25,2,FALSE) -> TRUE | AL25: =IF(AND(AD25=TRUE,AE25=TRUE,AF25=TRUE,AG25=TRUE,AH25=TRUE,AI25=TRUE,AJ25=TRUE,AK25=TRUE),1,0) -> 1
A26: =IF(B26="",A25,B26+1) -> 26 | B26: =IF(AND(A25<1,AL26=1),1,IF(AL26=1,A25,"")) -> 25 | C26: 44317 | D26: THIRSK | E26: Flat | F26: Flat | G26: Hcap | H26: Open | J26: 3yo+ | K26: A | L26: 4 | N26: 66-85 | O26: 5f | P26: 5f | Q26: 7650 | R26: FRANKEL HCAP STKS | T26: North | U26: 0 | AA26: =IF(OR(J26="2yo",J26="3yo"),J26,"Other") -> Other | AB26: =IF(K26="F",K26,"A") -> A | AC26: =VLOOKUP(P26,lists!$G:$H,2,FALSE) -> 1 | AD26: =VLOOKUP(G26,lists!$B$2:$C$3,2,FALSE) -> TRUE | AE26: =VLOOKUP(AA26,lists!$B:$C,2,FALSE) -> TRUE | AF26: =IF(AND(AC26>=VLOOKUP(FLAT!$I$1,lists!$G:$H,2,FALSE),AC26<=VLOOKUP(FLAT!$I$2,lists!$G:$H,2,FALSE)),TRUE,FALSE) -> TRUE | AG26: =VLOOKUP(AB26,lists!$B$7:$C$8,2,FALSE) -> TRUE | AH26: =VLOOKUP(IF(H26="","Open",SUBSTITUTE(H26,"/Nov","")),lists!$B$27:$D$29,2,FALSE) -> TRUE | AI26: =IF(FLAT!$I$5="All",TRUE,IF(FLAT!$I$5=TEXT('Raw - F'!C26,"mmm"),TRUE,FALSE)) -> TRUE | AJ26: =VLOOKUP(L26,lists!B:C,2,FALSE) -> TRUE | AK26: =VLOOKUP(T26,lists!$B$23:$D$25,2,FALSE) -> TRUE | AL26: =IF(AND(AD26=TRUE,AE26=TRUE,AF26=TRUE,AG26=TRUE,AH26=TRUE,AI26=TRUE,AJ26=TRUE,AK26=TRUE),1,0) -> 1
A27: =IF(B27="",A26,B27+1) -> 27 | B27: =IF(AND(A26<1,AL27=1),1,IF(AL27=1,A26,"")) -> 26 | C27: 44317 | D27: THIRSK | E27: Flat | F27: Flat | G27: WFA | H27: Mdn | J27: 3yo+ | K27: F | L27: 4 | N27: Open | O27: 7f | P27: 7f | Q27: 7650 | R27: STUDS EBF MDN STKS | T27: North | U27: 0 | Z27: EBF | AA27: =IF(OR(J27="2yo",J27="3yo"),J27,"Other") -> Other | AB27: =IF(K27="F",K27,"A") -> F | AC27: =VLOOKUP(P27,lists!$G:$H,2,FALSE) -> 3 | AD27: =VLOOKUP(G27,lists!$B$2:$C$3,2,FALSE) -> TRUE | AE27: =VLOOKUP(AA27,lists!$B:$C,2,FALSE) -> TRUE | AF27: =IF(AND(AC27>=VLOOKUP(FLAT!$I$1,lists!$G:$H,2,FALSE),AC27<=VLOOKUP(FLAT!$I$2,lists!$G:$H,2,FALSE)),TRUE,FALSE) -> TRUE | AG27: =VLOOKUP(AB27,lists!$B$7:$C$8,2,FALSE) -> TRUE | AH27: =VLOOKUP(IF(H27="","Open",SUBSTITUTE(H27,"/Nov","")),lists!$B$27:$D$29,2,FALSE) -> TRUE | AI27: =IF(FLAT!$I$5="All",TRUE,IF(FLAT!$I$5=TEXT('Raw - F'!C27,"mmm"),TRUE,FALSE)) -> TRUE | AJ27: =VLOOKUP(L27,lists!B:C,2,FALSE) -> TRUE | AK27: =VLOOKUP(T27,lists!$B$23:$D$25,2,FALSE) -> TRUE | AL27: =IF(AND(AD27=TRUE,AE27=TRUE,AF27=TRUE,AG27=TRUE,AH27=TRUE,AI27=TRUE,AJ27=TRUE,AK27=TRUE),1,0) -> 1
A28: =IF(B28="",A27,B28+1) -> 28 | B28: =IF(AND(A27<1,AL28=1),1,IF(AL28=1,A27,"")) -> 27 | C28: 44317 | D28: THIRSK | E28: Flat | F28: Flat | G28: Hcap | H28: Open | J28: 3yo+ | K28: A | L28: 5 | N28: 51-70 | O28: 7f218y | P28: 1m | Q28: 5400 | R28: CLIFF STUD HCAP STKS | T28: North | U28: 0 | AA28: =IF(OR(J28="2yo",J28="3yo"),J28,"Other") -> Other | AB28: =IF(K28="F",K28,"A") -> A | AC28: =VLOOKUP(P28,lists!$G:$H,2,FALSE) -> 4 | AD28: =VLOOKUP(G28,lists!$B$2:$C$3,2,FALSE) -> TRUE | AE28: =VLOOKUP(AA28,lists!$B:$C,2,FALSE) -> TRUE | AF28: =IF(AND(AC28>=VLOOKUP(FLAT!$I$1,lists!$G:$H,2,FALSE),AC28<=VLOOKUP(FLAT!$I$2,lists!$G:$H,2,FALSE)),TRUE,FALSE) -> TRUE | AG28: =VLOOKUP(AB28,lists!$B$7:$C$8,2,FALSE) -> TRUE | AH28: =VLOOKUP(IF(H28="","Open",SUBSTITUTE(H28,"/Nov","")),lists!$B$27:$D$29,2,FALSE) -> TRUE | AI28: =IF(FLAT!$I$5="All",TRUE,IF(FLAT!$I$5=TEXT('Raw - F'!C28,"mmm"),TRUE,FALSE)) -> TRUE | AJ28: =VLOOKUP(L28,lists!B:C,2,FALSE) -> TRUE | AK28: =VLOOKUP(T28,lists!$B$23:$D$25,2,FALSE) -> TRUE | AL28: =IF(AND(AD28=TRUE,AE28=TRUE,AF28=TRUE,AG28=TRUE,AH28=TRUE,AI28=TRUE,AJ28=TRUE,AK28=TRUE),1,0) -> 1
A29: =IF(B29="",A28,B29+1) -> 29 | B29: =IF(AND(A28<1,AL29=1),1,IF(AL29=1,A28,"")) -> 28 | C29: 44317 | D29: THIRSK | E29: Flat | F29: Flat | G29: Hcap | H29: Open | J29: 4yo+ | K29: A | L29: 5 | N29: 51-70 | O29: 1m6f | P29: 1m 6f | Q29: 5400 | R29: CECIL HCAP STKS | T29: North | U29: 0 | AA29: =IF(OR(J29="2yo",J29="3yo"),J29,"Other") -> Other | AB29: =IF(K29="F",K29,"A") -> A | AC29: =VLOOKUP(P29,lists!$G:$H,2,FALSE) -> 9 | AD29: =VLOOKUP(G29,lists!$B$2:$C$3,2,FALSE) -> TRUE | AE29: =VLOOKUP(AA29,lists!$B:$C,2,FALSE) -> TRUE | AF29: =IF(AND(AC29>=VLOOKUP(FLAT!$I$1,lists!$G:$H,2,FALSE),AC29<=VLOOKUP(FLAT!$I$2,lists!$G:$H,2,FALSE)),TRUE,FALSE) -> TRUE | AG29: =VLOOKUP(AB29,lists!$B$7:$C$8,2,FALSE) -> TRUE | AH29: =VLOOKUP(IF(H29="","Open",SUBSTITUTE(H29,"/Nov","")),lists!$B$27:$D$29,2,FALSE) -> TRUE | AI29: =IF(FLAT!$I$5="All",TRUE,IF(FLAT!$I$5=TEXT('Raw - F'!C29,"mmm"),TRUE,FALSE)) -> TRUE | AJ29: =VLOOKUP(L29,lists!B:C,2,FALSE) -> TRUE | AK29: =VLOOKUP(T29,lists!$B$23:$D$25,2,FALSE) -> TRUE | AL29: =IF(AND(AD29=TRUE,AE29=TRUE,AF29=TRUE,AG29=TRUE,AH29=TRUE,AI29=TRUE,AJ29=TRUE,AK29=TRUE),1,0) -> 1
A30: =IF(B30="",A29,B30+1) -> 30 | B30: =IF(AND(A29<1,AL30=1),1,IF(AL30=1,A29,"")) -> 29 | C30: 44317 | D30: THIRSK | E30: Flat | F30: Flat | G30: WFA | H30: Nov | J30: 2yo | K30: A | L30: 5 | N30: Open | O30: 5f | P30: 5f | Q30: 5000 | R30: CLIFF STUD NOV STKS | T30: North | U30: 0 | X30: Rest. | Y30: B | AA30: =IF(OR(J30="2yo",J30="3yo"),J30,"Other") -> 2yo | AB30: =IF(K30="F",K30,"A") -> A | AC30: =VLOOKUP(P30,lists!$G:$H,2,FALSE) -> 1 | AD30: =VLOOKUP(G30,lists!$B$2:$C$3,2,FALSE) -> TRUE | AE30: =VLOOKUP(AA30,lists!$B:$C,2,FALSE) -> TRUE | AF30: =IF(AND(AC30>=VLOOKUP(FLAT!$I$1,lists!$G:$H,2,FALSE),AC30<=VLOOKUP(FLAT!$I$2,lists!$G:$H,2,FALSE)),TRUE,FALSE) -> TRUE | AG30: =VLOOKUP(AB30,lists!$B$7:$C$8,2,FALSE) -> TRUE | AH30: =VLOOKUP(IF(H30="","Open",SUBSTITUTE(H30,"/Nov","")),lists!$B$27:$D$29,2,FALSE) -> TRUE | AI30: =IF(FLAT!$I$5="All",TRUE,IF(FLAT!$I$5=TEXT('Raw - F'!C30,"mmm"),TRUE,FALSE)) -> TRUE | AJ30: =VLOOKUP(L30,lists!B:C,2,FALSE) -> TRUE | AK30: =VLOOKUP(T30,lists!$B$23:$D$25,2,FALSE) -> TRUE | AL30: =IF(AND(AD30=TRUE,AE30=TRUE,AF30=TRUE,AG30=TRUE,AH30=TRUE,AI30=TRUE,AJ30=TRUE,AK30=TRUE),1,0) -> 1
A31: =IF(B31="",A30,B31+1) -> 31 | B31: =IF(AND(A30<1,AL31=1),1,IF(AL31=1,A30,"")) -> 30 | C31: 44318 | D31: HAMILTON PARK | E31: Flat | F31: Flat | G31: WFA | H31: Open | I31: Conditions | J31: 3yo | K31: A | L31: 2 | N31: Open | O31: 5f7y | P31: 5f | Q31: 32000 | R31: TANGERINE TREES EBF STKS | T31: North | U31: 0 | Z31: EBF | AA31: =IF(OR(J31="2yo",J31="3yo"),J31,"Other") -> 3yo | AB31: =IF(K31="F",K31,"A") -> A | AC31: =VLOOKUP(P31,lists!$G:$H,2,FALSE) -> 1 | AD31: =VLOOKUP(G31,lists!$B$2:$C$3,2,FALSE) -> TRUE | AE31: =VLOOKUP(AA31,lists!$B:$C,2,FALSE) -> TRUE | AF31: =IF(AND(AC31>=VLOOKUP(FLAT!$I$1,lists!$G:$H,2,FALSE),AC31<=VLOOKUP(FLAT!$I$2,lists!$G:$H,2,FALSE)),TRUE,FALSE) -> TRUE | AG31: =VLOOKUP(AB31,lists!$B$7:$C$8,2,FALSE) -> TRUE | AH31: =VLOOKUP(IF(H31="","Open",SUBSTITUTE(H31,"/Nov","")),lists!$B$27:$D$29,2,FALSE) -> TRUE | AI31: =IF(FLAT!$I$5="All",TRUE,IF(FLAT!$I$5=TEXT('Raw - F'!C31,"mmm"),TRUE,FALSE)) -> TRUE | AJ31: =VLOOKUP(L31,lists!B:C,2,FALSE) -> TRUE | AK31: =VLOOKUP(T31,lists!$B$23:$D$25,2,FALSE) -> TRUE | AL31: =IF(AND(AD31=TRUE,AE31=TRUE,AF31=TRUE,AG31=TRUE,AH31=TRUE,AI31=TRUE,AJ31=TRUE,AK31=TRUE),1,0) -> 1
A32: =IF(B32="",A31,B32+1) -> 32 | B32: =IF(AND(A31<1,AL32=1),1,IF(AL32=1,A31,"")) -> 31 | C32: 44318 | D32: HAMILTON PARK | E32: Flat | F32: Flat | G32: Hcap | H32: Open | J32: 4yo+ | K32: A | L32: 3 | N32: 76-95 | O32: 1m5f16y | P32: 1m 5f | Q32: 30000 | R32: BUTTONHOOK HCAP STKS | T32: North | U32: 0 | AA32: =IF(OR(J32="2yo",J32="3yo"),J32,"Other") -> Other | AB32: =IF(K32="F",K32,"A") -> A | AC32: =VLOOKUP(P32,lists!$G:$H,2,FALSE) -> 8 | AD32: =VLOOKUP(G32,lists!$B$2:$C$3,2,FALSE) -> TRUE | AE32: =VLOOKUP(AA32,lists!$B:$C,2,FALSE) -> TRUE | AF32: =IF(AND(AC32>=VLOOKUP(FLAT!$I$1,lists!$G:$H,2,FALSE),AC32<=VLOOKUP(FLAT!$I$2,lists!$G:$H,2,FALSE)),TRUE,FALSE) -> TRUE | AG32: =VLOOKUP(AB32,lists!$B$7:$C$8,2,FALSE) -> TRUE | AH32: =VLOOKUP(IF(H32="","Open",SUBSTITUTE(H32,"/Nov","")),lists!$B$27:$D$29,2,FALSE) -> TRUE | AI32: =IF(FLAT!$I$5="All",TRUE,IF(FLAT!$I$5=TEXT('Raw - F'!C32,"mmm"),TRUE,FALSE)) -> TRUE | AJ32: =VLOOKUP(L32,lists!B:C,2,FALSE) -> TRUE | AK32: =VLOOKUP(T32,lists!$B$23:$D$25,2,FALSE) -> TRUE | AL32: =IF(AND(AD32=TRUE,AE32=TRUE,AF32=TRUE,AG32=TRUE,AH32=TRUE,AI32=TRUE,AJ32=TRUE,AK32=TRUE),1,0) -> 1
A33: =IF(B33="",A32,B33+1) -> 33 | B33: =IF(AND(A32<1,AL33=1),1,IF(AL33=1,A32,"")) -> 32 | C33: 44318 | D33: HAMILTON PARK | E33: Flat | F33: Flat | G33: Hcap | H33: Open | J33: 4yo+ | K33: A | L33: 4 | N33: 66-85 | O33: 1m68y | P33: 1m | Q33: 10000 | R33: WINDOW BLINDS HCAP | T33: North | U33: 0 | AA33: =IF(OR(J33="2yo",J33="3yo"),J33,"Other") -> Other | AB33: =IF(K33="F",K33,"A") -> A | AC33: =VLOOKUP(P33,lists!$G:$H,2,FALSE) -> 4 | AD33: =VLOOKUP(G33,lists!$B$2:$C$3,2,FALSE) -> TRUE | AE33: =VLOOKUP(AA33,lists!$B:$C,2,FALSE) -> TRUE | AF33: =IF(AND(AC33>=VLOOKUP(FLAT!$I$1,lists!$G:$H,2,FALSE),AC33<=VLOOKUP(FLAT!$I$2,lists!$G:$H,2,FALSE)),TRUE,FALSE) -> TRUE | AG33: =VLOOKUP(AB33,lists!$B$7:$C$8,2,FALSE) -> TRUE | AH33: =VLOOKUP(IF(H33="","Open",SUBSTITUTE(H33,"/Nov","")),lists!$B$27:$D$29,2,FALSE) -> TRUE | AI33: =IF(FLAT!$I$5="All",TRUE,IF(FLAT!$I$5=TEXT('Raw - F'!C33,"mmm"),TRUE,FALSE)) -> TRUE | AJ33: =VLOOKUP(L33,lists!B:C,2,FALSE) -> TRUE | AK33: =VLOOKUP(T33,lists!$B$23:$D$25,2,FALSE) -> TRUE | AL33: =IF(AND(AD33=TRUE,AE33=TRUE,AF33=TRUE,AG33=TRUE,AH33=TRUE,AI33=TRUE,AJ33=TRUE,AK33=TRUE),1,0) -> 1
A34: =IF(B34="",A33,B34+1) -> 34 | B34: =IF(AND(A33<1,AL34=1),1,IF(AL34=1,A33,"")) -> 33 | C34: 44318 | D34: HAMILTON PARK | E34: Flat | F34: Flat | G34: WFA | H34: Mdn | J34: 3yo+ | K34: A | L34: 5 | N34: Open | O34: 1m68y | P34: 1m | Q34: 7000 | R34: SKY 426 MDN STKS | T34: North | U34: 0 | AA34: =IF(OR(J34="2yo",J34="3yo"),J34,"Other") -> Other | AB34: =IF(K34="F",K34,"A") -> A | AC34: =VLOOKUP(P34,lists!$G:$H,2,FALSE) -> 4 | AD34: =VLOOKUP(G34,lists!$B$2:$C$3,2,FALSE) -> TRUE | AE34: =VLOOKUP(AA34,lists!$B:$C,2,FALSE) -> TRUE | AF34: =IF(AND(AC34>=VLOOKUP(FLAT!$I$1,lists!$G:$H,2,FALSE),AC34<=VLOOKUP(FLAT!$I$2,lists!$G:$H,2,FALSE)),TRUE,FALSE) -> TRUE | AG34: =VLOOKUP(AB34,lists!$B$7:$C$8,2,FALSE) -> TRUE | AH34: =VLOOKUP(IF(H34="","Open",SUBSTITUTE(H34,"/Nov","")),lists!$B$27:$D$29,2,FALSE) -> TRUE | AI34: =IF(FLAT!$I$5="All",TRUE,IF(FLAT!$I$5=TEXT('Raw - F'!C34,"mmm"),TRUE,FALSE)) -> TRUE | AJ34: =VLOOKUP(L34,lists!B:C,2,FALSE) -> TRUE | AK34: =VLOOKUP(T34,lists!$B$23:$D$25,2,FALSE) -> TRUE | AL34: =IF(AND(AD34=TRUE,AE34=TRUE,AF34=TRUE,AG34=TRUE,AH34=TRUE,AI34=TRUE,AJ34=TRUE,AK34=TRUE),1,0) -> 1
A35: =IF(B35="",A34,B35+1) -> 35 | B35: =IF(AND(A34<1,AL35=1),1,IF(AL35=1,A34,"")) -> 34 | C35: 44318 | D35: HAMILTON PARK | E35: Flat | F35: Flat | G35: Hcap | H35: Open | J35: 4yo+ | K35: A | L35: 5 | N35: 51-70 | O35: 5f7y | P35: 5f | Q35: 7000 | R35: TOP CAT HCAP STKS | T35: North | U35: 0 | AA35: =IF(OR(J35="2yo",J35="3yo"),J35,"Other") -> Other | AB35: =IF(K35="F",K35,"A") -> A | AC35: =VLOOKUP(P35,lists!$G:$H,2,FALSE) -> 1 | AD35: =VLOOKUP(G35,lists!$B$2:$C$3,2,FALSE) -> TRUE | AE35: =VLOOKUP(AA35,lists!$B:$C,2,FALSE) -> TRUE | AF35: =IF(AND(AC35>=VLOOKUP(FLAT!$I$1,lists!$G:$H,2,FALSE),AC35<=VLOOKUP(FLAT!$I$2,lists!$G:$H,2,FALSE)),TRUE,FALSE) -> TRUE | AG35: =VLOOKUP(AB35,lists!$B$7:$C$8,2,FALSE) -> TRUE | AH35: =VLOOKUP(IF(H35="","Open",SUBSTITUTE(H35,"/Nov","")),lists!$B$27:$D$29,2,FALSE) -> TRUE | AI35: =IF(FLAT!$I$5="All",TRUE,IF(FLAT!$I$5=TEXT('Raw - F'!C35,"mmm"),TRUE,FALSE)) -> TRUE | AJ35: =VLOOKUP(L35,lists!B:C,2,FALSE) -> TRUE | AK35: =VLOOKUP(T35,lists!$B$23:$D$25,2,FALSE) -> TRUE | AL35: =IF(AND(AD35=TRUE,AE35=TRUE,AF35=TRUE,AG35=TRUE,AH35=TRUE,AI35=TRUE,AJ35=TRUE,AK35=TRUE),1,0) -> 1
A36: =IF(B36="",A35,B36+1) -> 36 | B36: =IF(AND(A35<1,AL36=1),1,IF(AL36=1,A35,"")) -> 35 | C36: 44318 | D36: HAMILTON PARK | E36: Flat | F36: Flat | G36: Hcap | H36: Open | J36: 4yo+ | K36: A | L36: 5 | N36: 51-70 | O36: 6f6y | P36: 6f | Q36: 7000 | R36: RTV PROFITS HCP STKS | T36: North | U36: 0 | AA36: =IF(OR(J36="2yo",J36="3yo"),J36,"Other") -> Other | AB36: =IF(K36="F",K36,"A") -> A | AC36: =VLOOKUP(P36,lists!$G:$H,2,FALSE) -> 2 | AD36: =VLOOKUP(G36,lists!$B$2:$C$3,2,FALSE) -> TRUE | AE36: =VLOOKUP(AA36,lists!$B:$C,2,FALSE) -> TRUE | AF36: =IF(AND(AC36>=VLOOKUP(FLAT!$I$1,lists!$G:$H,2,FALSE),AC36<=VLOOKUP(FLAT!$I$2,lists!$G:$H,2,FALSE)),TRUE,FALSE) -> TRUE | AG36: =VLOOKUP(AB36,lists!$B$7:$C$8,2,FALSE) -> TRUE | AH36: =VLOOKUP(IF(H36="","Open",SUBSTITUTE(H36,"/Nov","")),lists!$B$27:$D$29,2,FALSE) -> TRUE | AI36: =IF(FLAT!$I$5="All",TRUE,IF(FLAT!$I$5=TEXT('Raw - F'!C36,"mmm"),TRUE,FALSE)) -> TRUE | AJ36: =VLOOKUP(L36,lists!B:C,2,FALSE) -> TRUE | AK36: =VLOOKUP(T36,lists!$B$23:$D$25,2,FALSE) -> TRUE | AL36: =IF(AND(AD36=TRUE,AE36=TRUE,AF36=TRUE,AG36=TRUE,AH36=TRUE,AI36=TRUE,AJ36=TRUE,AK36=TRUE),1,0) -> 1
A37: =IF(B37="",A36,B37+1) -> 37 | B37: =IF(AND(A36<1,AL37=1),1,IF(AL37=1,A36,"")) -> 36 | C37: 44318 | D37: HAMILTON PARK | E37: Flat | F37: Flat | G37: Hcap | H37: Open | J37: 4yo+ | K37: A | L37: 5 | N37: 51-70 | O37: 1m3f15y | P37: 1m 3f | Q37: 7000 | R37: TWITTER HCAP STKS | T37: North | U37: 0 | AA37: =IF(OR(J37="2yo",J37="3yo"),J37,"Other") -> Other | AB37: =IF(K37="F",K37,"A") -> A | AC37: =VLOOKUP(P37,lists!$G:$H,2,FALSE) -> 6 | AD37: =VLOOKUP(G37,lists!$B$2:$C$3,2,FALSE) -> TRUE | AE37: =VLOOKUP(AA37,lists!$B:$C,2,FALSE) -> TRUE | AF37: =IF(AND(AC37>=VLOOKUP(FLAT!$I$1,lists!$G:$H,2,FALSE),AC37<=VLOOKUP(FLAT!$I$2,lists!$G:$H,2,FALSE)),TRUE,FALSE) -> TRUE | AG37: =VLOOKUP(AB37,lists!$B$7:$C$8,2,FALSE) -> TRUE | AH37: =VLOOKUP(IF(H37="","Open",SUBSTITUTE(H37,"/Nov","")),lists!$B$27:$D$29,2,FALSE) -> TRUE | AI37: =IF(FLAT!$I$5="All",TRUE,IF(FLAT!$I$5=TEXT('Raw - F'!C37,"mmm"),TRUE,FALSE)) -> TRUE | AJ37: =VLOOKUP(L37,lists!B:C,2,FALSE) -> TRUE | AK37: =VLOOKUP(T37,lists!$B$23:$D$25,2,FALSE) -> TRUE | AL37: =IF(AND(AD37=TRUE,AE37=TRUE,AF37=TRUE,AG37=TRUE,AH37=TRUE,AI37=TRUE,AJ37=TRUE,AK37=TRUE),1,0) -> 1
A38: =IF(B38="",A37,B38+1) -> 38 | B38: =IF(AND(A37<1,AL38=1),1,IF(AL38=1,A37,"")) -> 37 | C38: 44318 | D38: NEWMARKET | E38: Flat | F38: Flat | G38: WFA | H38: Open | J38: 3yo | K38: F | L38: 1 | M38: 1(G1) | N38: Open | O38: 1m | P38: 1m | Q38: 375000 | R38: 1000 GUINEAS STKS | T38: Midlands | U38: 0 | AA38: =IF(OR(J38="2yo",J38="3yo"),J38,"Other") -> 3yo | AB38: =IF(K38="F",K38,"A") -> F | AC38: =VLOOKUP(P38,lists!$G:$H,2,FALSE) -> 4 | AD38: =VLOOKUP(G38,lists!$B$2:$C$3,2,FALSE) -> TRUE | AE38: =VLOOKUP(AA38,lists!$B:$C,2,FALSE) -> TRUE | AF38: =IF(AND(AC38>=VLOOKUP(FLAT!$I$1,lists!$G:$H,2,FALSE),AC38<=VLOOKUP(FLAT!$I$2,lists!$G:$H,2,FALSE)),TRUE,FALSE) -> TRUE | AG38: =VLOOKUP(AB38,lists!$B$7:$C$8,2,FALSE) -> TRUE | AH38: =VLOOKUP(IF(H38="","Open",SUBSTITUTE(H38,"/Nov","")),lists!$B$27:$D$29,2,FALSE) -> TRUE | AI38: =IF(FLAT!$I$5="All",TRUE,IF(FLAT!$I$5=TEXT('Raw - F'!C38,"mmm"),TRUE,FALSE)) -> TRUE | AJ38: =VLOOKUP(L38,lists!B:C,2,FALSE) -> TRUE | AK38: =VLOOKUP(T38,lists!$B$23:$D$25,2,FALSE) -> TRUE | AL38: =IF(AND(AD38=TRUE,AE38=TRUE,AF38=TRUE,AG38=TRUE,AH38=TRUE,AI38=TRUE,AJ38=TRUE,AK38=TRUE),1,0) -> 1
A39: =IF(B39="",A38,B39+1) -> 39 | B39: =IF(AND(A38<1,AL39=1),1,IF(AL39=1,A38,"")) -> 38 | C39: 44318 | D39: NEWMARKET | E39: Flat | F39: Flat | G39: WFA | H39: Open | J39: 4yo+ | K39: F | L39: 1 | M39: 1(G2) | N39: Open | O39: 1m1f | P39: 1m 1f | Q39: 75000 | R39: DAHLIA STKS | T39: Midlands | U39: 0 | AA39: =IF(OR(J39="2yo",J39="3yo"),J39,"Other") -> Other | AB39: =IF(K39="F",K39,"A") -> F | AC39: =VLOOKUP(P39,lists!$G:$H,2,FALSE) -> 5 | AD39: =VLOOKUP(G39,lists!$B$2:$C$3,2,FALSE) -> TRUE | AE39: =VLOOKUP(AA39,lists!$B:$C,2,FALSE) -> TRUE | AF39: =IF(AND(AC39>=VLOOKUP(FLAT!$I$1,lists!$G:$H,2,FALSE),AC39<=VLOOKUP(FLAT!$I$2,lists!$G:$H,2,FALSE)),TRUE,FALSE) -> TRUE | AG39: =VLOOKUP(AB39,lists!$B$7:$C$8,2,FALSE) -> TRUE | AH39: =VLOOKUP(IF(H39="","Open",SUBSTITUTE(H39,"/Nov","")),lists!$B$27:$D$29,2,FALSE) -> TRUE | AI39: =IF(FLAT!$I$5="All",TRUE,IF(FLAT!$I$5=TEXT('Raw - F'!C39,"mmm"),TRUE,FALSE)) -> TRUE | AJ39: =VLOOKUP(L39,lists!B:C,2,FALSE) -> TRUE | AK39: =VLOOKUP(T39,lists!$B$23:$D$25,2,FALSE) -> TRUE | AL39: =IF(AND(AD39=TRUE,AE39=TRUE,AF39=TRUE,AG39=TRUE,AH39=TRUE,AI39=TRUE,AJ39=TRUE,AK39=TRUE),1,0) -> 1
A40: =IF(B40="",A39,B40+1) -> 40 | B40: =IF(AND(A39<1,AL40=1),1,IF(AL40=1,A39,"")) -> 39 | C40: 44318 | D40: NEWMARKET | E40: Flat | F40: Flat | G40: WFA | H40: Open | J40: 3yo | K40: F | L40: 1 | M40: 1(Lstd) | N40: Open | O40: 1m2f | P40: 1m 2f | Q40: 50000 | R40: PRETTY POLLY STKS | T40: Midlands | U40: 0 | AA40: =IF(OR(J40="2yo",J40="3yo"),J40,"Other") -> 3yo | AB40: =IF(K40="F",K40,"A") -> F | AC40: =VLOOKUP(P40,lists!$G:$H,2,FALSE) -> 5 | AD40: =VLOOKUP(G40,lists!$B$2:$C$3,2,FALSE) -> TRUE | AE40: =VLOOKUP(AA40,lists!$B:$C,2,FALSE) -> TRUE | AF40: =IF(AND(AC40>=VLOOKUP(FLAT!$I$1,lists!$G:$H,2,FALSE),AC40<=VLOOKUP(FLAT!$I$2,lists!$G:$H,2,FALSE)),TRUE,FALSE) -> TRUE | AG40: =VLOOKUP(AB40,lists!$B$7:$C$8,2,FALSE) -> TRUE | AH40: =VLOOKUP(IF(H40="","Open",SUBSTITUTE(H40,"/Nov","")),lists!$B$27:$D$29,2,FALSE) -> TRUE | AI40: =IF(FLAT!$I$5="All",TRUE,IF(FLAT!$I$5=TEXT('Raw - F'!C40,"mmm"),TRUE,FALSE)) -> TRUE | AJ40: =VLOOKUP(L40,lists!B:C,2,FALSE) -> TRUE | AK40: =VLOOKUP(T40,lists!$B$23:$D$25,2,FALSE) -> TRUE | AL40: =IF(AND(AD40=TRUE,AE40=TRUE,AF40=TRUE,AG40=TRUE,AH40=TRUE,AI40=TRUE,AJ40=TRUE,AK40=TRUE),1,0) -> 1
A41: =IF(B41="",A40,B41+1) -> 41 | B41: =IF(AND(A40<1,AL41=1),1,IF(AL41=1,A40,"")) -> 40 | C41: 44318 | D41: NEWMARKET | E41: Flat | F41: Flat | G41: Hcap | H41: Open | J41: 4yo+ | K41: A | L41: 2 | N41: 0-105 | O41: 1m4f | P41: 1m 4f | Q41: 50000 | R41: RACING TV HCAP STKS | T41: Midlands | U41: 0 | AA41: =IF(OR(J41="2yo",J41="3yo"),J41,"Other") -> Other | AB41: =IF(K41="F",K41,"A") -> A | AC41: =VLOOKUP(P41,lists!$G:$H,2,FALSE) -> 7 | AD41: =VLOOKUP(G41,lists!$B$2:$C$3,2,FALSE) -> TRUE | AE41: =VLOOKUP(AA41,lists!$B:$C,2,FALSE) -> TRUE | AF41: =IF(AND(AC41>=VLOOKUP(FLAT!$I$1,lists!$G:$H,2,FALSE),AC41<=VLOOKUP(FLAT!$I$2,lists!$G:$H,2,FALSE)),TRUE,FALSE) -> TRUE | AG41: =VLOOKUP(AB41,lists!$B$7:$C$8,2,FALSE) -> TRUE | AH41: =VLOOKUP(IF(H41="","Open",SUBSTITUTE(H41,"/Nov","")),lists!$B$27:$D$29,2,FALSE) -> TRUE | AI41: =IF(FLAT!$I$5="All",TRUE,IF(FLAT!$I$5=TEXT('Raw - F'!C41,"mmm"),TRUE,FALSE)) -> TRUE | AJ41: =VLOOKUP(L41,lists!B:C,2,FALSE) -> TRUE | AK41: =VLOOKUP(T41,lists!$B$23:$D$25,2,FALSE) -> TRUE | AL41: =IF(AND(AD41=TRUE,AE41=TRUE,AF41=TRUE,AG41=TRUE,AH41=TRUE,AI41=TRUE,AJ41=TRUE,AK41=TRUE),1,0) -> 1
A42: =IF(B42="",A41,B42+1) -> 42 | B42: =IF(AND(A41<1,AL42=1),1,IF(AL42=1,A41,"")) -> 41 | C42: 44318 | D42: NEWMARKET | E42: Flat | F42: Flat | G42: Hcap | H42: Open | J42: 3yo | K42: A | L42: 3 | N42: 76-95 | O42: 1m2f | P42: 1m 2f | Q42: 20000 | R42: HOME OF RACING HCAP | T42: Midlands | U42: 0 | AA42: =IF(OR(J42="2yo",J42="3yo"),J42,"Other") -> 3yo | AB42: =IF(K42="F",K42,"A") -> A | AC42: =VLOOKUP(P42,lists!$G:$H,2,FALSE) -> 5 | AD42: =VLOOKUP(G42,lists!$B$2:$C$3,2,FALSE) -> TRUE | AE42: =VLOOKUP(AA42,lists!$B:$C,2,FALSE) -> TRUE | AF42: =IF(AND(AC42>=VLOOKUP(FLAT!$I$1,lists!$G:$H,2,FALSE),AC42<=VLOOKUP(FLAT!$I$2,lists!$G:$H,2,FALSE)),TRUE,FALSE) -> TRUE | AG42: =VLOOKUP(AB42,lists!$B$7:$C$8,2,FALSE) -> TRUE | AH42: =VLOOKUP(IF(H42="","Open",SUBSTITUTE(H42,"/Nov","")),lists!$B$27:$D$29,2,FALSE) -> TRUE | AI42: =IF(FLAT!$I$5="All",TRUE,IF(FLAT!$I$5=TEXT('Raw - F'!C42,"mmm"),TRUE,FALSE)) -> TRUE | AJ42: =VLOOKUP(L42,lists!B:C,2,FALSE) -> TRUE | AK42: =VLOOKUP(T42,lists!$B$23:$D$25,2,FALSE) -> TRUE | AL42: =IF(AND(AD42=TRUE,AE42=TRUE,AF42=TRUE,AG42=TRUE,AH42=TRUE,AI42=TRUE,AJ42=TRUE,AK42=TRUE),1,0) -> 1
A43: =IF(B43="",A42,B43+1) -> 43 | B43: =IF(AND(A42<1,AL43=1),1,IF(AL43=1,A42,"")) -> 42 | C43: 44318 | D43: NEWMARKET | E43: Flat | F43: Flat | G43: WFA | H43: Mdn | J43: 2yo | K43: A | L43: 3 | N43: Open | O43: 5f | P43: 5f | Q43: 12000 | R43: BRITISH EBF MDN STKS | T43: Midlands | U43: 0 | Z43: EBF | AA43: =IF(OR(J43="2yo",J43="3yo"),J43,"Other") -> 2yo | AB43: =IF(K43="F",K43,"A") -> A | AC43: =VLOOKUP(P43,lists!$G:$H,2,FALSE) -> 1 | AD43: =VLOOKUP(G43,lists!$B$2:$C$3,2,FALSE) -> TRUE | AE43: =VLOOKUP(AA43,lists!$B:$C,2,FALSE) -> TRUE | AF43: =IF(AND(AC43>=VLOOKUP(FLAT!$I$1,lists!$G:$H,2,FALSE),AC43<=VLOOKUP(FLAT!$I$2,lists!$G:$H,2,FALSE)),TRUE,FALSE) -> TRUE | AG43: =VLOOKUP(AB43,lists!$B$7:$C$8,2,FALSE) -> TRUE | AH43: =VLOOKUP(IF(H43="","Open",SUBSTITUTE(H43,"/Nov","")),lists!$B$27:$D$29,2,FALSE) -> TRUE | AI43: =IF(FLAT!$I$5="All",TRUE,IF(FLAT!$I$5=TEXT('Raw - F'!C43,"mmm"),TRUE,FALSE)) -> TRUE | AJ43: =VLOOKUP(L43,lists!B:C,2,FALSE) -> TRUE | AK43: =VLOOKUP(T43,lists!$B$23:$D$25,2,FALSE) -> TRUE | AL43: =IF(AND(AD43=TRUE,AE43=TRUE,AF43=TRUE,AG43=TRUE,AH43=TRUE,AI43=TRUE,AJ43=TRUE,AK43=TRUE),1,0) -> 1
A44: =IF(B44="",A43,B44+1) -> 44 | B44: =IF(AND(A43<1,AL44=1),1,IF(AL44=1,A43,"")) -> 43 | C44: 44318 | D44: NEWMARKET | G44: Hcap | H44: Open | J44: 3yo | K44: A | L44: 3 | N44: 71-90 | P44: 1m 4f | R44: Race to be discussed | T44: South | U44: 0 | AA44: =IF(OR(J44="2yo",J44="3yo"),J44,"Other") -> 3yo | AB44: =IF(K44="F",K44,"A") -> A | AC44: =VLOOKUP(P44,lists!$G:$H,2,FALSE) -> 7 | AD44: =VLOOKUP(G44,lists!$B$2:$C$3,2,FALSE) -> TRUE | AE44: =VLOOKUP(AA44,lists!$B:$C,2,FALSE) -> TRUE | AF44: =IF(AND(AC44>=VLOOKUP(FLAT!$I$1,lists!$G:$H,2,FALSE),AC44<=VLOOKUP(FLAT!$I$2,lists!$G:$H,2,FALSE)),TRUE,FALSE) -> TRUE | AG44: =VLOOKUP(AB44,lists!$B$7:$C$8,2,FALSE) -> TRUE | AH44: =VLOOKUP(IF(H44="","Open",SUBSTITUTE(H44,"/Nov","")),lists!$B$27:$D$29,2,FALSE) -> TRUE | AI44: =IF(FLAT!$I$5="All",TRUE,IF(FLAT!$I$5=TEXT('Raw - F'!C44,"mmm"),TRUE,FALSE)) -> TRUE | AJ44: =VLOOKUP(L44,lists!B:C,2,FALSE) -> TRUE | AK44: =VLOOKUP(T44,lists!$B$23:$D$25,2,FALSE) -> TRUE | AL44: =IF(AND(AD44=TRUE,AE44=TRUE,AF44=TRUE,AG44=TRUE,AH44=TRUE,AI44=TRUE,AJ44=TRUE,AK44=TRUE),1,0) -> 1
A45: =IF(B45="",A44,B45+1) -> 45 | B45: =IF(AND(A44<1,AL45=1),1,IF(AL45=1,A44,"")) -> 44 | C45: 44318 | D45: NEWMARKET | G45: Hcap | H45: Open | J45: 3yo | K45: A | L45: 4 | N45: 66-85 | P45: 7f | R45: Won no more than one race | S45: F | T45: Midlands | AA45: =IF(OR(J45="2yo",J45="3yo"),J45,"Other") -> 3yo | AB45: =IF(K45="F",K45,"A") -> A | AC45: =VLOOKUP(P45,lists!$G:$H,2,FALSE) -> 3 | AD45: =VLOOKUP(G45,lists!$B$2:$C$3,2,FALSE) -> TRUE | AE45: =VLOOKUP(AA45,lists!$B:$C,2,FALSE) -> TRUE | AF45: =IF(AND(AC45>=VLOOKUP(FLAT!$I$1,lists!$G:$H,2,FALSE),AC45<=VLOOKUP(FLAT!$I$2,lists!$G:$H,2,FALSE)),TRUE,FALSE) -> TRUE | AG45: =VLOOKUP(AB45,lists!$B$7:$C$8,2,FALSE) -> TRUE | AH45: =VLOOKUP(IF(H45="","Open",SUBSTITUTE(H45,"/Nov","")),lists!$B$27:$D$29,2,FALSE) -> TRUE | AI45: =IF(FLAT!$I$5="All",TRUE,IF(FLAT!$I$5=TEXT('Raw - F'!C45,"mmm"),TRUE,FALSE)) -> TRUE | AJ45: =VLOOKUP(L45,lists!B:C,2,FALSE) -> TRUE | AK45: =VLOOKUP(T45,lists!$B$23:$D$25,2,FALSE) -> TRUE | AL45: =IF(AND(AD45=TRUE,AE45=TRUE,AF45=TRUE,AG45=TRUE,AH45=TRUE,AI45=TRUE,AJ45=TRUE,AK45=TRUE),1,0) -> 1
A46: =IF(B46="",A45,B46+1) -> 46 | B46: =IF(AND(A45<1,AL46=1),1,IF(AL46=1,A45,"")) -> 45 | C46: 44318 | D46: SALISBURY | E46: Flat | F46: Flat | G46: Hcap | H46: Open | J46: 4yo+ | K46: A | L46: 3 | N46: 76-95 | O46: 1m6f44y | P46: 1m 6f | Q46: 17500 | R46: CITY BOWL HCAP STKS | T46: South | U46: 0 | AA46: =IF(OR(J46="2yo",J46="3yo"),J46,"Other") -> Other | AB46: =IF(K46="F",K46,"A") -> A | AC46: =VLOOKUP(P46,lists!$G:$H,2,FALSE) -> 9 | AD46: =VLOOKUP(G46,lists!$B$2:$C$3,2,FALSE) -> TRUE | AE46: =VLOOKUP(AA46,lists!$B:$C,2,FALSE) -> TRUE | AF46: =IF(AND(AC46>=VLOOKUP(FLAT!$I$1,lists!$G:$H,2,FALSE),AC46<=VLOOKUP(FLAT!$I$2,lists!$G:$H,2,FALSE)),TRUE,FALSE) -> TRUE | AG46: =VLOOKUP(AB46,lists!$B$7:$C$8,2,FALSE) -> TRUE | AH46: =VLOOKUP(IF(H46="","Open",SUBSTITUTE(H46,"/Nov","")),lists!$B$27:$D$29,2,FALSE) -> TRUE | AI46: =IF(FLAT!$I$5="All",TRUE,IF(FLAT!$I$5=TEXT('Raw - F'!C46,"mmm"),TRUE,FALSE)) -> TRUE | AJ46: =VLOOKUP(L46,lists!B:C,2,FALSE) -> TRUE | AK46: =VLOOKUP(T46,lists!$B$23:$D$25,2,FALSE) -> TRUE | AL46: =IF(AND(AD46=TRUE,AE46=TRUE,AF46=TRUE,AG46=TRUE,AH46=TRUE,AI46=TRUE,AJ46=TRUE,AK46=TRUE),1,0) -> 1
A47: =IF(B47="",A46,B47+1) -> 47 | B47: =IF(AND(A46<1,AL47=1),1,IF(AL47=1,A46,"")) -> 46 | C47: 44318 | D47: SALISBURY | E47: Flat | F47: Flat | G47: Hcap | H47: Open | J47: 3yo | K47: F | L47: 3 | N47: 71-90 | O47: 6f213y | P47: 7f | Q47: 12000 | R47: AMAZING HCAP STKS | T47: South | U47: 0 | AA47: =IF(OR(J47="2yo",J47="3yo"),J47,"Other") -> 3yo | AB47: =IF(K47="F",K47,"A") -> F | AC47: =VLOOKUP(P47,lists!$G:$H,2,FALSE) -> 3 | AD47: =VLOOKUP(G47,lists!$B$2:$C$3,2,FALSE) -> TRUE | AE47: =VLOOKUP(AA47,lists!$B:$C,2,FALSE) -> TRUE | AF47: =IF(AND(AC47>=VLOOKUP(FLAT!$I$1,lists!$G:$H,2,FALSE),AC47<=VLOOKUP(FLAT!$I$2,lists!$G:$H,2,FALSE)),TRUE,FALSE) -> TRUE | AG47: =VLOOKUP(AB47,lists!$B$7:$C$8,2,FALSE) -> TRUE | AH47: =VLOOKUP(IF(H47="","Open",SUBSTITUTE(H47,"/Nov","")),lists!$B$27:$D$29,2,FALSE) -> TRUE | AI47: =IF(FLAT!$I$5="All",TRUE,IF(FLAT!$I$5=TEXT('Raw - F'!C47,"mmm"),TRUE,FALSE)) -> TRUE | AJ47: =VLOOKUP(L47,lists!B:C,2,FALSE) -> TRUE | AK47: =VLOOKUP(T47,lists!$B$23:$D$25,2,FALSE) -> TRUE | AL47: =IF(AND(AD47=TRUE,AE47=TRUE,AF47=TRUE,AG47=TRUE,AH47=TRUE,AI47=TRUE,AJ47=TRUE,AK47=TRUE),1,0) -> 1
A48: =IF(B48="",A47,B48+1) -> 48 | B48: =IF(AND(A47<1,AL48=1),1,IF(AL48=1,A47,"")) -> 47 | C48: 44318 | D48: SALISBURY | E48: Flat | F48: Flat | G48: WFA | H48: Open | I48: Conditions | J48: 2yo | K48: F | L48: 3 | N48: Open | O48: 5f | P48: 5f | Q48: 12000 | R48: PARADISE ISLAND STKS | T48: South | U48: 0 | AA48: =IF(OR(J48="2yo",J48="3yo"),J48,"Other") -> 2yo | AB48: =IF(K48="F",K48,"A") -> F | AC48: =VLOOKUP(P48,lists!$G:$H,2,FALSE) -> 1 | AD48: =VLOOKUP(G48,lists!$B$2:$C$3,2,FALSE) -> TRUE | AE48: =VLOOKUP(AA48,lists!$B:$C,2,FALSE) -> TRUE | AF48: =IF(AND(AC48>=VLOOKUP(FLAT!$I$1,lists!$G:$H,2,FALSE),AC48<=VLOOKUP(FLAT!$I$2,lists!$G:$H,2,FALSE)),TRUE,FALSE) -> TRUE | AG48: =VLOOKUP(AB48,lists!$B$7:$C$8,2,FALSE) -> TRUE | AH48: =VLOOKUP(IF(H48="","Open",SUBSTITUTE(H48,"/Nov","")),lists!$B$27:$D$29,2,FALSE) -> TRUE | AI48: =IF(FLAT!$I$5="All",TRUE,IF(FLAT!$I$5=TEXT('Raw - F'!C48,"mmm"),TRUE,FALSE)) -> TRUE | AJ48: =VLOOKUP(L48,lists!B:C,2,FALSE) -> TRUE | AK48: =VLOOKUP(T48,lists!$B$23:$D$25,2,FALSE) -> TRUE | AL48: =IF(AND(AD48=TRUE,AE48=TRUE,AF48=TRUE,AG48=TRUE,AH48=TRUE,AI48=TRUE,AJ48=TRUE,AK48=TRUE),1,0) -> 1
A49: =IF(B49="",A48,B49+1) -> 49 | B49: =IF(AND(A48<1,AL49=1),1,IF(AL49=1,A48,"")) -> 48 | C49: 44318 | D49: SALISBURY | E49: Flat | F49: Flat | G49: WFA | H49: Mdn | J49: 3yo | K49: A | L49: 4 | N49: Open | O49: 1m4f5y | P49: 1m 4f | Q49: 9600 | R49: BRITISH EBF MDN STKS | T49: South | U49: 0 | Z49: EBF | AA49: =IF(OR(J49="2yo",J49="3yo"),J49,"Other") -> 3yo | AB49: =IF(K49="F",K49,"A") -> A | AC49: =VLOOKUP(P49,lists!$G:$H,2,FALSE) -> 7 | AD49: =VLOOKUP(G49,lists!$B$2:$C$3,2,FALSE) -> TRUE | AE49: =VLOOKUP(AA49,lists!$B:$C,2,FALSE) -> TRUE | AF49: =IF(AND(AC49>=VLOOKUP(FLAT!$I$1,lists!$G:$H,2,FALSE),AC49<=VLOOKUP(FLAT!$I$2,lists!$G:$H,2,FALSE)),TRUE,FALSE) -> TRUE | AG49: =VLOOKUP(AB49,lists!$B$7:$C$8,2,FALSE) -> TRUE | AH49: =VLOOKUP(IF(H49="","Open",SUBSTITUTE(H49,"/Nov","")),lists!$B$27:$D$29,2,FALSE) -> TRUE | AI49: =IF(FLAT!$I$5="All",TRUE,IF(FLAT!$I$5=TEXT('Raw - F'!C49,"mmm"),TRUE,FALSE)) -> TRUE | AJ49: =VLOOKUP(L49,lists!B:C,2,FALSE) -> TRUE | AK49: =VLOOKUP(T49,lists!$B$23:$D$25,2,FALSE) -> TRUE | AL49: =IF(AND(AD49=TRUE,AE49=TRUE,AF49=TRUE,AG49=TRUE,AH49=TRUE,AI49=TRUE,AJ49=TRUE,AK49=TRUE),1,0) -> 1
A50: =IF(B50="",A49,B50+1) -> 50 | B50: =IF(AND(A49<1,AL50=1),1,IF(AL50=1,A49,"")) -> 49 | C50: 44318 | D50: SALISBURY | E50: Flat | F50: Flat | G50: Hcap | H50: Open | J50: 3yo | K50: A | L50: 4 | N50: 61-80 | O50: 1m1f201y | P50: 1m 2f | Q50: 8000 | R50: NEWHOUSE HCAP STKS | T50: South | U50: 0 | AA50: =IF(OR(J50="2yo",J50="3yo"),J50,"Other") -> 3yo | AB50: =IF(K50="F",K50,"A") -> A | AC50: =VLOOKUP(P50,lists!$G:$H,2,FALSE) -> 5 | AD50: =VLOOKUP(G50,lists!$B$2:$C$3,2,FALSE) -> TRUE | AE50: =VLOOKUP(AA50,lists!$B:$C,2,FALSE) -> TRUE | AF50: =IF(AND(AC50>=VLOOKUP(FLAT!$I$1,lists!$G:$H,2,FALSE),AC50<=VLOOKUP(FLAT!$I$2,lists!$G:$H,2,FALSE)),TRUE,FALSE) -> TRUE | AG50: =VLOOKUP(AB50,lists!$B$7:$C$8,2,FALSE) -> TRUE | AH50: =VLOOKUP(IF(H50="","Open",SUBSTITUTE(H50,"/Nov","")),lists!$B$27:$D$29,2,FALSE) -> TRUE | AI50: =IF(FLAT!$I$5="All",TRUE,IF(FLAT!$I$5=TEXT('Raw - F'!C50,"mmm"),TRUE,FALSE)) -> TRUE | AJ50: =VLOOKUP(L50,lists!B:C,2,FALSE) -> TRUE | AK50: =VLOOKUP(T50,lists!$B$23:$D$25,2,FALSE) -> TRUE | AL50: =IF(AND(AD50=TRUE,AE50=TRUE,AF50=TRUE,AG50=TRUE,AH50=TRUE,AI50=TRUE,AJ50=TRUE,AK50=TRUE),1,0) -> 1
A51: =IF(B51="",A50,B51+1) -> 51 | B51: =IF(AND(A50<1,AL51=1),1,IF(AL51=1,A50,"")) -> 50 | C51: 44318 | D51: SALISBURY | E51: Flat | F51: Flat | G51: WFA | H51: Nov | J51: 3yo | K51: C | L51: 5 | N51: Open | O51: 6f213y | P51: 7f | Q51: 5850 | R51: SRI LANKA NOV STKS | T51: South | U51: 0 | AA51: =IF(OR(J51="2yo",J51="3yo"),J51,"Other") -> 3yo | AB51: =IF(K51="F",K51,"A") -> A | AC51: =VLOOKUP(P51,lists!$G:$H,2,FALSE) -> 3 | AD51: =VLOOKUP(G51,lists!$B$2:$C$3,2,FALSE) -> TRUE | AE51: =VLOOKUP(AA51,lists!$B:$C,2,FALSE) -> TRUE | AF51: =IF(AND(AC51>=VLOOKUP(FLAT!$I$1,lists!$G:$H,2,FALSE),AC51<=VLOOKUP(FLAT!$I$2,lists!$G:$H,2,FALSE)),TRUE,FALSE) -> TRUE | AG51: =VLOOKUP(AB51,lists!$B$7:$C$8,2,FALSE) -> TRUE | AH51: =VLOOKUP(IF(H51="","Open",SUBSTITUTE(H51,"/Nov","")),lists!$B$27:$D$29,2,FALSE) -> TRUE | AI51: =IF(FLAT!$I$5="All",TRUE,IF(FLAT!$I$5=TEXT('Raw - F'!C51,"mmm"),TRUE,FALSE)) -> TRUE | AJ51: =VLOOKUP(L51,lists!B:C,2,FALSE) -> TRUE | AK51: =VLOOKUP(T51,lists!$B$23:$D$25,2,FALSE) -> TRUE | AL51: =IF(AND(AD51=TRUE,AE51=TRUE,AF51=TRUE,AG51=TRUE,AH51=TRUE,AI51=TRUE,AJ51=TRUE,AK51=TRUE),1,0) -> 1
A52: =IF(B52="",A51,B52+1) -> 52 | B52: =IF(AND(A51<1,AL52=1),1,IF(AL52=1,A51,"")) -> 51 | C52: 44318 | D52: SALISBURY | E52: Flat | F52: Flat | G52: Hcap | H52: Open | J52: 4yo+ | K52: A | L52: 6 | N52: 46-65 | O52: 6f213y | P52: 7f | Q52: 4067 | R52: VISIT LR HCAP STKS | T52: South | U52: 0 | V52: Lady | AA52: =IF(OR(J52="2yo",J52="3yo"),J52,"Other") -> Other | AB52: =IF(K52="F",K52,"A") -> A | AC52: =VLOOKUP(P52,lists!$G:$H,2,FALSE) -> 3 | AD52: =VLOOKUP(G52,lists!$B$2:$C$3,2,FALSE) -> TRUE | AE52: =VLOOKUP(AA52,lists!$B:$C,2,FALSE) -> TRUE | AF52: =IF(AND(AC52>=VLOOKUP(FLAT!$I$1,lists!$G:$H,2,FALSE),AC52<=VLOOKUP(FLAT!$I$2,lists!$G:$H,2,FALSE)),TRUE,FALSE) -> TRUE | AG52: =VLOOKUP(AB52,lists!$B$7:$C$8,2,FALSE) -> TRUE | AH52: =VLOOKUP(IF(H52="","Open",SUBSTITUTE(H52,"/Nov","")),lists!$B$27:$D$29,2,FALSE) -> TRUE | AI52: =IF(FLAT!$I$5="All",TRUE,IF(FLAT!$I$5=TEXT('Raw - F'!C52,"mmm"),TRUE,FALSE)) -> TRUE | AJ52: =VLOOKUP(L52,lists!B:C,2,FALSE) -> TRUE | AK52: =VLOOKUP(T52,lists!$B$23:$D$25,2,FALSE) -> TRUE | AL52: =IF(AND(AD52=TRUE,AE52=TRUE,AF52=TRUE,AG52=TRUE,AH52=TRUE,AI52=TRUE,AJ52=TRUE,AK52=TRUE),1,0) -> 1
A53: =IF(B53="",A52,B53+1) -> 53 | B53: =IF(AND(A52<1,AL53=1),1,IF(AL53=1,A52,"")) -> 52 | C53: 44319 | D53: BATH | E53: Flat | F53: Flat | G53: Hcap | H53: Open | J53: 4yo+ | K53: A | L53: 4 | N53: 66-85 | O53: 5f10y | P53: 5f | Q53: 7650 | R53: BRISTOL HCAP STKS | S53: C | T53: South | U53: 0 | AA53: =IF(OR(J53="2yo",J53="3yo"),J53,"Other") -> Other | AB53: =IF(K53="F",K53,"A") -> A | AC53: =VLOOKUP(P53,lists!$G:$H,2,FALSE) -> 1 | AD53: =VLOOKUP(G53,lists!$B$2:$C$3,2,FALSE) -> TRUE | AE53: =VLOOKUP(AA53,lists!$B:$C,2,FALSE) -> TRUE | AF53: =IF(AND(AC53>=VLOOKUP(FLAT!$I$1,lists!$G:$H,2,FALSE),AC53<=VLOOKUP(FLAT!$I$2,lists!$G:$H,2,FALSE)),TRUE,FALSE) -> TRUE | AG53: =VLOOKUP(AB53,lists!$B$7:$C$8,2,FALSE) -> TRUE | AH53: =VLOOKUP(IF(H53="","Open",SUBSTITUTE(H53,"/Nov","")),lists!$B$27:$D$29,2,FALSE) -> TRUE | AI53: =IF(FLAT!$I$5="All",TRUE,IF(FLAT!$I$5=TEXT('Raw - F'!C53,"mmm"),TRUE,FALSE)) -> TRUE | AJ53: =VLOOKUP(L53,lists!B:C,2,FALSE) -> TRUE | AK53: =VLOOKUP(T53,lists!$B$23:$D$25,2,FALSE) -> TRUE | AL53: =IF(AND(AD53=TRUE,AE53=TRUE,AF53=TRUE,AG53=TRUE,AH53=TRUE,AI53=TRUE,AJ53=TRUE,AK53=TRUE),1,0) -> 1
A54: =IF(B54="",A53,B54+1) -> 54 | B54: =IF(AND(A53<1,AL54=1),1,IF(AL54=1,A53,"")) -> 53 | C54: 44319 | D54: BATH | E54: Flat | F54: Flat | G54: WFA | H54: Nov | J54: 2yo | K54: A | L54: 4 | N54: Open | O54: 5f10y | P54: 5f | Q54: 6500 | R54: DRIVE VAUXHALL NOV | S54: C | T54: South | U54: 0 | X54: Rest. | Y54: C | Z54: EBF | AA54: =IF(OR(J54="2yo",J54="3yo"),J54,"Other") -> 2yo | AB54: =IF(K54="F",K54,"A") -> A | AC54: =VLOOKUP(P54,lists!$G:$H,2,FALSE) -> 1 | AD54: =VLOOKUP(G54,lists!$B$2:$C$3,2,FALSE) -> TRUE | AE54: =VLOOKUP(AA54,lists!$B:$C,2,FALSE) -> TRUE | AF54: =IF(AND(AC54>=VLOOKUP(FLAT!$I$1,lists!$G:$H,2,FALSE),AC54<=VLOOKUP(FLAT!$I$2,lists!$G:$H,2,FALSE)),TRUE,FALSE) -> TRUE | AG54: =VLOOKUP(AB54,lists!$B$7:$C$8,2,FALSE) -> TRUE | AH54: =VLOOKUP(IF(H54="","Open",SUBSTITUTE(H54,"/Nov","")),lists!$B$27:$D$29,2,FALSE) -> TRUE | AI54: =IF(FLAT!$I$5="All",TRUE,IF(FLAT!$I$5=TEXT('Raw - F'!C54,"mmm"),TRUE,FALSE)) -> TRUE | AJ54: =VLOOKUP(L54,lists!B:C,2,FALSE) -> TRUE | AK54: =VLOOKUP(T54,lists!$B$23:$D$25,2,FALSE) -> TRUE | AL54: =IF(AND(AD54=TRUE,AE54=TRUE,AF54=TRUE,AG54=TRUE,AH54=TRUE,AI54=TRUE,AJ54=TRUE,AK54=TRUE),1,0) -> 1
A55: =IF(B55="",A54,B55+1) -> 55 | B55: =IF(AND(A54<1,AL55=1),1,IF(AL55=1,A54,"")) -> 54 | C55: 44319 | D55: BATH | E55: Flat | F55: Flat | G55: Hcap | H55: Open | J55: 3yo | K55: A | L55: 5 | N55: 56-75 | O55: 1m2f37y | P55: 1m 2f | Q55: 4900 | R55: NEW CORSA HCAP STKS | T55: South | U55: 0 | AA55: =IF(OR(J55="2yo",J55="3yo"),J55,"Other") -> 3yo | AB55: =IF(K55="F",K55,"A") -> A | AC55: =VLOOKUP(P55,lists!$G:$H,2,FALSE) -> 5 | AD55: =VLOOKUP(G55,lists!$B$2:$C$3,2,FALSE) -> TRUE | AE55: =VLOOKUP(AA55,lists!$B:$C,2,FALSE) -> TRUE | AF55: =IF(AND(AC55>=VLOOKUP(FLAT!$I$1,lists!$G:$H,2,FALSE),AC55<=VLOOKUP(FLAT!$I$2,lists!$G:$H,2,FALSE)),TRUE,FALSE) -> TRUE | AG55: =VLOOKUP(AB55,lists!$B$7:$C$8,2,FALSE) -> TRUE | AH55: =VLOOKUP(IF(H55="","Open",SUBSTITUTE(H55,"/Nov","")),lists!$B$27:$D$29,2,FALSE) -> TRUE | AI55: =IF(FLAT!$I$5="All",TRUE,IF(FLAT!$I$5=TEXT('Raw - F'!C55,"mmm"),TRUE,FALSE)) -> TRUE | AJ55: =VLOOKUP(L55,lists!B:C,2,FALSE) -> TRUE | AK55: =VLOOKUP(T55,lists!$B$23:$D$25,2,FALSE) -> TRUE | AL55: =IF(AND(AD55=TRUE,AE55=TRUE,AF55=TRUE,AG55=TRUE,AH55=TRUE,AI55=TRUE,AJ55=TRUE,AK55=TRUE),1,0) -> 1
A56: =IF(B56="",A55,B56+1) -> 56 | B56: =IF(AND(A55<1,AL56=1),1,IF(AL56=1,A55,"")) -> 55 | C56: 44319 | D56: BATH | E56: Flat | F56: Flat | G56: Hcap | H56: Open | J56: 4yo+ | K56: A | L56: 5 | N56: 56-75 | O56: 1m | P56: 1m | Q56: 4900 | R56: CROSSLAND X HCAP | T56: South | U56: 0 | AA56: =IF(OR(J56="2yo",J56="3yo"),J56,"Other") -> Other | AB56: =IF(K56="F",K56,"A") -> A | AC56: =VLOOKUP(P56,lists!$G:$H,2,FALSE) -> 4 | AD56: =VLOOKUP(G56,lists!$B$2:$C$3,2,FALSE) -> TRUE | AE56: =VLOOKUP(AA56,lists!$B:$C,2,FALSE) -> TRUE | AF56: =IF(AND(AC56>=VLOOKUP(FLAT!$I$1,lists!$G:$H,2,FALSE),AC56<=VLOOKUP(FLAT!$I$2,lists!$G:$H,2,FALSE)),TRUE,FALSE) -> TRUE | AG56: =VLOOKUP(AB56,lists!$B$7:$C$8,2,FALSE) -> TRUE | AH56: =VLOOKUP(IF(H56="","Open",SUBSTITUTE(H56,"/Nov","")),lists!$B$27:$D$29,2,FALSE) -> TRUE | AI56: =IF(FLAT!$I$5="All",TRUE,IF(FLAT!$I$5=TEXT('Raw - F'!C56,"mmm"),TRUE,FALSE)) -> TRUE | AJ56: =VLOOKUP(L56,lists!B:C,2,FALSE) -> TRUE | AK56: =VLOOKUP(T56,lists!$B$23:$D$25,2,FALSE) -> TRUE | AL56: =IF(AND(AD56=TRUE,AE56=TRUE,AF56=TRUE,AG56=TRUE,AH56=TRUE,AI56=TRUE,AJ56=TRUE,AK56=TRUE),1,0) -> 1
A57: =IF(B57="",A56,B57+1) -> 57 | B57: =IF(AND(A56<1,AL57=1),1,IF(AL57=1,A56,"")) -> 56 | C57: 44319 | D57: BATH | E57: Flat | F57: Flat | G57: Hcap | H57: Open | J57: 4yo+ | K57: A | L57: 5 | N57: 51-70 | O57: 1m3f137y | P57: 1m 4f | Q57: 3900 | R57: VAUXHALL HCAP STKS | S57: C | T57: South | U57: 0 | AA57: =IF(OR(J57="2yo",J57="3yo"),J57,"Other") -> Other | AB57: =IF(K57="F",K57,"A") -> A | AC57: =VLOOKUP(P57,lists!$G:$H,2,FALSE) -> 7 | AD57: =VLOOKUP(G57,lists!$B$2:$C$3,2,FALSE) -> TRUE | AE57: =VLOOKUP(AA57,lists!$B:$C,2,FALSE) -> TRUE | AF57: =IF(AND(AC57>=VLOOKUP(FLAT!$I$1,lists!$G:$H,2,FALSE),AC57<=VLOOKUP(FLAT!$I$2,lists!$G:$H,2,FALSE)),TRUE,FALSE) -> TRUE | AG57: =VLOOKUP(AB57,lists!$B$7:$C$8,2,FALSE) -> TRUE | AH57: =VLOOKUP(IF(H57="","Open",SUBSTITUTE(H57,"/Nov","")),lists!$B$27:$D$29,2,FALSE) -> TRUE | AI57: =IF(FLAT!$I$5="All",TRUE,IF(FLAT!$I$5=TEXT('Raw - F'!C57,"mmm"),TRUE,FALSE)) -> TRUE | AJ57: =VLOOKUP(L57,lists!B:C,2,FALSE) -> TRUE | AK57: =VLOOKUP(T57,lists!$B$23:$D$25,2,FALSE) -> TRUE | AL57: =IF(AND(AD57=TRUE,AE57=TRUE,AF57=TRUE,AG57=TRUE,AH57=TRUE,AI57=TRUE,AJ57=TRUE,AK57=TRUE),1,0) -> 1
A58: =IF(B58="",A57,B58+1) -> 58 | B58: =IF(AND(A57<1,AL58=1),1,IF(AL58=1,A57,"")) -> 57 | C58: 44319 | D58: BATH | E58: Flat | F58: Flat | G58: Hcap | H58: Open | J58: 3yo | K58: A | L58: 6 | N58: 46-60 | O58: 5f160y | P58: 6f | Q58: 3900 | R58: DRIVE VAUXHALL HCAP | T58: South | U58: 0 | AA58: =IF(OR(J58="2yo",J58="3yo"),J58,"Other") -> 3yo | AB58: =IF(K58="F",K58,"A") -> A | AC58: =VLOOKUP(P58,lists!$G:$H,2,FALSE) -> 2 | AD58: =VLOOKUP(G58,lists!$B$2:$C$3,2,FALSE) -> TRUE | AE58: =VLOOKUP(AA58,lists!$B:$C,2,FALSE) -> TRUE | AF58: =IF(AND(AC58>=VLOOKUP(FLAT!$I$1,lists!$G:$H,2,FALSE),AC58<=VLOOKUP(FLAT!$I$2,lists!$G:$H,2,FALSE)),TRUE,FALSE) -> TRUE | AG58: =VLOOKUP(AB58,lists!$B$7:$C$8,2,FALSE) -> TRUE | AH58: =VLOOKUP(IF(H58="","Open",SUBSTITUTE(H58,"/Nov","")),lists!$B$27:$D$29,2,FALSE) -> TRUE | AI58: =IF(FLAT!$I$5="All",TRUE,IF(FLAT!$I$5=TEXT('Raw - F'!C58,"mmm"),TRUE,FALSE)) -> TRUE | AJ58: =VLOOKUP(L58,lists!B:C,2,FALSE) -> TRUE | AK58: =VLOOKUP(T58,lists!$B$23:$D$25,2,FALSE) -> TRUE | AL58: =IF(AND(AD58=TRUE,AE58=TRUE,AF58=TRUE,AG58=TRUE,AH58=TRUE,AI58=TRUE,AJ58=TRUE,AK58=TRUE),1,0) -> 1
A59: =IF(B59="",A58,B59+1) -> 59 | B59: =IF(AND(A58<1,AL59=1),1,IF(AL59=1,A58,"")) -> 58 | C59: 44319 | D59: BATH | E59: Flat | F59: Flat | G59: Hcap | H59: Open | J59: 4yo+ | K59: A | L59: 6 | N59: 46-60 | O59: 5f10y | P59: 5f | Q59: 3900 | R59: NEW CAR TODAY HCAP | T59: South | U59: 0 | AA59: =IF(OR(J59="2yo",J59="3yo"),J59,"Other") -> Other | AB59: =IF(K59="F",K59,"A") -> A | AC59: =VLOOKUP(P59,lists!$G:$H,2,FALSE) -> 1 | AD59: =VLOOKUP(G59,lists!$B$2:$C$3,2,FALSE) -> TRUE | AE59: =VLOOKUP(AA59,lists!$B:$C,2,FALSE) -> TRUE | AF59: =IF(AND(AC59>=VLOOKUP(FLAT!$I$1,lists!$G:$H,2,FALSE),AC59<=VLOOKUP(FLAT!$I$2,lists!$G:$H,2,FALSE)),TRUE,FALSE) -> TRUE | AG59: =VLOOKUP(AB59,lists!$B$7:$C$8,2,FALSE) -> TRUE | AH59: =VLOOKUP(IF(H59="","Open",SUBSTITUTE(H59,"/Nov","")),lists!$B$27:$D$29,2,FALSE) -> TRUE | AI59: =IF(FLAT!$I$5="All",TRUE,IF(FLAT!$I$5=TEXT('Raw - F'!C59,"mmm"),TRUE,FALSE)) -> TRUE | AJ59: =VLOOKUP(L59,lists!B:C,2,FALSE) -> TRUE | AK59: =VLOOKUP(T59,lists!$B$23:$D$25,2,FALSE) -> TRUE | AL59: =IF(AND(AD59=TRUE,AE59=TRUE,AF59=TRUE,AG59=TRUE,AH59=TRUE,AI59=TRUE,AJ59=TRUE,AK59=TRUE),1,0) -> 1
A60: =IF(B60="",A59,B60+1) -> 60 | B60: =IF(AND(A59<1,AL60=1),1,IF(AL60=1,A59,"")) -> 59 | C60: 44319 | D60: BEVERLEY | E60: Flat | F60: Flat | G60: Hcap | H60: Open | J60: 4yo+ | K60: A | L60: 4 | N60: 61-80 | O60: 1m100y | P60: 1m | Q60: 10400 | R60: RACING TV HCAP STKS | T60: North | U60: 0 | AA60: =IF(OR(J60="2yo",J60="3yo"),J60,"Other") -> Other | AB60: =IF(K60="F",K60,"A") -> A | AC60: =VLOOKUP(P60,lists!$G:$H,2,FALSE) -> 4 | AD60: =VLOOKUP(G60,lists!$B$2:$C$3,2,FALSE) -> TRUE | AE60: =VLOOKUP(AA60,lists!$B:$C,2,FALSE) -> TRUE | AF60: =IF(AND(AC60>=VLOOKUP(FLAT!$I$1,lists!$G:$H,2,FALSE),AC60<=VLOOKUP(FLAT!$I$2,lists!$G:$H,2,FALSE)),TRUE,FALSE) -> TRUE | AG60: =VLOOKUP(AB60,lists!$B$7:$C$8,2,FALSE) -> TRUE | AH60: =VLOOKUP(IF(H60="","Open",SUBSTITUTE(H60,"/Nov","")),lists!$B$27:$D$29,2,FALSE) -> TRUE | AI60: =IF(FLAT!$I$5="All",TRUE,IF(FLAT!$I$5=TEXT('Raw - F'!C60,"mmm"),TRUE,FALSE)) -> TRUE | AJ60: =VLOOKUP(L60,lists!B:C,2,FALSE) -> TRUE | AK60: =VLOOKUP(T60,lists!$B$23:$D$25,2,FALSE) -> TRUE | AL60: =IF(AND(AD60=TRUE,AE60=TRUE,AF60=TRUE,AG60=TRUE,AH60=TRUE,AI60=TRUE,AJ60=TRUE,AK60=TRUE),1,0) -> 1
A61: =IF(B61="",A60,B61+1) -> 61 | B61: =IF(AND(A60<1,AL61=1),1,IF(AL61=1,A60,"")) -> 60 | C61: 44319 | D61: BEVERLEY | E61: Flat | F61: Flat | G61: WFA | H61: Nov | J61: 3yo+ | K61: F | L61: 5 | N61: Open | O61: 1m1f207y | P61: 1m 2f | Q61: 6400 | R61: HOLDERNESS NOV STKS | T61: North | U61: 0 | AA61: =IF(OR(J61="2yo",J61="3yo"),J61,"Other") -> Other | AB61: =IF(K61="F",K61,"A") -> F | AC61: =VLOOKUP(P61,lists!$G:$H,2,FALSE) -> 5 | AD61: =VLOOKUP(G61,lists!$B$2:$C$3,2,FALSE) -> TRUE | AE61: =VLOOKUP(AA61,lists!$B:$C,2,FALSE) -> TRUE | AF61: =IF(AND(AC61>=VLOOKUP(FLAT!$I$1,lists!$G:$H,2,FALSE),AC61<=VLOOKUP(FLAT!$I$2,lists!$G:$H,2,FALSE)),TRUE,FALSE) -> TRUE | AG61: =VLOOKUP(AB61,lists!$B$7:$C$8,2,FALSE) -> TRUE | AH61: =VLOOKUP(IF(H61="","Open",SUBSTITUTE(H61,"/Nov","")),lists!$B$27:$D$29,2,FALSE) -> TRUE | AI61: =IF(FLAT!$I$5="All",TRUE,IF(FLAT!$I$5=TEXT('Raw - F'!C61,"mmm"),TRUE,FALSE)) -> TRUE | AJ61: =VLOOKUP(L61,lists!B:C,2,FALSE) -> TRUE | AK61: =VLOOKUP(T61,lists!$B$23:$D$25,2,FALSE) -> TRUE | AL61: =IF(AND(AD61=TRUE,AE61=TRUE,AF61=TRUE,AG61=TRUE,AH61=TRUE,AI61=TRUE,AJ61=TRUE,AK61=TRUE),1,0) -> 1
A62: =IF(B62="",A61,B62+1) -> 62 | B62: =IF(AND(A61<1,AL62=1),1,IF(AL62=1,A61,"")) -> 61 | C62: 44319 | D62: BEVERLEY | E62: Flat | F62: Flat | G62: WFA | H62: Nov | J62: 2yo | K62: A | L62: 6 | N62: Open | O62: 5f | P62: 5f | Q62: 6000 | R62: KIPLINGCOTE NOV STKS | T62: North | U62: 0 | X62: Rest. | Y62: C | AA62: =IF(OR(J62="2yo",J62="3yo"),J62,"Other") -> 2yo | AB62: =IF(K62="F",K62,"A") -> A | AC62: =VLOOKUP(P62,lists!$G:$H,2,FALSE) -> 1 | AD62: =VLOOKUP(G62,lists!$B$2:$C$3,2,FALSE) -> TRUE | AE62: =VLOOKUP(AA62,lists!$B:$C,2,FALSE) -> TRUE | AF62: =IF(AND(AC62>=VLOOKUP(FLAT!$I$1,lists!$G:$H,2,FALSE),AC62<=VLOOKUP(FLAT!$I$2,lists!$G:$H,2,FALSE)),TRUE,FALSE) -> TRUE | AG62: =VLOOKUP(AB62,lists!$B$7:$C$8,2,FALSE) -> TRUE | AH62: =VLOOKUP(IF(H62="","Open",SUBSTITUTE(H62,"/Nov","")),lists!$B$27:$D$29,2,FALSE) -> TRUE | AI62: =IF(FLAT!$I$5="All",TRUE,IF(FLAT!$I$5=TEXT('Raw - F'!C62,"mmm"),TRUE,FALSE)) -> TRUE | AJ62: =VLOOKUP(L62,lists!B:C,2,FALSE) -> TRUE | AK62: =VLOOKUP(T62,lists!$B$23:$D$25,2,FALSE) -> TRUE | AL62: =IF(AND(AD62=TRUE,AE62=TRUE,AF62=TRUE,AG62=TRUE,AH62=TRUE,AI62=TRUE,AJ62=TRUE,AK62=TRUE),1,0) -> 1
A63: =IF(B63="",A62,B63+1) -> 63 | B63: =IF(AND(A62<1,AL63=1),1,IF(AL63=1,A62,"")) -> 62 | C63: 44319 | D63: BEVERLEY | E63: Flat | F63: Flat | G63: Hcap | H63: Open | J63: 3yo | K63: A | L63: 5 | N63: 51-70 | O63: 5f | P63: 5f | Q63: 6000 | R63: BEVERLEY HCAP STKS | T63: North | U63: 0 | AA63: =IF(OR(J63="2yo",J63="3yo"),J63,"Other") -> 3yo | AB63: =IF(K63="F",K63,"A") -> A | AC63: =VLOOKUP(P63,lists!$G:$H,2,FALSE) -> 1 | AD63: =VLOOKUP(G63,lists!$B$2:$C$3,2,FALSE) -> TRUE | AE63: =VLOOKUP(AA63,lists!$B:$C,2,FALSE) -> TRUE | AF63: =IF(AND(AC63>=VLOOKUP(FLAT!$I$1,lists!$G:$H,2,FALSE),AC63<=VLOOKUP(FLAT!$I$2,lists!$G:$H,2,FALSE)),TRUE,FALSE) -> TRUE | AG63: =VLOOKUP(AB63,lists!$B$7:$C$8,2,FALSE) -> TRUE | AH63: =VLOOKUP(IF(H63="","Open",SUBSTITUTE(H63,"/Nov","")),lists!$B$27:$D$29,2,FALSE) -> TRUE | AI63: =IF(FLAT!$I$5="All",TRUE,IF(FLAT!$I$5=TEXT('Raw - F'!C63,"mmm"),TRUE,FALSE)) -> TRUE | AJ63: =VLOOKUP(L63,lists!B:C,2,FALSE) -> TRUE | AK63: =VLOOKUP(T63,lists!$B$23:$D$25,2,FALSE) -> TRUE | AL63: =IF(AND(AD63=TRUE,AE63=TRUE,AF63=TRUE,AG63=TRUE,AH63=TRUE,AI63=TRUE,AJ63=TRUE,AK63=TRUE),1,0) -> 1
A64: =IF(B64="",A63,B64+1) -> 64 | B64: =IF(AND(A63<1,AL64=1),1,IF(AL64=1,A63,"")) -> 63 | C64: 44319 | D64: BEVERLEY | E64: Flat | F64: Flat | G64: Hcap | H64: Open | J64: 3yo | K64: A | L64: 6 | N64: 46-60 | O64: 1m1f207y | P64: 1m 2f | Q64: 4900 | R64: B.DIXON HCAP STKS | T64: North | U64: 0 | AA64: =IF(OR(J64="2yo",J64="3yo"),J64,"Other") -> 3yo | AB64: =IF(K64="F",K64,"A") -> A | AC64: =VLOOKUP(P64,lists!$G:$H,2,FALSE) -> 5 | AD64: =VLOOKUP(G64,lists!$B$2:$C$3,2,FALSE) -> TRUE | AE64: =VLOOKUP(AA64,lists!$B:$C,2,FALSE) -> TRUE | AF64: =IF(AND(AC64>=VLOOKUP(FLAT!$I$1,lists!$G:$H,2,FALSE),AC64<=VLOOKUP(FLAT!$I$2,lists!$G:$H,2,FALSE)),TRUE,FALSE) -> TRUE | AG64: =VLOOKUP(AB64,lists!$B$7:$C$8,2,FALSE) -> TRUE | AH64: =VLOOKUP(IF(H64="","Open",SUBSTITUTE(H64,"/Nov","")),lists!$B$27:$D$29,2,FALSE) -> TRUE | AI64: =IF(FLAT!$I$5="All",TRUE,IF(FLAT!$I$5=TEXT('Raw - F'!C64,"mmm"),TRUE,FALSE)) -> TRUE | AJ64: =VLOOKUP(L64,lists!B:C,2,FALSE) -> TRUE | AK64: =VLOOKUP(T64,lists!$B$23:$D$25,2,FALSE) -> TRUE | AL64: =IF(AND(AD64=TRUE,AE64=TRUE,AF64=TRUE,AG64=TRUE,AH64=TRUE,AI64=TRUE,AJ64=TRUE,AK64=TRUE),1,0) -> 1
A65: =IF(B65="",A64,B65+1) -> 65 | B65: =IF(AND(A64<1,AL65=1),1,IF(AL65=1,A64,"")) -> 64 | C65: 44319 | D65: BEVERLEY | E65: Flat | F65: Flat | G65: Hcap | H65: Open | J65: 3yo | K65: A | L65: 5 | N65: 56-75 | O65: 7f96y | P65: 7f | Q65: 4400 | R65: BURTON HCAP STKS | T65: North | U65: 0 | AA65: =IF(OR(J65="2yo",J65="3yo"),J65,"Other") -> 3yo | AB65: =IF(K65="F",K65,"A") -> A | AC65: =VLOOKUP(P65,lists!$G:$H,2,FALSE) -> 3 | AD65: =VLOOKUP(G65,lists!$B$2:$C$3,2,FALSE) -> TRUE | AE65: =VLOOKUP(AA65,lists!$B:$C,2,FALSE) -> TRUE | AF65: =IF(AND(AC65>=VLOOKUP(FLAT!$I$1,lists!$G:$H,2,FALSE),AC65<=VLOOKUP(FLAT!$I$2,lists!$G:$H,2,FALSE)),TRUE,FALSE) -> TRUE | AG65: =VLOOKUP(AB65,lists!$B$7:$C$8,2,FALSE) -> TRUE | AH65: =VLOOKUP(IF(H65="","Open",SUBSTITUTE(H65,"/Nov","")),lists!$B$27:$D$29,2,FALSE) -> TRUE | AI65: =IF(FLAT!$I$5="All",TRUE,IF(FLAT!$I$5=TEXT('Raw - F'!C65,"mmm"),TRUE,FALSE)) -> TRUE | AJ65: =VLOOKUP(L65,lists!B:C,2,FALSE) -> TRUE | AK65: =VLOOKUP(T65,lists!$B$23:$D$25,2,FALSE) -> TRUE | AL65: =IF(AND(AD65=TRUE,AE65=TRUE,AF65=TRUE,AG65=TRUE,AH65=TRUE,AI65=TRUE,AJ65=TRUE,AK65=TRUE),1,0) -> 1
A66: =IF(B66="",A65,B66+1) -> 66 | B66: =IF(AND(A65<1,AL66=1),1,IF(AL66=1,A65,"")) -> 65 | C66: 44319 | D66: BEVERLEY | E66: Flat | F66: Flat | G66: Hcap | H66: Open | J66: 4yo+ | K66: A | L66: 6 | N66: 46-60 | O66: 7f96y | P66: 7f | Q66: 4000 | R66: LECONFIELD HCAP STKS | T66: North | U66: 0 | AA66: =IF(OR(J66="2yo",J66="3yo"),J66,"Other") -> Other | AB66: =IF(K66="F",K66,"A") -> A | AC66: =VLOOKUP(P66,lists!$G:$H,2,FALSE) -> 3 | AD66: =VLOOKUP(G66,lists!$B$2:$C$3,2,FALSE) -> TRUE | AE66: =VLOOKUP(AA66,lists!$B:$C,2,FALSE) -> TRUE | AF66: =IF(AND(AC66>=VLOOKUP(FLAT!$I$1,lists!$G:$H,2,FALSE),AC66<=VLOOKUP(FLAT!$I$2,lists!$G:$H,2,FALSE)),TRUE,FALSE) -> TRUE | AG66: =VLOOKUP(AB66,lists!$B$7:$C$8,2,FALSE) -> TRUE | AH66: =VLOOKUP(IF(H66="","Open",SUBSTITUTE(H66,"/Nov","")),lists!$B$27:$D$29,2,FALSE) -> TRUE | AI66: =IF(FLAT!$I$5="All",TRUE,IF(FLAT!$I$5=TEXT('Raw - F'!C66,"mmm"),TRUE,FALSE)) -> TRUE | AJ66: =VLOOKUP(L66,lists!B:C,2,FALSE) -> TRUE | AK66: =VLOOKUP(T66,lists!$B$23:$D$25,2,FALSE) -> TRUE | AL66: =IF(AND(AD66=TRUE,AE66=TRUE,AF66=TRUE,AG66=TRUE,AH66=TRUE,AI66=TRUE,AJ66=TRUE,AK66=TRUE),1,0) -> 1
A67: =IF(B67="",A66,B67+1) -> 67 | B67: =IF(AND(A66<1,AL67=1),1,IF(AL67=1,A66,"")) -> 66 | C67: 44319 | D67: WINDSOR | E67: Flat | F67: Flat | G67: Hcap | H67: Open | J67: 4yo+ | K67: A | L67: 3 | N67: 76-95 | O67: 1m31y | P67: 1m | Q67: 11500 | R67: GEMS HCAP STKS | T67: South | U67: 0 | AA67: =IF(OR(J67="2yo",J67="3yo"),J67,"Other") -> Other | AB67: =IF(K67="F",K67,"A") -> A | AC67: =VLOOKUP(P67,lists!$G:$H,2,FALSE) -> 4 | AD67: =VLOOKUP(G67,lists!$B$2:$C$3,2,FALSE) -> TRUE | AE67: =VLOOKUP(AA67,lists!$B:$C,2,FALSE) -> TRUE | AF67: =IF(AND(AC67>=VLOOKUP(FLAT!$I$1,lists!$G:$H,2,FALSE),AC67<=VLOOKUP(FLAT!$I$2,lists!$G:$H,2,FALSE)),TRUE,FALSE) -> TRUE | AG67: =VLOOKUP(AB67,lists!$B$7:$C$8,2,FALSE) -> TRUE | AH67: =VLOOKUP(IF(H67="","Open",SUBSTITUTE(H67,"/Nov","")),lists!$B$27:$D$29,2,FALSE) -> TRUE | AI67: =IF(FLAT!$I$5="All",TRUE,IF(FLAT!$I$5=TEXT('Raw - F'!C67,"mmm"),TRUE,FALSE)) -> TRUE | AJ67: =VLOOKUP(L67,lists!B:C,2,FALSE) -> TRUE | AK67: =VLOOKUP(T67,lists!$B$23:$D$25,2,FALSE) -> TRUE | AL67: =IF(AND(AD67=TRUE,AE67=TRUE,AF67=TRUE,AG67=TRUE,AH67=TRUE,AI67=TRUE,AJ67=TRUE,AK67=TRUE),1,0) -> 1
A68: =IF(B68="",A67,B68+1) -> 68 | B68: =IF(AND(A67<1,AL68=1),1,IF(AL68=1,A67,"")) -> 67 | C68: 44319 | D68: WINDSOR | E68: Flat | F68: Flat | G68: Hcap | H68: Open | J68: 4yo+ | K68: A | L68: 4 | N68: 66-85 | O68: 6f12y | P68: 6f | Q68: 7650 | R68: P. RENDELL HCAP STKS | T68: South | U68: 0 | AA68: =IF(OR(J68="2yo",J68="3yo"),J68,"Other") -> Other | AB68: =IF(K68="F",K68,"A") -> A | AC68: =VLOOKUP(P68,lists!$G:$H,2,FALSE) -> 2 | AD68: =VLOOKUP(G68,lists!$B$2:$C$3,2,FALSE) -> TRUE | AE68: =VLOOKUP(AA68,lists!$B:$C,2,FALSE) -> TRUE | AF68: =IF(AND(AC68>=VLOOKUP(FLAT!$I$1,lists!$G:$H,2,FALSE),AC68<=VLOOKUP(FLAT!$I$2,lists!$G:$H,2,FALSE)),TRUE,FALSE) -> TRUE | AG68: =VLOOKUP(AB68,lists!$B$7:$C$8,2,FALSE) -> TRUE | AH68: =VLOOKUP(IF(H68="","Open",SUBSTITUTE(H68,"/Nov","")),lists!$B$27:$D$29,2,FALSE) -> TRUE | AI68: =IF(FLAT!$I$5="All",TRUE,IF(FLAT!$I$5=TEXT('Raw - F'!C68,"mmm"),TRUE,FALSE)) -> TRUE | AJ68: =VLOOKUP(L68,lists!B:C,2,FALSE) -> TRUE | AK68: =VLOOKUP(T68,lists!$B$23:$D$25,2,FALSE) -> TRUE | AL68: =IF(AND(AD68=TRUE,AE68=TRUE,AF68=TRUE,AG68=TRUE,AH68=TRUE,AI68=TRUE,AJ68=TRUE,AK68=TRUE),1,0) -> 1
A69: =IF(B69="",A68,B69+1) -> 69 | B69: =IF(AND(A68<1,AL69=1),1,IF(AL69=1,A68,"")) -> 68 | C69: 44319 | D69: WINDSOR | E69: Flat | F69: Flat | G69: Hcap | H69: Open | J69: 3yo | K69: A | L69: 5 | N69: 51-70 | O69: 6f12y | P69: 6f | Q69: 4900 | R69: TWITTER HCAP STKS | T69: South | U69: 0 | AA69: =IF(OR(J69="2yo",J69="3yo"),J69,"Other") -> 3yo | AB69: =IF(K69="F",K69,"A") -> A | AC69: =VLOOKUP(P69,lists!$G:$H,2,FALSE) -> 2 | AD69: =VLOOKUP(G69,lists!$B$2:$C$3,2,FALSE) -> TRUE | AE69: =VLOOKUP(AA69,lists!$B:$C,2,FALSE) -> TRUE | AF69: =IF(AND(AC69>=VLOOKUP(FLAT!$I$1,lists!$G:$H,2,FALSE),AC69<=VLOOKUP(FLAT!$I$2,lists!$G:$H,2,FALSE)),TRUE,FALSE) -> TRUE | AG69: =VLOOKUP(AB69,lists!$B$7:$C$8,2,FALSE) -> TRUE | AH69: =VLOOKUP(IF(H69="","Open",SUBSTITUTE(H69,"/Nov","")),lists!$B$27:$D$29,2,FALSE) -> TRUE | AI69: =IF(FLAT!$I$5="All",TRUE,IF(FLAT!$I$5=TEXT('Raw - F'!C69,"mmm"),TRUE,FALSE)) -> TRUE | AJ69: =VLOOKUP(L69,lists!B:C,2,FALSE) -> TRUE | AK69: =VLOOKUP(T69,lists!$B$23:$D$25,2,FALSE) -> TRUE | AL69: =IF(AND(AD69=TRUE,AE69=TRUE,AF69=TRUE,AG69=TRUE,AH69=TRUE,AI69=TRUE,AJ69=TRUE,AK69=TRUE),1,0) -> 1
A70: =IF(B70="",A69,B70+1) -> 70 | B70: =IF(AND(A69<1,AL70=1),1,IF(AL70=1,A69,"")) -> 69 | C70: 44319 | D70: WINDSOR | E70: Flat | F70: Flat | G70: WFA | H70: Nov | J70: 3-4yo | K70: A | L70: 5 | N70: Open | O70: 1m31y | P70: 1m | Q70: 4900 | R70: VISIT NOV STKS | T70: South | U70: 0 | AA70: =IF(OR(J70="2yo",J70="3yo"),J70,"Other") -> Other | AB70: =IF(K70="F",K70,"A") -> A | AC70: =VLOOKUP(P70,lists!$G:$H,2,FALSE) -> 4 | AD70: =VLOOKUP(G70,lists!$B$2:$C$3,2,FALSE) -> TRUE | AE70: =VLOOKUP(AA70,lists!$B:$C,2,FALSE) -> TRUE | AF70: =IF(AND(AC70>=VLOOKUP(FLAT!$I$1,lists!$G:$H,2,FALSE),AC70<=VLOOKUP(FLAT!$I$2,lists!$G:$H,2,FALSE)),TRUE,FALSE) -> TRUE | AG70: =VLOOKUP(AB70,lists!$B$7:$C$8,2,FALSE) -> TRUE | AH70: =VLOOKUP(IF(H70="","Open",SUBSTITUTE(H70,"/Nov","")),lists!$B$27:$D$29,2,FALSE) -> TRUE | AI70: =IF(FLAT!$I$5="All",TRUE,IF(FLAT!$I$5=TEXT('Raw - F'!C70,"mmm"),TRUE,FALSE)) -> TRUE | AJ70: =VLOOKUP(L70,lists!B:C,2,FALSE) -> TRUE | AK70: =VLOOKUP(T70,lists!$B$23:$D$25,2,FALSE) -> TRUE | AL70: =IF(AND(AD70=TRUE,AE70=TRUE,AF70=TRUE,AG70=TRUE,AH70=TRUE,AI70=TRUE,AJ70=TRUE,AK70=TRUE),1,0) -> 1
A71: =IF(B71="",A70,B71+1) -> 71 | B71: =IF(AND(A70<1,AL71=1),1,IF(AL71=1,A70,"")) -> 70 | C71: 44319 | D71: WINDSOR | E71: Flat | F71: Flat | G71: Hcap | H71: Open | J71: 4yo+ | K71: A | L71: 5 | N71: 56-75 | O71: 5f21y | P71: 5f | Q71: 4900 | R71: SKY SPORT APP HCP | S71: C | T71: South | U71: 0 | V71: App | AA71: =IF(OR(J71="2yo",J71="3yo"),J71,"Other") -> Other | AB71: =IF(K71="F",K71,"A") -> A | AC71: =VLOOKUP(P71,lists!$G:$H,2,FALSE) -> 1 | AD71: =VLOOKUP(G71,lists!$B$2:$C$3,2,FALSE) -> TRUE | AE71: =VLOOKUP(AA71,lists!$B:$C,2,FALSE) -> TRUE | AF71: =IF(AND(AC71>=VLOOKUP(FLAT!$I$1,lists!$G:$H,2,FALSE),AC71<=VLOOKUP(FLAT!$I$2,lists!$G:$H,2,FALSE)),TRUE,FALSE) -> TRUE | AG71: =VLOOKUP(AB71,lists!$B$7:$C$8,2,FALSE) -> TRUE | AH71: =VLOOKUP(IF(H71="","Open",SUBSTITUTE(H71,"/Nov","")),lists!$B$27:$D$29,2,FALSE) -> TRUE | AI71: =IF(FLAT!$I$5="All",TRUE,IF(FLAT!$I$5=TEXT('Raw - F'!C71,"mmm"),TRUE,FALSE)) -> TRUE | AJ71: =VLOOKUP(L71,lists!B:C,2,FALSE) -> TRUE | AK71: =VLOOKUP(T71,lists!$B$23:$D$25,2,FALSE) -> TRUE | AL71: =IF(AND(AD71=TRUE,AE71=TRUE,AF71=TRUE,AG71=TRUE,AH71=TRUE,AI71=TRUE,AJ71=TRUE,AK71=TRUE),1,0) -> 1
A72: =IF(B72="",A71,B72+1) -> 72 | B72: =IF(AND(A71<1,AL72=1),1,IF(AL72=1,A71,"")) -> 71 | C72: 44319 | D72: WINDSOR | E72: Flat | F72: Flat | G72: Hcap | H72: Open | J72: 4yo+ | K72: A | L72: 5 | N72: 51-70 | O72: 1m2f | P72: 1m 2f | Q72: 4900 | R72: SKY 415 HCP STKS | T72: South | U72: 0 | AA72: =IF(OR(J72="2yo",J72="3yo"),J72,"Other") -> Other | AB72: =IF(K72="F",K72,"A") -> A | AC72: =VLOOKUP(P72,lists!$G:$H,2,FALSE) -> 5 | AD72: =VLOOKUP(G72,lists!$B$2:$C$3,2,FALSE) -> TRUE | AE72: =VLOOKUP(AA72,lists!$B:$C,2,FALSE) -> TRUE | AF72: =IF(AND(AC72>=VLOOKUP(FLAT!$I$1,lists!$G:$H,2,FALSE),AC72<=VLOOKUP(FLAT!$I$2,lists!$G:$H,2,FALSE)),TRUE,FALSE) -> TRUE | AG72: =VLOOKUP(AB72,lists!$B$7:$C$8,2,FALSE) -> TRUE | AH72: =VLOOKUP(IF(H72="","Open",SUBSTITUTE(H72,"/Nov","")),lists!$B$27:$D$29,2,FALSE) -> TRUE | AI72: =IF(FLAT!$I$5="All",TRUE,IF(FLAT!$I$5=TEXT('Raw - F'!C72,"mmm"),TRUE,FALSE)) -> TRUE | AJ72: =VLOOKUP(L72,lists!B:C,2,FALSE) -> TRUE | AK72: =VLOOKUP(T72,lists!$B$23:$D$25,2,FALSE) -> TRUE | AL72: =IF(AND(AD72=TRUE,AE72=TRUE,AF72=TRUE,AG72=TRUE,AH72=TRUE,AI72=TRUE,AJ72=TRUE,AK72=TRUE),1,0) -> 1
A73: =IF(B73="",A72,B73+1) -> 73 | B73: =IF(AND(A72<1,AL73=1),1,IF(AL73=1,A72,"")) -> 72 | C73: 44319 | D73: WINDSOR | E73: Flat | F73: Flat | G73: Hcap | H73: Open | J73: 3yo | K73: A | L73: 6 | N73: 46-55 | O73: 1m3f99y | P73: 1m 3f | Q73: 3900 | R73: SKY SPORTS HCAP STKS | S73: C | T73: South | U73: 0 | AA73: =IF(OR(J73="2yo",J73="3yo"),J73,"Other") -> 3yo | AB73: =IF(K73="F",K73,"A") -> A | AC73: =VLOOKUP(P73,lists!$G:$H,2,FALSE) -> 6 | AD73: =VLOOKUP(G73,lists!$B$2:$C$3,2,FALSE) -> TRUE | AE73: =VLOOKUP(AA73,lists!$B:$C,2,FALSE) -> TRUE | AF73: =IF(AND(AC73>=VLOOKUP(FLAT!$I$1,lists!$G:$H,2,FALSE),AC73<=VLOOKUP(FLAT!$I$2,lists!$G:$H,2,FALSE)),TRUE,FALSE) -> TRUE | AG73: =VLOOKUP(AB73,lists!$B$7:$C$8,2,FALSE) -> TRUE | AH73: =VLOOKUP(IF(H73="","Open",SUBSTITUTE(H73,"/Nov","")),lists!$B$27:$D$29,2,FALSE) -> TRUE | AI73: =IF(FLAT!$I$5="All",TRUE,IF(FLAT!$I$5=TEXT('Raw - F'!C73,"mmm"),TRUE,FALSE)) -> TRUE | AJ73: =VLOOKUP(L73,lists!B:C,2,FALSE) -> TRUE | AK73: =VLOOKUP(T73,lists!$B$23:$D$25,2,FALSE) -> TRUE | AL73: =IF(AND(AD73=TRUE,AE73=TRUE,AF73=TRUE,AG73=TRUE,AH73=TRUE,AI73=TRUE,AJ73=TRUE,AK73=TRUE),1,0) -> 1
A74: =IF(B74="",A73,B74+1) -> 74 | B74: =IF(AND(A73<1,AL74=1),1,IF(AL74=1,A73,"")) -> 73 | C74: 44320 | D74: LINGFIELD PARK | E74: Flat | G74: Hcap | H74: Open | J74: 4yo+ | K74: A | L74: 6 | N74: 46-55 | P74: 6f | R74: New Race | T74: South | U74: 1 | AA74: =IF(OR(J74="2yo",J74="3yo"),J74,"Other") -> Other | AB74: =IF(K74="F",K74,"A") -> A | AC74: =VLOOKUP(P74,lists!$G:$H,2,FALSE) -> 2 | AD74: =VLOOKUP(G74,lists!$B$2:$C$3,2,FALSE) -> TRUE | AE74: =VLOOKUP(AA74,lists!$B:$C,2,FALSE) -> TRUE | AF74: =IF(AND(AC74>=VLOOKUP(FLAT!$I$1,lists!$G:$H,2,FALSE),AC74<=VLOOKUP(FLAT!$I$2,lists!$G:$H,2,FALSE)),TRUE,FALSE) -> TRUE | AG74: =VLOOKUP(AB74,lists!$B$7:$C$8,2,FALSE) -> TRUE | AH74: =VLOOKUP(IF(H74="","Open",SUBSTITUTE(H74,"/Nov","")),lists!$B$27:$D$29,2,FALSE) -> TRUE | AI74: =IF(FLAT!$I$5="All",TRUE,IF(FLAT!$I$5=TEXT('Raw - F'!C74,"mmm"),TRUE,FALSE)) -> TRUE | AJ74: =VLOOKUP(L74,lists!B:C,2,FALSE) -> TRUE | AK74: =VLOOKUP(T74,lists!$B$23:$D$25,2,FALSE) -> TRUE | AL74: =IF(AND(AD74=TRUE,AE74=TRUE,AF74=TRUE,AG74=TRUE,AH74=TRUE,AI74=TRUE,AJ74=TRUE,AK74=TRUE),1,0) -> 1
A75: =IF(B75="",A74,B75+1) -> 75 | B75: =IF(AND(A74<1,AL75=1),1,IF(AL75=1,A74,"")) -> 74 | C75: 44320 | D75: LINGFIELD PARK | E75: Flat | F75: Flat | G75: Hcap | H75: Open | J75: 4yo+ | K75: A | L75: 4 | N75: 61-80 | O75: 6f1y | P75: 6f | Q75: 7650 | R75: BETWAY HCAP STKS | T75: South | U75: 1 | AA75: =IF(OR(J75="2yo",J75="3yo"),J75,"Other") -> Other | AB75: =IF(K75="F",K75,"A") -> A | AC75: =VLOOKUP(P75,lists!$G:$H,2,FALSE) -> 2 | AD75: =VLOOKUP(G75,lists!$B$2:$C$3,2,FALSE) -> TRUE | AE75: =VLOOKUP(AA75,lists!$B:$C,2,FALSE) -> TRUE | AF75: =IF(AND(AC75>=VLOOKUP(FLAT!$I$1,lists!$G:$H,2,FALSE),AC75<=VLOOKUP(FLAT!$I$2,lists!$G:$H,2,FALSE)),TRUE,FALSE) -> TRUE | AG75: =VLOOKUP(AB75,lists!$B$7:$C$8,2,FALSE) -> TRUE | AH75: =VLOOKUP(IF(H75="","Open",SUBSTITUTE(H75,"/Nov","")),lists!$B$27:$D$29,2,FALSE) -> TRUE | AI75: =IF(FLAT!$I$5="All",TRUE,IF(FLAT!$I$5=TEXT('Raw - F'!C75,"mmm"),TRUE,FALSE)) -> TRUE | AJ75: =VLOOKUP(L75,lists!B:C,2,FALSE) -> TRUE | AK75: =VLOOKUP(T75,lists!$B$23:$D$25,2,FALSE) -> TRUE | AL75: =IF(AND(AD75=TRUE,AE75=TRUE,AF75=TRUE,AG75=TRUE,AH75=TRUE,AI75=TRUE,AJ75=TRUE,AK75=TRUE),1,0) -> 1
A76: =IF(B76="",A75,B76+1) -> 76 | B76: =IF(AND(A75<1,AL76=1),1,IF(AL76=1,A75,"")) -> 75 | C76: 44320 | D76: LINGFIELD PARK | E76: Flat | F76: Flat | G76: Hcap | H76: Open | J76: 4yo+ | K76: A | L76: 4 | N76: 61-80 | O76: 1m1y | P76: 1m | Q76: 4900 | R76: OWN DRUM HCAP STKS | T76: South | U76: 1 | AA76: =IF(OR(J76="2yo",J76="3yo"),J76,"Other") -> Other | AB76: =IF(K76="F",K76,"A") -> A | AC76: =VLOOKUP(P76,lists!$G:$H,2,FALSE) -> 4 | AD76: =VLOOKUP(G76,lists!$B$2:$C$3,2,FALSE) -> TRUE | AE76: =VLOOKUP(AA76,lists!$B:$C,2,FALSE) -> TRUE | AF76: =IF(AND(AC76>=VLOOKUP(FLAT!$I$1,lists!$G:$H,2,FALSE),AC76<=VLOOKUP(FLAT!$I$2,lists!$G:$H,2,FALSE)),TRUE,FALSE) -> TRUE | AG76: =VLOOKUP(AB76,lists!$B$7:$C$8,2,FALSE) -> TRUE | AH76: =VLOOKUP(IF(H76="","Open",SUBSTITUTE(H76,"/Nov","")),lists!$B$27:$D$29,2,FALSE) -> TRUE | AI76: =IF(FLAT!$I$5="All",TRUE,IF(FLAT!$I$5=TEXT('Raw - F'!C76,"mmm"),TRUE,FALSE)) -> TRUE | AJ76: =VLOOKUP(L76,lists!B:C,2,FALSE) -> TRUE | AK76: =VLOOKUP(T76,lists!$B$23:$D$25,2,FALSE) -> TRUE | AL76: =IF(AND(AD76=TRUE,AE76=TRUE,AF76=TRUE,AG76=TRUE,AH76=TRUE,AI76=TRUE,AJ76=TRUE,AK76=TRUE),1,0) -> 1
A77: =IF(B77="",A76,B77+1) -> 77 | B77: =IF(AND(A76<1,AL77=1),1,IF(AL77=1,A76,"")) -> 76 | C77: 44320 | D77: LINGFIELD PARK | E77: Flat | F77: Flat | G77: Hcap | H77: Open | J77: 3yo | K77: A | L77: 5 | N77: 56-75 | O77: 5f6y | P77: 5f | Q77: 4900 | R77: LADBROKES HCAP STKS | T77: South | U77: 1 | AA77: =IF(OR(J77="2yo",J77="3yo"),J77,"Other") -> 3yo | AB77: =IF(K77="F",K77,"A") -> A | AC77: =VLOOKUP(P77,lists!$G:$H,2,FALSE) -> 1 | AD77: =VLOOKUP(G77,lists!$B$2:$C$3,2,FALSE) -> TRUE | AE77: =VLOOKUP(AA77,lists!$B:$C,2,FALSE) -> TRUE | AF77: =IF(AND(AC77>=VLOOKUP(FLAT!$I$1,lists!$G:$H,2,FALSE),AC77<=VLOOKUP(FLAT!$I$2,lists!$G:$H,2,FALSE)),TRUE,FALSE) -> TRUE | AG77: =VLOOKUP(AB77,lists!$B$7:$C$8,2,FALSE) -> TRUE | AH77: =VLOOKUP(IF(H77="","Open",SUBSTITUTE(H77,"/Nov","")),lists!$B$27:$D$29,2,FALSE) -> TRUE | AI77: =IF(FLAT!$I$5="All",TRUE,IF(FLAT!$I$5=TEXT('Raw - F'!C77,"mmm"),TRUE,FALSE)) -> TRUE | AJ77: =VLOOKUP(L77,lists!B:C,2,FALSE) -> TRUE | AK77: =VLOOKUP(T77,lists!$B$23:$D$25,2,FALSE) -> TRUE | AL77: =IF(AND(AD77=TRUE,AE77=TRUE,AF77=TRUE,AG77=TRUE,AH77=TRUE,AI77=TRUE,AJ77=TRUE,AK77=TRUE),1,0) -> 1
A78: =IF(B78="",A77,B78+1) -> 78 | B78: =IF(AND(A77<1,AL78=1),1,IF(AL78=1,A77,"")) -> 77 | C78: 44320 | D78: LINGFIELD PARK | E78: Flat | F78: Flat | G78: WFA | H78: Nov | J78: 3yo | K78: A | L78: 5 | N78: Open | O78: 1m1y | P78: 1m | Q78: 4900 | R78: ODDS BOOST NOV STKS | T78: South | U78: 1 | AA78: =IF(OR(J78="2yo",J78="3yo"),J78,"Other") -> 3yo | AB78: =IF(K78="F",K78,"A") -> A | AC78: =VLOOKUP(P78,lists!$G:$H,2,FALSE) -> 4 | AD78: =VLOOKUP(G78,lists!$B$2:$C$3,2,FALSE) -> TRUE | AE78: =VLOOKUP(AA78,lists!$B:$C,2,FALSE) -> TRUE | AF78: =IF(AND(AC78>=VLOOKUP(FLAT!$I$1,lists!$G:$H,2,FALSE),AC78<=VLOOKUP(FLAT!$I$2,lists!$G:$H,2,FALSE)),TRUE,FALSE) -> TRUE | AG78: =VLOOKUP(AB78,lists!$B$7:$C$8,2,FALSE) -> TRUE | AH78: =VLOOKUP(IF(H78="","Open",SUBSTITUTE(H78,"/Nov","")),lists!$B$27:$D$29,2,FALSE) -> TRUE | AI78: =IF(FLAT!$I$5="All",TRUE,IF(FLAT!$I$5=TEXT('Raw - F'!C78,"mmm"),TRUE,FALSE)) -> TRUE | AJ78: =VLOOKUP(L78,lists!B:C,2,FALSE) -> TRUE | AK78: =VLOOKUP(T78,lists!$B$23:$D$25,2,FALSE) -> TRUE | AL78: =IF(AND(AD78=TRUE,AE78=TRUE,AF78=TRUE,AG78=TRUE,AH78=TRUE,AI78=TRUE,AJ78=TRUE,AK78=TRUE),1,0) -> 1
A79: =IF(B79="",A78,B79+1) -> 79 | B79: =IF(AND(A78<1,AL79=1),1,IF(AL79=1,A78,"")) -> 78 | C79: 44320 | D79: LINGFIELD PARK | E79: Flat | F79: Flat | G79: WFA | H79: Nov | J79: 2yo | K79: A | L79: 5 | N79: Open | O79: 5f6y | P79: 5f | Q79: 4900 | R79: LADBROKES NOV STKS | T79: South | U79: 1 | X79: Rest. | Y79: C | AA79: =IF(OR(J79="2yo",J79="3yo"),J79,"Other") -> 2yo | AB79: =IF(K79="F",K79,"A") -> A | AC79: =VLOOKUP(P79,lists!$G:$H,2,FALSE) -> 1 | AD79: =VLOOKUP(G79,lists!$B$2:$C$3,2,FALSE) -> TRUE | AE79: =VLOOKUP(AA79,lists!$B:$C,2,FALSE) -> TRUE | AF79: =IF(AND(AC79>=VLOOKUP(FLAT!$I$1,lists!$G:$H,2,FALSE),AC79<=VLOOKUP(FLAT!$I$2,lists!$G:$H,2,FALSE)),TRUE,FALSE) -> TRUE | AG79: =VLOOKUP(AB79,lists!$B$7:$C$8,2,FALSE) -> TRUE | AH79: =VLOOKUP(IF(H79="","Open",SUBSTITUTE(H79,"/Nov","")),lists!$B$27:$D$29,2,FALSE) -> TRUE | AI79: =IF(FLAT!$I$5="All",TRUE,IF(FLAT!$I$5=TEXT('Raw - F'!C79,"mmm"),TRUE,FALSE)) -> TRUE | AJ79: =VLOOKUP(L79,lists!B:C,2,FALSE) -> TRUE | AK79: =VLOOKUP(T79,lists!$B$23:$D$25,2,FALSE) -> TRUE | AL79: =IF(AND(AD79=TRUE,AE79=TRUE,AF79=TRUE,AG79=TRUE,AH79=TRUE,AI79=TRUE,AJ79=TRUE,AK79=TRUE),1,0) -> 1
A80: =IF(B80="",A79,B80+1) -> 80 | B80: =IF(AND(A79<1,AL80=1),1,IF(AL80=1,A79,"")) -> 79 | C80: 44320 | D80: LINGFIELD PARK | E80: Flat | F80: Flat | G80: Hcap | H80: Open | J80: 4yo+ | K80: A | L80: 6 | N80: 46-60 | O80: 1m4f | P80: 1m 4f | Q80: 3900 | R80: BETWAY APP HCP STKS | S80: F | T80: South | U80: 1 | V80: App | AA80: =IF(OR(J80="2yo",J80="3yo"),J80,"Other") -> Other | AB80: =IF(K80="F",K80,"A") -> A | AC80: =VLOOKUP(P80,lists!$G:$H,2,FALSE) -> 7 | AD80: =VLOOKUP(G80,lists!$B$2:$C$3,2,FALSE) -> TRUE | AE80: =VLOOKUP(AA80,lists!$B:$C,2,FALSE) -> TRUE | AF80: =IF(AND(AC80>=VLOOKUP(FLAT!$I$1,lists!$G:$H,2,FALSE),AC80<=VLOOKUP(FLAT!$I$2,lists!$G:$H,2,FALSE)),TRUE,FALSE) -> TRUE | AG80: =VLOOKUP(AB80,lists!$B$7:$C$8,2,FALSE) -> TRUE | AH80: =VLOOKUP(IF(H80="","Open",SUBSTITUTE(H80,"/Nov","")),lists!$B$27:$D$29,2,FALSE) -> TRUE | AI80: =IF(FLAT!$I$5="All",TRUE,IF(FLAT!$I$5=TEXT('Raw - F'!C80,"mmm"),TRUE,FALSE)) -> TRUE | AJ80: =VLOOKUP(L80,lists!B:C,2,FALSE) -> TRUE | AK80: =VLOOKUP(T80,lists!$B$23:$D$25,2,FALSE) -> TRUE | AL80: =IF(AND(AD80=TRUE,AE80=TRUE,AF80=TRUE,AG80=TRUE,AH80=TRUE,AI80=TRUE,AJ80=TRUE,AK80=TRUE),1,0) -> 1
A81: =IF(B81="",A80,B81+1) -> 81 | B81: =IF(AND(A80<1,AL81=1),1,IF(AL81=1,A80,"")) -> 80 | C81: 44320 | D81: WOLVERHAMPTON | E81: Flat | F81: Flat | G81: WFA | H81: Nov | J81: 3yo+ | K81: A | L81: 4 | N81: Open | O81: 6f20y | P81: 5f | Q81: 6500 | R81: ATTHERACES NOV STKS | S81: C | T81: Midlands | U81: 1 | AA81: =IF(OR(J81="2yo",J81="3yo"),J81,"Other") -> Other | AB81: =IF(K81="F",K81,"A") -> A | AC81: =VLOOKUP(P81,lists!$G:$H,2,FALSE) -> 1 | AD81: =VLOOKUP(G81,lists!$B$2:$C$3,2,FALSE) -> TRUE | AE81: =VLOOKUP(AA81,lists!$B:$C,2,FALSE) -> TRUE | AF81: =IF(AND(AC81>=VLOOKUP(FLAT!$I$1,lists!$G:$H,2,FALSE),AC81<=VLOOKUP(FLAT!$I$2,lists!$G:$H,2,FALSE)),TRUE,FALSE) -> TRUE | AG81: =VLOOKUP(AB81,lists!$B$7:$C$8,2,FALSE) -> TRUE | AH81: =VLOOKUP(IF(H81="","Open",SUBSTITUTE(H81,"/Nov","")),lists!$B$27:$D$29,2,FALSE) -> TRUE | AI81: =IF(FLAT!$I$5="All",TRUE,IF(FLAT!$I$5=TEXT('Raw - F'!C81,"mmm"),TRUE,FALSE)) -> TRUE | AJ81: =VLOOKUP(L81,lists!B:C,2,FALSE) -> TRUE | AK81: =VLOOKUP(T81,lists!$B$23:$D$25,2,FALSE) -> TRUE | AL81: =IF(AND(AD81=TRUE,AE81=TRUE,AF81=TRUE,AG81=TRUE,AH81=TRUE,AI81=TRUE,AJ81=TRUE,AK81=TRUE),1,0) -> 1
A82: =IF(B82="",A81,B82+1) -> 82 | B82: =IF(AND(A81<1,AL82=1),1,IF(AL82=1,A81,"")) -> 81 | C82: 44320 | D82: WOLVERHAMPTON | E82: Flat | F82: Flat | G82: WFA | H82: Nov | J82: 3yo+ | K82: F | L82: 5 | N82: Open | O82: 7f36y | P82: 7f | Q82: 4900 | R82: SKY SPORTS NOV STKS | T82: Midlands | U82: 1 | AA82: =IF(OR(J82="2yo",J82="3yo"),J82,"Other") -> Other | AB82: =IF(K82="F",K82,"A") -> F | AC82: =VLOOKUP(P82,lists!$G:$H,2,FALSE) -> 3 | AD82: =VLOOKUP(G82,lists!$B$2:$C$3,2,FALSE) -> TRUE | AE82: =VLOOKUP(AA82,lists!$B:$C,2,FALSE) -> TRUE | AF82: =IF(AND(AC82>=VLOOKUP(FLAT!$I$1,lists!$G:$H,2,FALSE),AC82<=VLOOKUP(FLAT!$I$2,lists!$G:$H,2,FALSE)),TRUE,FALSE) -> TRUE | AG82: =VLOOKUP(AB82,lists!$B$7:$C$8,2,FALSE) -> TRUE | AH82: =VLOOKUP(IF(H82="","Open",SUBSTITUTE(H82,"/Nov","")),lists!$B$27:$D$29,2,FALSE) -> TRUE | AI82: =IF(FLAT!$I$5="All",TRUE,IF(FLAT!$I$5=TEXT('Raw - F'!C82,"mmm"),TRUE,FALSE)) -> TRUE | AJ82: =VLOOKUP(L82,lists!B:C,2,FALSE) -> TRUE | AK82: =VLOOKUP(T82,lists!$B$23:$D$25,2,FALSE) -> TRUE | AL82: =IF(AND(AD82=TRUE,AE82=TRUE,AF82=TRUE,AG82=TRUE,AH82=TRUE,AI82=TRUE,AJ82=TRUE,AK82=TRUE),1,0) -> 1
A83: =IF(B83="",A82,B83+1) -> 83 | B83: =IF(AND(A82<1,AL83=1),1,IF(AL83=1,A82,"")) -> 82 | C83: 44320 | D83: WOLVERHAMPTON | E83: Flat | F83: Flat | G83: Hcap | H83: Open | J83: 4yo+ | K83: A | L83: 6 | N83: 46-60 | O83: 1m5f219y | P83: 1m 6f | Q83: 3900 | R83: WOLVERHAMPTON HCP | T83: Midlands | U83: 1 | AA83: =IF(OR(J83="2yo",J83="3yo"),J83,"Other") -> Other | AB83: =IF(K83="F",K83,"A") -> A | AC83: =VLOOKUP(P83,lists!$G:$H,2,FALSE) -> 9 | AD83: =VLOOKUP(G83,lists!$B$2:$C$3,2,FALSE) -> TRUE | AE83: =VLOOKUP(AA83,lists!$B:$C,2,FALSE) -> TRUE | AF83: =IF(AND(AC83>=VLOOKUP(FLAT!$I$1,lists!$G:$H,2,FALSE),AC83<=VLOOKUP(FLAT!$I$2,lists!$G:$H,2,FALSE)),TRUE,FALSE) -> TRUE | AG83: =VLOOKUP(AB83,lists!$B$7:$C$8,2,FALSE) -> TRUE | AH83: =VLOOKUP(IF(H83="","Open",SUBSTITUTE(H83,"/Nov","")),lists!$B$27:$D$29,2,FALSE) -> TRUE | AI83: =IF(FLAT!$I$5="All",TRUE,IF(FLAT!$I$5=TEXT('Raw - F'!C83,"mmm"),TRUE,FALSE)) -> TRUE | AJ83: =VLOOKUP(L83,lists!B:C,2,FALSE) -> TRUE | AK83: =VLOOKUP(T83,lists!$B$23:$D$25,2,FALSE) -> TRUE | AL83: =IF(AND(AD83=TRUE,AE83=TRUE,AF83=TRUE,AG83=TRUE,AH83=TRUE,AI83=TRUE,AJ83=TRUE,AK83=TRUE),1,0) -> 1
A84: =IF(B84="",A83,B84+1) -> 84 | B84: =IF(AND(A83<1,AL84=1),1,IF(AL84=1,A83,"")) -> 83 | C84: 44320 | D84: WOLVERHAMPTON | E84: Flat | F84: Flat | G84: Hcap | H84: Open | J84: 4yo+ | K84: A | L84: 6 | N84: 46-65 | O84: 1m142y | P84: 1m | Q84: 3900 | R84: TWITTER HCP STKS | S84: C | T84: Midlands | U84: 1 | AA84: =IF(OR(J84="2yo",J84="3yo"),J84,"Other") -> Other | AB84: =IF(K84="F",K84,"A") -> A | AC84: =VLOOKUP(P84,lists!$G:$H,2,FALSE) -> 4 | AD84: =VLOOKUP(G84,lists!$B$2:$C$3,2,FALSE) -> TRUE | AE84: =VLOOKUP(AA84,lists!$B:$C,2,FALSE) -> TRUE | AF84: =IF(AND(AC84>=VLOOKUP(FLAT!$I$1,lists!$G:$H,2,FALSE),AC84<=VLOOKUP(FLAT!$I$2,lists!$G:$H,2,FALSE)),TRUE,FALSE) -> TRUE | AG84: =VLOOKUP(AB84,lists!$B$7:$C$8,2,FALSE) -> TRUE | AH84: =VLOOKUP(IF(H84="","Open",SUBSTITUTE(H84,"/Nov","")),lists!$B$27:$D$29,2,FALSE) -> TRUE | AI84: =IF(FLAT!$I$5="All",TRUE,IF(FLAT!$I$5=TEXT('Raw - F'!C84,"mmm"),TRUE,FALSE)) -> TRUE | AJ84: =VLOOKUP(L84,lists!B:C,2,FALSE) -> TRUE | AK84: =VLOOKUP(T84,lists!$B$23:$D$25,2,FALSE) -> TRUE | AL84: =IF(AND(AD84=TRUE,AE84=TRUE,AF84=TRUE,AG84=TRUE,AH84=TRUE,AI84=TRUE,AJ84=TRUE,AK84=TRUE),1,0) -> 1
A85: =IF(B85="",A84,B85+1) -> 85 | B85: =IF(AND(A84<1,AL85=1),1,IF(AL85=1,A84,"")) -> 84 | C85: 44320 | D85: WOLVERHAMPTON | E85: Flat | F85: Flat | G85: Hcap | H85: Open | J85: 4yo+ | K85: A | L85: 6 | N85: 46-60 | O85: 1m4f51y | P85: 7f | Q85: 3900 | R85: PUSSYCAT HCAP STKS | S85: F | T85: Midlands | U85: 1 | AA85: =IF(OR(J85="2yo",J85="3yo"),J85,"Other") -> Other | AB85: =IF(K85="F",K85,"A") -> A | AC85: =VLOOKUP(P85,lists!$G:$H,2,FALSE) -> 3 | AD85: =VLOOKUP(G85,lists!$B$2:$C$3,2,FALSE) -> TRUE | AE85: =VLOOKUP(AA85,lists!$B:$C,2,FALSE) -> TRUE | AF85: =IF(AND(AC85>=VLOOKUP(FLAT!$I$1,lists!$G:$H,2,FALSE),AC85<=VLOOKUP(FLAT!$I$2,lists!$G:$H,2,FALSE)),TRUE,FALSE) -> TRUE | AG85: =VLOOKUP(AB85,lists!$B$7:$C$8,2,FALSE) -> TRUE | AH85: =VLOOKUP(IF(H85="","Open",SUBSTITUTE(H85,"/Nov","")),lists!$B$27:$D$29,2,FALSE) -> TRUE | AI85: =IF(FLAT!$I$5="All",TRUE,IF(FLAT!$I$5=TEXT('Raw - F'!C85,"mmm"),TRUE,FALSE)) -> TRUE | AJ85: =VLOOKUP(L85,lists!B:C,2,FALSE) -> TRUE | AK85: =VLOOKUP(T85,lists!$B$23:$D$25,2,FALSE) -> TRUE | AL85: =IF(AND(AD85=TRUE,AE85=TRUE,AF85=TRUE,AG85=TRUE,AH85=TRUE,AI85=TRUE,AJ85=TRUE,AK85=TRUE),1,0) -> 1
A86: =IF(B86="",A85,B86+1) -> 86 | B86: =IF(AND(A85<1,AL86=1),1,IF(AL86=1,A85,"")) -> 85 | C86: 44320 | D86: WOLVERHAMPTON | E86: Flat | F86: Flat | G86: Hcap | H86: Open | J86: 3yo | K86: A | L86: 6 | N86: 46-65 | O86: 1m142y | P86: 1m | Q86: 3900 | R86: L. PAYNE HCAP STKS | S86: C | T86: Midlands | U86: 1 | AA86: =IF(OR(J86="2yo",J86="3yo"),J86,"Other") -> 3yo | AB86: =IF(K86="F",K86,"A") -> A | AC86: =VLOOKUP(P86,lists!$G:$H,2,FALSE) -> 4 | AD86: =VLOOKUP(G86,lists!$B$2:$C$3,2,FALSE) -> TRUE | AE86: =VLOOKUP(AA86,lists!$B:$C,2,FALSE) -> TRUE | AF86: =IF(AND(AC86>=VLOOKUP(FLAT!$I$1,lists!$G:$H,2,FALSE),AC86<=VLOOKUP(FLAT!$I$2,lists!$G:$H,2,FALSE)),TRUE,FALSE) -> TRUE | AG86: =VLOOKUP(AB86,lists!$B$7:$C$8,2,FALSE) -> TRUE | AH86: =VLOOKUP(IF(H86="","Open",SUBSTITUTE(H86,"/Nov","")),lists!$B$27:$D$29,2,FALSE) -> TRUE | AI86: =IF(FLAT!$I$5="All",TRUE,IF(FLAT!$I$5=TEXT('Raw - F'!C86,"mmm"),TRUE,FALSE)) -> TRUE | AJ86: =VLOOKUP(L86,lists!B:C,2,FALSE) -> TRUE | AK86: =VLOOKUP(T86,lists!$B$23:$D$25,2,FALSE) -> TRUE | AL86: =IF(AND(AD86=TRUE,AE86=TRUE,AF86=TRUE,AG86=TRUE,AH86=TRUE,AI86=TRUE,AJ86=TRUE,AK86=TRUE),1,0) -> 1
A87: =IF(B87="",A86,B87+1) -> 87 | B87: =IF(AND(A86<1,AL87=1),1,IF(AL87=1,A86,"")) -> 86 | C87: 44320 | D87: WOLVERHAMPTON | E87: Flat | F87: Flat | G87: Hcap | H87: Open | J87: 3yo | K87: A | L87: 6 | N87: 46-60 | O87: 5f21y | P87: 5f | Q87: 3900 | R87: NAME A RACE HCAP | S87: C | T87: Midlands | U87: 1 | AA87: =IF(OR(J87="2yo",J87="3yo"),J87,"Other") -> 3yo | AB87: =IF(K87="F",K87,"A") -> A | AC87: =VLOOKUP(P87,lists!$G:$H,2,FALSE) -> 1 | AD87: =VLOOKUP(G87,lists!$B$2:$C$3,2,FALSE) -> TRUE | AE87: =VLOOKUP(AA87,lists!$B:$C,2,FALSE) -> TRUE | AF87: =IF(AND(AC87>=VLOOKUP(FLAT!$I$1,lists!$G:$H,2,FALSE),AC87<=VLOOKUP(FLAT!$I$2,lists!$G:$H,2,FALSE)),TRUE,FALSE) -> TRUE | AG87: =VLOOKUP(AB87,lists!$B$7:$C$8,2,FALSE) -> TRUE | AH87: =VLOOKUP(IF(H87="","Open",SUBSTITUTE(H87,"/Nov","")),lists!$B$27:$D$29,2,FALSE) -> TRUE | AI87: =IF(FLAT!$I$5="All",TRUE,IF(FLAT!$I$5=TEXT('Raw - F'!C87,"mmm"),TRUE,FALSE)) -> TRUE | AJ87: =VLOOKUP(L87,lists!B:C,2,FALSE) -> TRUE | AK87: =VLOOKUP(T87,lists!$B$23:$D$25,2,FALSE) -> TRUE | AL87: =IF(AND(AD87=TRUE,AE87=TRUE,AF87=TRUE,AG87=TRUE,AH87=TRUE,AI87=TRUE,AJ87=TRUE,AK87=TRUE),1,0) -> 1
A88: =IF(B88="",A87,B88+1) -> 88 | B88: =IF(AND(A87<1,AL88=1),1,IF(AL88=1,A87,"")) -> 87 | C88: 44321 | D88: CHESTER | E88: Flat | F88: Flat | G88: WFA | H88: Open | J88: 3yo | K88: C | L88: 1 | M88: 1(G3) | N88: Open | O88: 1m4f63y | P88: 1m 4f | Q88: 60000 | R88: CHESTER VASE STKS | T88: Midlands | U88: 0 | AA88: =IF(OR(J88="2yo",J88="3yo"),J88,"Other") -> 3yo | AB88: =IF(K88="F",K88,"A") -> A | AC88: =VLOOKUP(P88,lists!$G:$H,2,FALSE) -> 7 | AD88: =VLOOKUP(G88,lists!$B$2:$C$3,2,FALSE) -> TRUE | AE88: =VLOOKUP(AA88,lists!$B:$C,2,FALSE) -> TRUE | AF88: =IF(AND(AC88>=VLOOKUP(FLAT!$I$1,lists!$G:$H,2,FALSE),AC88<=VLOOKUP(FLAT!$I$2,lists!$G:$H,2,FALSE)),TRUE,FALSE) -> TRUE | AG88: =VLOOKUP(AB88,lists!$B$7:$C$8,2,FALSE) -> TRUE | AH88: =VLOOKUP(IF(H88="","Open",SUBSTITUTE(H88,"/Nov","")),lists!$B$27:$D$29,2,FALSE) -> TRUE | AI88: =IF(FLAT!$I$5="All",TRUE,IF(FLAT!$I$5=TEXT('Raw - F'!C88,"mmm"),TRUE,FALSE)) -> TRUE | AJ88: =VLOOKUP(L88,lists!B:C,2,FALSE) -> TRUE | AK88: =VLOOKUP(T88,lists!$B$23:$D$25,2,FALSE) -> TRUE | AL88: =IF(AND(AD88=TRUE,AE88=TRUE,AF88=TRUE,AG88=TRUE,AH88=TRUE,AI88=TRUE,AJ88=TRUE,AK88=TRUE),1,0) -> 1
A89: =IF(B89="",A88,B89+1) -> 89 | B89: =IF(AND(A88<1,AL89=1),1,IF(AL89=1,A88,"")) -> 88 | C89: 44321 | D89: CHESTER | E89: Flat | F89: Flat | G89: WFA | H89: Open | J89: 3yo | K89: F | L89: 1 | M89: 1(Lstd) | N89: Open | O89: 1m3f75y | P89: 1m 3f | Q89: 37000 | R89: CHESHIRE OAKS STKS | T89: Midlands | U89: 0 | AA89: =IF(OR(J89="2yo",J89="3yo"),J89,"Other") -> 3yo | AB89: =IF(K89="F",K89,"A") -> F | AC89: =VLOOKUP(P89,lists!$G:$H,2,FALSE) -> 6 | AD89: =VLOOKUP(G89,lists!$B$2:$C$3,2,FALSE) -> TRUE | AE89: =VLOOKUP(AA89,lists!$B:$C,2,FALSE) -> TRUE | AF89: =IF(AND(AC89>=VLOOKUP(FLAT!$I$1,lists!$G:$H,2,FALSE),AC89<=VLOOKUP(FLAT!$I$2,lists!$G:$H,2,FALSE)),TRUE,FALSE) -> TRUE | AG89: =VLOOKUP(AB89,lists!$B$7:$C$8,2,FALSE) -> TRUE | AH89: =VLOOKUP(IF(H89="","Open",SUBSTITUTE(H89,"/Nov","")),lists!$B$27:$D$29,2,FALSE) -> TRUE | AI89: =IF(FLAT!$I$5="All",TRUE,IF(FLAT!$I$5=TEXT('Raw - F'!C89,"mmm"),TRUE,FALSE)) -> TRUE | AJ89: =VLOOKUP(L89,lists!B:C,2,FALSE) -> TRUE | AK89: =VLOOKUP(T89,lists!$B$23:$D$25,2,FALSE) -> TRUE | AL89: =IF(AND(AD89=TRUE,AE89=TRUE,AF89=TRUE,AG89=TRUE,AH89=TRUE,AI89=TRUE,AJ89=TRUE,AK89=TRUE),1,0) -> 1
A90: =IF(B90="",A89,B90+1) -> 90 | B90: =IF(AND(A89<1,AL90=1),1,IF(AL90=1,A89,"")) -> 89 | C90: 44321 | D90: CHESTER | E90: Flat | F90: Flat | G90: Hcap | H90: Open | J90: 3yo | K90: A | L90: 2 | N90: 86-105 | O90: 5f15y | P90: 5f | Q90: 19000 | R90: BOODLES HCAP STKS | T90: Midlands | U90: 0 | AA90: =IF(OR(J90="2yo",J90="3yo"),J90,"Other") -> 3yo | AB90: =IF(K90="F",K90,"A") -> A | AC90: =VLOOKUP(P90,lists!$G:$H,2,FALSE) -> 1 | AD90: =VLOOKUP(G90,lists!$B$2:$C$3,2,FALSE) -> TRUE | AE90: =VLOOKUP(AA90,lists!$B:$C,2,FALSE) -> TRUE | AF90: =IF(AND(AC90>=VLOOKUP(FLAT!$I$1,lists!$G:$H,2,FALSE),AC90<=VLOOKUP(FLAT!$I$2,lists!$G:$H,2,FALSE)),TRUE,FALSE) -> TRUE | AG90: =VLOOKUP(AB90,lists!$B$7:$C$8,2,FALSE) -> TRUE | AH90: =VLOOKUP(IF(H90="","Open",SUBSTITUTE(H90,"/Nov","")),lists!$B$27:$D$29,2,FALSE) -> TRUE | AI90: =IF(FLAT!$I$5="All",TRUE,IF(FLAT!$I$5=TEXT('Raw - F'!C90,"mmm"),TRUE,FALSE)) -> TRUE | AJ90: =VLOOKUP(L90,lists!B:C,2,FALSE) -> TRUE | AK90: =VLOOKUP(T90,lists!$B$23:$D$25,2,FALSE) -> TRUE | AL90: =IF(AND(AD90=TRUE,AE90=TRUE,AF90=TRUE,AG90=TRUE,AH90=TRUE,AI90=TRUE,AJ90=TRUE,AK90=TRUE),1,0) -> 1
A91: =IF(B91="",A90,B91+1) -> 91 | B91: =IF(AND(A90<1,AL91=1),1,IF(AL91=1,A90,"")) -> 90 | C91: 44321 | D91: CHESTER | E91: Flat | F91: Flat | G91: WFA | H91: Open | I91: Conditions | J91: 2yo | K91: A | L91: 2 | N91: Open | O91: 5f15y | P91: 5f | Q91: 14000 | R91: LILY AGNES STKS | T91: Midlands | U91: 0 | AA91: =IF(OR(J91="2yo",J91="3yo"),J91,"Other") -> 2yo | AB91: =IF(K91="F",K91,"A") -> A | AC91: =VLOOKUP(P91,lists!$G:$H,2,FALSE) -> 1 | AD91: =VLOOKUP(G91,lists!$B$2:$C$3,2,FALSE) -> TRUE | AE91: =VLOOKUP(AA91,lists!$B:$C,2,FALSE) -> TRUE | AF91: =IF(AND(AC91>=VLOOKUP(FLAT!$I$1,lists!$G:$H,2,FALSE),AC91<=VLOOKUP(FLAT!$I$2,lists!$G:$H,2,FALSE)),TRUE,FALSE) -> TRUE | AG91: =VLOOKUP(AB91,lists!$B$7:$C$8,2,FALSE) -> TRUE | AH91: =VLOOKUP(IF(H91="","Open",SUBSTITUTE(H91,"/Nov","")),lists!$B$27:$D$29,2,FALSE) -> TRUE | AI91: =IF(FLAT!$I$5="All",TRUE,IF(FLAT!$I$5=TEXT('Raw - F'!C91,"mmm"),TRUE,FALSE)) -> TRUE | AJ91: =VLOOKUP(L91,lists!B:C,2,FALSE) -> TRUE | AK91: =VLOOKUP(T91,lists!$B$23:$D$25,2,FALSE) -> TRUE | AL91: =IF(AND(AD91=TRUE,AE91=TRUE,AF91=TRUE,AG91=TRUE,AH91=TRUE,AI91=TRUE,AJ91=TRUE,AK91=TRUE),1,0) -> 1
A92: =IF(B92="",A91,B92+1) -> 92 | B92: =IF(AND(A91<1,AL92=1),1,IF(AL92=1,A91,"")) -> 91 | C92: 44321 | D92: CHESTER | E92: Flat | F92: Flat | G92: WFA | H92: Mdn | J92: 3yo | K92: A | L92: 3 | N92: Open | O92: 1m2f70y | P92: 1m 2f | Q92: 11500 | R92: SPORTPESA MDN STKS | T92: Midlands | U92: 0 | AA92: =IF(OR(J92="2yo",J92="3yo"),J92,"Other") -> 3yo | AB92: =IF(K92="F",K92,"A") -> A | AC92: =VLOOKUP(P92,lists!$G:$H,2,FALSE) -> 5 | AD92: =VLOOKUP(G92,lists!$B$2:$C$3,2,FALSE) -> TRUE | AE92: =VLOOKUP(AA92,lists!$B:$C,2,FALSE) -> TRUE | AF92: =IF(AND(AC92>=VLOOKUP(FLAT!$I$1,lists!$G:$H,2,FALSE),AC92<=VLOOKUP(FLAT!$I$2,lists!$G:$H,2,FALSE)),TRUE,FALSE) -> TRUE | AG92: =VLOOKUP(AB92,lists!$B$7:$C$8,2,FALSE) -> TRUE | AH92: =VLOOKUP(IF(H92="","Open",SUBSTITUTE(H92,"/Nov","")),lists!$B$27:$D$29,2,FALSE) -> TRUE | AI92: =IF(FLAT!$I$5="All",TRUE,IF(FLAT!$I$5=TEXT('Raw - F'!C92,"mmm"),TRUE,FALSE)) -> TRUE | AJ92: =VLOOKUP(L92,lists!B:C,2,FALSE) -> TRUE | AK92: =VLOOKUP(T92,lists!$B$23:$D$25,2,FALSE) -> TRUE | AL92: =IF(AND(AD92=TRUE,AE92=TRUE,AF92=TRUE,AG92=TRUE,AH92=TRUE,AI92=TRUE,AJ92=TRUE,AK92=TRUE),1,0) -> 1
A93: =IF(B93="",A92,B93+1) -> 93 | B93: =IF(AND(A92<1,AL93=1),1,IF(AL93=1,A92,"")) -> 92 | C93: 44321 | D93: CHESTER | E93: Flat | F93: Flat | G93: Hcap | H93: Open | J93: 3yo | K93: A | L93: 3 | N93: 76-95 | O93: 6f17y | P93: 6f | Q93: 11500 | R93: HOMESERVE HCAP STKS | T93: Midlands | U93: 0 | AA93: =IF(OR(J93="2yo",J93="3yo"),J93,"Other") -> 3yo | AB93: =IF(K93="F",K93,"A") -> A | AC93: =VLOOKUP(P93,lists!$G:$H,2,FALSE) -> 2 | AD93: =VLOOKUP(G93,lists!$B$2:$C$3,2,FALSE) -> TRUE | AE93: =VLOOKUP(AA93,lists!$B:$C,2,FALSE) -> TRUE | AF93: =IF(AND(AC93>=VLOOKUP(FLAT!$I$1,lists!$G:$H,2,FALSE),AC93<=VLOOKUP(FLAT!$I$2,lists!$G:$H,2,FALSE)),TRUE,FALSE) -> TRUE | AG93: =VLOOKUP(AB93,lists!$B$7:$C$8,2,FALSE) -> TRUE | AH93: =VLOOKUP(IF(H93="","Open",SUBSTITUTE(H93,"/Nov","")),lists!$B$27:$D$29,2,FALSE) -> TRUE | AI93: =IF(FLAT!$I$5="All",TRUE,IF(FLAT!$I$5=TEXT('Raw - F'!C93,"mmm"),TRUE,FALSE)) -> TRUE | AJ93: =VLOOKUP(L93,lists!B:C,2,FALSE) -> TRUE | AK93: =VLOOKUP(T93,lists!$B$23:$D$25,2,FALSE) -> TRUE | AL93: =IF(AND(AD93=TRUE,AE93=TRUE,AF93=TRUE,AG93=TRUE,AH93=TRUE,AI93=TRUE,AJ93=TRUE,AK93=TRUE),1,0) -> 1
A94: =IF(B94="",A93,B94+1) -> 94 | B94: =IF(AND(A93<1,AL94=1),1,IF(AL94=1,A93,"")) -> 93 | C94: 44321 | D94: CHESTER | E94: Flat | F94: Flat | G94: Hcap | H94: Open | J94: 4yo+ | K94: A | L94: 4 | N94: 66-85 | O94: 7f1y | P94: 7f | Q94: 7250 | R94: HR OWEN HCAP STKS | T94: Midlands | U94: 0 | AA94: =IF(OR(J94="2yo",J94="3yo"),J94,"Other") -> Other | AB94: =IF(K94="F",K94,"A") -> A | AC94: =VLOOKUP(P94,lists!$G:$H,2,FALSE) -> 3 | AD94: =VLOOKUP(G94,lists!$B$2:$C$3,2,FALSE) -> TRUE | AE94: =VLOOKUP(AA94,lists!$B:$C,2,FALSE) -> TRUE | AF94: =IF(AND(AC94>=VLOOKUP(FLAT!$I$1,lists!$G:$H,2,FALSE),AC94<=VLOOKUP(FLAT!$I$2,lists!$G:$H,2,FALSE)),TRUE,FALSE) -> TRUE | AG94: =VLOOKUP(AB94,lists!$B$7:$C$8,2,FALSE) -> TRUE | AH94: =VLOOKUP(IF(H94="","Open",SUBSTITUTE(H94,"/Nov","")),lists!$B$27:$D$29,2,FALSE) -> TRUE | AI94: =IF(FLAT!$I$5="All",TRUE,IF(FLAT!$I$5=TEXT('Raw - F'!C94,"mmm"),TRUE,FALSE)) -> TRUE | AJ94: =VLOOKUP(L94,lists!B:C,2,FALSE) -> TRUE | AK94: =VLOOKUP(T94,lists!$B$23:$D$25,2,FALSE) -> TRUE | AL94: =IF(AND(AD94=TRUE,AE94=TRUE,AF94=TRUE,AG94=TRUE,AH94=TRUE,AI94=TRUE,AJ94=TRUE,AK94=TRUE),1,0) -> 1
A95: =IF(B95="",A94,B95+1) -> 95 | B95: =IF(AND(A94<1,AL95=1),1,IF(AL95=1,A94,"")) -> 94 | C95: 44321 | D95: KEMPTON PARK | E95: Flat | F95: Flat | G95: Hcap | H95: Open | J95: 4yo+ | K95: A | L95: 3 | N95: 76-95 | O95: 1m | P95: 7f | Q95: 11500 | R95: 32RED HCAP STKS | T95: South | U95: 1 | AA95: =IF(OR(J95="2yo",J95="3yo"),J95,"Other") -> Other | AB95: =IF(K95="F",K95,"A") -> A | AC95: =VLOOKUP(P95,lists!$G:$H,2,FALSE) -> 3 | AD95: =VLOOKUP(G95,lists!$B$2:$C$3,2,FALSE) -> TRUE | AE95: =VLOOKUP(AA95,lists!$B:$C,2,FALSE) -> TRUE | AF95: =IF(AND(AC95>=VLOOKUP(FLAT!$I$1,lists!$G:$H,2,FALSE),AC95<=VLOOKUP(FLAT!$I$2,lists!$G:$H,2,FALSE)),TRUE,FALSE) -> TRUE | AG95: =VLOOKUP(AB95,lists!$B$7:$C$8,2,FALSE) -> TRUE | AH95: =VLOOKUP(IF(H95="","Open",SUBSTITUTE(H95,"/Nov","")),lists!$B$27:$D$29,2,FALSE) -> TRUE | AI95: =IF(FLAT!$I$5="All",TRUE,IF(FLAT!$I$5=TEXT('Raw - F'!C95,"mmm"),TRUE,FALSE)) -> TRUE | AJ95: =VLOOKUP(L95,lists!B:C,2,FALSE) -> TRUE | AK95: =VLOOKUP(T95,lists!$B$23:$D$25,2,FALSE) -> TRUE | AL95: =IF(AND(AD95=TRUE,AE95=TRUE,AF95=TRUE,AG95=TRUE,AH95=TRUE,AI95=TRUE,AJ95=TRUE,AK95=TRUE),1,0) -> 1
A96: =IF(B96="",A95,B96+1) -> 96 | B96: =IF(AND(A95<1,AL96=1),1,IF(AL96=1,A95,"")) -> 95 | C96: 44321 | D96: KEMPTON PARK | E96: Flat | F96: Flat | G96: Hcap | H96: Open | J96: 4yo+ | K96: A | L96: 5 | N96: 56-75 | O96: 7f | P96: 7f | Q96: 7650 | R96: 32RED.COM HCAP STKS | T96: South | U96: 1 | AA96: =IF(OR(J96="2yo",J96="3yo"),J96,"Other") -> Other | AB96: =IF(K96="F",K96,"A") -> A | AC96: =VLOOKUP(P96,lists!$G:$H,2,FALSE) -> 3 | AD96: =VLOOKUP(G96,lists!$B$2:$C$3,2,FALSE) -> TRUE | AE96: =VLOOKUP(AA96,lists!$B:$C,2,FALSE) -> TRUE | AF96: =IF(AND(AC96>=VLOOKUP(FLAT!$I$1,lists!$G:$H,2,FALSE),AC96<=VLOOKUP(FLAT!$I$2,lists!$G:$H,2,FALSE)),TRUE,FALSE) -> TRUE | AG96: =VLOOKUP(AB96,lists!$B$7:$C$8,2,FALSE) -> TRUE | AH96: =VLOOKUP(IF(H96="","Open",SUBSTITUTE(H96,"/Nov","")),lists!$B$27:$D$29,2,FALSE) -> TRUE | AI96: =IF(FLAT!$I$5="All",TRUE,IF(FLAT!$I$5=TEXT('Raw - F'!C96,"mmm"),TRUE,FALSE)) -> TRUE | AJ96: =VLOOKUP(L96,lists!B:C,2,FALSE) -> TRUE | AK96: =VLOOKUP(T96,lists!$B$23:$D$25,2,FALSE) -> TRUE | AL96: =IF(AND(AD96=TRUE,AE96=TRUE,AF96=TRUE,AG96=TRUE,AH96=TRUE,AI96=TRUE,AJ96=TRUE,AK96=TRUE),1,0) -> 1
A97: =IF(B97="",A96,B97+1) -> 97 | B97: =IF(AND(A96<1,AL97=1),1,IF(AL97=1,A96,"")) -> 96 | C97: 44321 | D97: KEMPTON PARK | E97: Flat | F97: Flat | G97: Hcap | H97: Open | J97: 4yo+ | K97: F | L97: 5 | N97: 56-75 | O97: 6f | P97: 6f | Q97: 7650 | R97: APP STORE HCAP STKS | T97: South | U97: 1 | AA97: =IF(OR(J97="2yo",J97="3yo"),J97,"Other") -> Other | AB97: =IF(K97="F",K97,"A") -> F | AC97: =VLOOKUP(P97,lists!$G:$H,2,FALSE) -> 2 | AD97: =VLOOKUP(G97,lists!$B$2:$C$3,2,FALSE) -> TRUE | AE97: =VLOOKUP(AA97,lists!$B:$C,2,FALSE) -> TRUE | AF97: =IF(AND(AC97>=VLOOKUP(FLAT!$I$1,lists!$G:$H,2,FALSE),AC97<=VLOOKUP(FLAT!$I$2,lists!$G:$H,2,FALSE)),TRUE,FALSE) -> TRUE | AG97: =VLOOKUP(AB97,lists!$B$7:$C$8,2,FALSE) -> TRUE | AH97: =VLOOKUP(IF(H97="","Open",SUBSTITUTE(H97,"/Nov","")),lists!$B$27:$D$29,2,FALSE) -> TRUE | AI97: =IF(FLAT!$I$5="All",TRUE,IF(FLAT!$I$5=TEXT('Raw - F'!C97,"mmm"),TRUE,FALSE)) -> TRUE | AJ97: =VLOOKUP(L97,lists!B:C,2,FALSE) -> TRUE | AK97: =VLOOKUP(T97,lists!$B$23:$D$25,2,FALSE) -> TRUE | AL97: =IF(AND(AD97=TRUE,AE97=TRUE,AF97=TRUE,AG97=TRUE,AH97=TRUE,AI97=TRUE,AJ97=TRUE,AK97=TRUE),1,0) -> 1
A98: =IF(B98="",A97,B98+1) -> 98 | B98: =IF(AND(A97<1,AL98=1),1,IF(AL98=1,A97,"")) -> 97 | C98: 44321 | D98: KEMPTON PARK | E98: Flat | F98: Flat | G98: Hcap | H98: Open | J98: 4yo+ | K98: A | L98: 5 | N98: 51-70 | O98: 1m7f218y | P98: 2m+ | Q98: 7650 | R98: CASINO HCAP STKS | T98: South | U98: 1 | AA98: =IF(OR(J98="2yo",J98="3yo"),J98,"Other") -> Other | AB98: =IF(K98="F",K98,"A") -> A | AC98: =VLOOKUP(P98,lists!$G:$H,2,FALSE) -> 11 | AD98: =VLOOKUP(G98,lists!$B$2:$C$3,2,FALSE) -> TRUE | AE98: =VLOOKUP(AA98,lists!$B:$C,2,FALSE) -> TRUE | AF98: =IF(AND(AC98>=VLOOKUP(FLAT!$I$1,lists!$G:$H,2,FALSE),AC98<=VLOOKUP(FLAT!$I$2,lists!$G:$H,2,FALSE)),TRUE,FALSE) -> TRUE | AG98: =VLOOKUP(AB98,lists!$B$7:$C$8,2,FALSE) -> TRUE | AH98: =VLOOKUP(IF(H98="","Open",SUBSTITUTE(H98,"/Nov","")),lists!$B$27:$D$29,2,FALSE) -> TRUE | AI98: =IF(FLAT!$I$5="All",TRUE,IF(FLAT!$I$5=TEXT('Raw - F'!C98,"mmm"),TRUE,FALSE)) -> TRUE | AJ98: =VLOOKUP(L98,lists!B:C,2,FALSE) -> TRUE | AK98: =VLOOKUP(T98,lists!$B$23:$D$25,2,FALSE) -> TRUE | AL98: =IF(AND(AD98=TRUE,AE98=TRUE,AF98=TRUE,AG98=TRUE,AH98=TRUE,AI98=TRUE,AJ98=TRUE,AK98=TRUE),1,0) -> 1
A99: =IF(B99="",A98,B99+1) -> 99 | B99: =IF(AND(A98<1,AL99=1),1,IF(AL99=1,A98,"")) -> 98 | C99: 44321 | D99: KEMPTON PARK | E99: Flat | F99: Flat | G99: WFA | H99: Nov | J99: 3yo+ | K99: F | L99: 5 | N99: Open | O99: 1m3f219y | P99: 1m 4f | Q99: 4900 | R99: 32REDSPORT NOV STKS | T99: South | U99: 1 | AA99: =IF(OR(J99="2yo",J99="3yo"),J99,"Other") -> Other | AB99: =IF(K99="F",K99,"A") -> F | AC99: =VLOOKUP(P99,lists!$G:$H,2,FALSE) -> 7 | AD99: =VLOOKUP(G99,lists!$B$2:$C$3,2,FALSE) -> TRUE | AE99: =VLOOKUP(AA99,lists!$B:$C,2,FALSE) -> TRUE | AF99: =IF(AND(AC99>=VLOOKUP(FLAT!$I$1,lists!$G:$H,2,FALSE),AC99<=VLOOKUP(FLAT!$I$2,lists!$G:$H,2,FALSE)),TRUE,FALSE) -> TRUE | AG99: =VLOOKUP(AB99,lists!$B$7:$C$8,2,FALSE) -> TRUE | AH99: =VLOOKUP(IF(H99="","Open",SUBSTITUTE(H99,"/Nov","")),lists!$B$27:$D$29,2,FALSE) -> TRUE | AI99: =IF(FLAT!$I$5="All",TRUE,IF(FLAT!$I$5=TEXT('Raw - F'!C99,"mmm"),TRUE,FALSE)) -> TRUE | AJ99: =VLOOKUP(L99,lists!B:C,2,FALSE) -> TRUE | AK99: =VLOOKUP(T99,lists!$B$23:$D$25,2,FALSE) -> TRUE | AL99: =IF(AND(AD99=TRUE,AE99=TRUE,AF99=TRUE,AG99=TRUE,AH99=TRUE,AI99=TRUE,AJ99=TRUE,AK99=TRUE),1,0) -> 1
A100: =IF(B100="",A99,B100+1) -> 100 | B100: =IF(AND(A99<1,AL100=1),1,IF(AL100=1,A99,"")) -> 99 | C100: 44321 | D100: KEMPTON PARK | E100: Flat | F100: Flat | G100: WFA | H100: Nov | J100: 2yo | K100: F | L100: 4 | N100: Open | O100: 6f | P100: 5f | Q100: 4900 | R100: RACINGTV NOV STKS | T100: South | U100: 1 | X100: Rest. | Y100: B | Z100: EBF | AA100: =IF(OR(J100="2yo",J100="3yo"),J100,"Other") -> 2yo | AB100: =IF(K100="F",K100,"A") -> F | AC100: =VLOOKUP(P100,lists!$G:$H,2,FALSE) -> 1 | AD100: =VLOOKUP(G100,lists!$B$2:$C$3,2,FALSE) -> TRUE | AE100: =VLOOKUP(AA100,lists!$B:$C,2,FALSE) -> TRUE | AF100: =IF(AND(AC100>=VLOOKUP(FLAT!$I$1,lists!$G:$H,2,FALSE),AC100<=VLOOKUP(FLAT!$I$2,lists!$G:$H,2,FALSE)),TRUE,FALSE) -> TRUE | AG100: =VLOOKUP(AB100,lists!$B$7:$C$8,2,FALSE) -> TRUE | AH100: =VLOOKUP(IF(H100="","Open",SUBSTITUTE(H100,"/Nov","")),lists!$B$27:$D$29,2,FALSE) -> TRUE | AI100: =IF(FLAT!$I$5="All",TRUE,IF(FLAT!$I$5=TEXT('Raw - F'!C100,"mmm"),TRUE,FALSE)) -> TRUE | AJ100: =VLOOKUP(L100,lists!B:C,2,FALSE) -> TRUE | AK100: =VLOOKUP(T100,lists!$B$23:$D$25,2,FALSE) -> TRUE | AL100: =IF(AND(AD100=TRUE,AE100=TRUE,AF100=TRUE,AG100=TRUE,AH100=TRUE,AI100=TRUE,AJ100=TRUE,AK100=TRUE),1,0) -> 1
...

Sheet Raw - J
C1: Date | D1: Course | E1: Code | F1: Jump Type | G1: Type | H1: M/N | I1: RD | J1: NH Restricted | K1: Age | L1: Sex | M1: Class | N1: PL | O1: RB | P1: Distance | Q1: Distance Category | R1: RaceValue | S1: Race Name | T1: Region | U1: Rider | V1: SC | W1: Auc | X1: AucVal | Y1: Sex classification | Z1: Dist rank | AA1: HC inc | AB1: JT inc | AC1: Dist inc | AD1: Sex inc | AE1: Mdn/Nov | AF1: Month inc | AG1: Class inc | AH1: Region inc | AI1: INCLUDE?
A2: =IF(B2="",A1,B2+1) -> 2 | B2: =IF(AND(A1<1,AI2=1),1,IF(AI2=1,A1,"")) -> 1 | C2: 44317 | D2: HEXHAM | E2: Jump | F2: Hurdle | G2: WFA | H2: Open | K2: 4yo+ | L2: A | M2: 4 | O2: Open | P2: 2m48y | Q2: 2m | R2: 5900 | S2: CAMPBELL SELL HUR | T2: North | V2: S | X2: 0 | Y2: =IF(L2="F",L2,"A") -> A | Z2: =VLOOKUP(Q2,lists!Q:R,2,FALSE) -> 2 | AA2: =VLOOKUP(G2,lists!$B$2:$D$3,3,FALSE) -> TRUE | AB2: =VLOOKUP(F2,lists!$B:$C,2,FALSE) -> TRUE | AC2: =IF(AND(Z2>=VLOOKUP(JUMP!$I$1,lists!$Q:$R,2,FALSE),Z2<=VLOOKUP(JUMP!$I$2,lists!$Q:$R,2,FALSE)),TRUE,FALSE) -> TRUE | AD2: =VLOOKUP(Y2,lists!$B$7:$D$8,3,FALSE) -> TRUE | AE2: =VLOOKUP(SUBSTITUTE(IF(H2="","Open",H2),"Beg","Mdn"),lists!$B$27:$D$29,3,FALSE) -> TRUE | AF2: =IF(JUMP!$I$5="All",TRUE,IF(JUMP!$I$5=TEXT('Raw - J'!C2,"mmm"),TRUE,FALSE)) -> TRUE | AG2: =VLOOKUP(M2,lists!B:D,3,FALSE) -> TRUE | AH2: =VLOOKUP(T2,lists!$B$23:$D$25,3,FALSE) -> TRUE | AI2: =IF(AND(AA2=TRUE,AB2=TRUE,AC2=TRUE,AD2=TRUE,AE2=TRUE,AF2=TRUE,AG2=TRUE,AH2=TRUE),1,0) -> 1
A3: =IF(B3="",A2,B3+1) -> 3 | B3: =IF(AND(A2<1,AI3=1),1,IF(AI3=1,A2,"")) -> 2 | C3: 44317 | D3: HEXHAM | E3: Jump | F3: Hurdle | G3: WFA | H3: Nov | K3: 4yo+ | L3: A | M3: 4 | O3: Open | P3: 2m48y | Q3: 2m | R3: 6200 | S3: B.ROBERTS NOV HUR | T3: North | X3: 0 | Y3: =IF(L3="F",L3,"A") -> A | Z3: =VLOOKUP(Q3,lists!Q:R,2,FALSE) -> 2 | AA3: =VLOOKUP(G3,lists!$B$2:$D$3,3,FALSE) -> TRUE | AB3: =VLOOKUP(F3,lists!$B:$C,2,FALSE) -> TRUE | AC3: =IF(AND(Z3>=VLOOKUP(JUMP!$I$1,lists!$Q:$R,2,FALSE),Z3<=VLOOKUP(JUMP!$I$2,lists!$Q:$R,2,FALSE)),TRUE,FALSE) -> TRUE | AD3: =VLOOKUP(Y3,lists!$B$7:$D$8,3,FALSE) -> TRUE | AE3: =VLOOKUP(SUBSTITUTE(IF(H3="","Open",H3),"Beg","Mdn"),lists!$B$27:$D$29,3,FALSE) -> TRUE | AF3: =IF(JUMP!$I$5="All",TRUE,IF(JUMP!$I$5=TEXT('Raw - J'!C3,"mmm"),TRUE,FALSE)) -> TRUE | AG3: =VLOOKUP(M3,lists!B:D,3,FALSE) -> TRUE | AH3: =VLOOKUP(T3,lists!$B$23:$D$25,3,FALSE) -> TRUE | AI3: =IF(AND(AA3=TRUE,AB3=TRUE,AC3=TRUE,AD3=TRUE,AE3=TRUE,AF3=TRUE,AG3=TRUE,AH3=TRUE),1,0) -> 1
A4: =IF(B4="",A3,B4+1) -> 4 | B4: =IF(AND(A3<1,AI4=1),1,IF(AI4=1,A3,"")) -> 3 | C4: 44317 | D4: HEXHAM | E4: Jump | F4: Chase | G4: Hcap | H4: Open | K4: 5yo+ | L4: A | M4: 5 | O4: 0-100 | P4: 2m4f15y | Q4: 2m 4f | R4: 6500 | S4: HEART HCAP CSE | T4: North | X4: 0 | Y4: =IF(L4="F",L4,"A") -> A | Z4: =VLOOKUP(Q4,lists!Q:R,2,FALSE) -> 3 | AA4: =VLOOKUP(G4,lists!$B$2:$D$3,3,FALSE) -> TRUE | AB4: =VLOOKUP(F4,lists!$B:$C,2,FALSE) -> TRUE | AC4: =IF(AND(Z4>=VLOOKUP(JUMP!$I$1,lists!$Q:$R,2,FALSE),Z4<=VLOOKUP(JUMP!$I$2,lists!$Q:$R,2,FALSE)),TRUE,FALSE) -> TRUE | AD4: =VLOOKUP(Y4,lists!$B$7:$D$8,3,FALSE) -> TRUE | AE4: =VLOOKUP(SUBSTITUTE(IF(H4="","Open",H4),"Beg","Mdn"),lists!$B$27:$D$29,3,FALSE) -> TRUE | AF4: =IF(JUMP!$I$5="All",TRUE,IF(JUMP!$I$5=TEXT('Raw - J'!C4,"mmm"),TRUE,FALSE)) -> TRUE | AG4: =VLOOKUP(M4,lists!B:D,3,FALSE) -> TRUE | AH4: =VLOOKUP(T4,lists!$B$23:$D$25,3,FALSE) -> TRUE | AI4: =IF(AND(AA4=TRUE,AB4=TRUE,AC4=TRUE,AD4=TRUE,AE4=TRUE,AF4=TRUE,AG4=TRUE,AH4=TRUE),1,0) -> 1
A5: =IF(B5="",A4,B5+1) -> 5 | B5: =IF(AND(A4<1,AI5=1),1,IF(AI5=1,A4,"")) -> 4 | C5: 44317 | D5: HEXHAM | E5: Jump | F5: Hurdle | G5: Hcap | H5: Open | K5: 4yo+ | L5: A | M5: 5 | O5: 0-105 | P5: 2m7f63y | Q5: 3m | R5: 6600 | S5: GALLOPS CDL HCP HUR | T5: North | U5: Cond | X5: 0 | Y5: =IF(L5="F",L5,"A") -> A | Z5: =VLOOKUP(Q5,lists!Q:R,2,FALSE) -> 5 | AA5: =VLOOKUP(G5,lists!$B$2:$D$3,3,FALSE) -> TRUE | AB5: =VLOOKUP(F5,lists!$B:$C,2,FALSE) -> TRUE | AC5: =IF(AND(Z5>=VLOOKUP(JUMP!$I$1,lists!$Q:$R,2,FALSE),Z5<=VLOOKUP(JUMP!$I$2,lists!$Q:$R,2,FALSE)),TRUE,FALSE) -> TRUE | AD5: =VLOOKUP(Y5,lists!$B$7:$D$8,3,FALSE) -> TRUE | AE5: =VLOOKUP(SUBSTITUTE(IF(H5="","Open",H5),"Beg","Mdn"),lists!$B$27:$D$29,3,FALSE) -> TRUE | AF5: =IF(JUMP!$I$5="All",TRUE,IF(JUMP!$I$5=TEXT('Raw - J'!C5,"mmm"),TRUE,FALSE)) -> TRUE | AG5: =VLOOKUP(M5,lists!B:D,3,FALSE) -> TRUE | AH5: =VLOOKUP(T5,lists!$B$23:$D$25,3,FALSE) -> TRUE | AI5: =IF(AND(AA5=TRUE,AB5=TRUE,AC5=TRUE,AD5=TRUE,AE5=TRUE,AF5=TRUE,AG5=TRUE,AH5=TRUE),1,0) -> 1
A6: =IF(B6="",A5,B6+1) -> 6 | B6: =IF(AND(A5<1,AI6=1),1,IF(AI6=1,A5,"")) -> 5 | C6: 44317 | D6: HEXHAM | E6: Jump | F6: Chase | G6: WFA | H6: Beg | K6: 5yo+ | L6: A | M6: 4 | O6: Open | P6: 2m4f15y | Q6: 2m 4f | R6: 7200 | S6: CARAVAN BEG CSE | T6: North | X6: 0 | Y6: =IF(L6="F",L6,"A") -> A | Z6: =VLOOKUP(Q6,lists!Q:R,2,FALSE) -> 3 | AA6: =VLOOKUP(G6,lists!$B$2:$D$3,3,FALSE) -> TRUE | AB6: =VLOOKUP(F6,lists!$B:$C,2,FALSE) -> TRUE | AC6: =IF(AND(Z6>=VLOOKUP(JUMP!$I$1,lists!$Q:$R,2,FALSE),Z6<=VLOOKUP(JUMP!$I$2,lists!$Q:$R,2,FALSE)),TRUE,FALSE) -> TRUE | AD6: =VLOOKUP(Y6,lists!$B$7:$D$8,3,FALSE) -> TRUE | AE6: =VLOOKUP(SUBSTITUTE(IF(H6="","Open",H6),"Beg","Mdn"),lists!$B$27:$D$29,3,FALSE) -> TRUE | AF6: =IF(JUMP!$I$5="All",TRUE,IF(JUMP!$I$5=TEXT('Raw - J'!C6,"mmm"),TRUE,FALSE)) -> TRUE | AG6: =VLOOKUP(M6,lists!B:D,3,FALSE) -> TRUE | AH6: =VLOOKUP(T6,lists!$B$23:$D$25,3,FALSE) -> TRUE | AI6: =IF(AND(AA6=TRUE,AB6=TRUE,AC6=TRUE,AD6=TRUE,AE6=TRUE,AF6=TRUE,AG6=TRUE,AH6=TRUE),1,0) -> 1
A7: =IF(B7="",A6,B7+1) -> 7 | B7: =IF(AND(A6<1,AI7=1),1,IF(AI7=1,A6,"")) -> 6 | C7: 44317 | D7: HEXHAM | E7: Jump | F7: Chase | G7: Hcap | H7: Open | K7: 5yo+ | L7: A | M7: 4 | O7: 0-120 | P7: 3m41y | Q7: 3m | R7: 9800 | S7: HEXHAM HCAP CSE | T7: North | X7: 0 | Y7: =IF(L7="F",L7,"A") -> A | Z7: =VLOOKUP(Q7,lists!Q:R,2,FALSE) -> 5 | AA7: =VLOOKUP(G7,lists!$B$2:$D$3,3,FALSE) -> TRUE | AB7: =VLOOKUP(F7,lists!$B:$C,2,FALSE) -> TRUE | AC7: =IF(AND(Z7>=VLOOKUP(JUMP!$I$1,lists!$Q:$R,2,FALSE),Z7<=VLOOKUP(JUMP!$I$2,lists!$Q:$R,2,FALSE)),TRUE,FALSE) -> TRUE | AD7: =VLOOKUP(Y7,lists!$B$7:$D$8,3,FALSE) -> TRUE | AE7: =VLOOKUP(SUBSTITUTE(IF(H7="","Open",H7),"Beg","Mdn"),lists!$B$27:$D$29,3,FALSE) -> TRUE | AF7: =IF(JUMP!$I$5="All",TRUE,IF(JUMP!$I$5=TEXT('Raw - J'!C7,"mmm"),TRUE,FALSE)) -> TRUE | AG7: =VLOOKUP(M7,lists!B:D,3,FALSE) -> TRUE | AH7: =VLOOKUP(T7,lists!$B$23:$D$25,3,FALSE) -> TRUE | AI7: =IF(AND(AA7=TRUE,AB7=TRUE,AC7=TRUE,AD7=TRUE,AE7=TRUE,AF7=TRUE,AG7=TRUE,AH7=TRUE),1,0) -> 1
A8: =IF(B8="",A7,B8+1) -> 8 | B8: =IF(AND(A7<1,AI8=1),1,IF(AI8=1,A7,"")) -> 7 | C8: 44317 | D8: HEXHAM | E8: Jump | F8: Hurdle | G8: Hcap | H8: Open | K8: 4yo+ | L8: A | M8: 3 | O8: 0-130 | P8: 2m48y | Q8: 2m | R8: 10400 | S8: T. DOODY HCAP HUR | T8: North | X8: 0 | Y8: =IF(L8="F",L8,"A") -> A | Z8: =VLOOKUP(Q8,lists!Q:R,2,FALSE) -> 2 | AA8: =VLOOKUP(G8,lists!$B$2:$D$3,3,FALSE) -> TRUE | AB8: =VLOOKUP(F8,lists!$B:$C,2,FALSE) -> TRUE | AC8: =IF(AND(Z8>=VLOOKUP(JUMP!$I$1,lists!$Q:$R,2,FALSE),Z8<=VLOOKUP(JUMP!$I$2,lists!$Q:$R,2,FALSE)),TRUE,FALSE) -> TRUE | AD8: =VLOOKUP(Y8,lists!$B$7:$D$8,3,FALSE) -> TRUE | AE8: =VLOOKUP(SUBSTITUTE(IF(H8="","Open",H8),"Beg","Mdn"),lists!$B$27:$D$29,3,FALSE) -> TRUE | AF8: =IF(JUMP!$I$5="All",TRUE,IF(JUMP!$I$5=TEXT('Raw - J'!C8,"mmm"),TRUE,FALSE)) -> TRUE | AG8: =VLOOKUP(M8,lists!B:D,3,FALSE) -> TRUE | AH8: =VLOOKUP(T8,lists!$B$23:$D$25,3,FALSE) -> TRUE | AI8: =IF(AND(AA8=TRUE,AB8=TRUE,AC8=TRUE,AD8=TRUE,AE8=TRUE,AF8=TRUE,AG8=TRUE,AH8=TRUE),1,0) -> 1
A9: =IF(B9="",A8,B9+1) -> 9 | B9: =IF(AND(A8<1,AI9=1),1,IF(AI9=1,A8,"")) -> 8 | C9: 44317 | D9: UTTOXETER | E9: Jump | F9: Hurdle | G9: Hcap | H9: Nov | K9: 4yo+ | L9: A | M9: 5 | O9: 0-100 | P9: 2m7f70y | Q9: 3m | R9: 4400 | S9: BET365 NOV HCAP HUR | T9: Midlands | X9: 0 | Y9: =IF(L9="F",L9,"A") -> A | Z9: =VLOOKUP(Q9,lists!Q:R,2,FALSE) -> 5 | AA9: =VLOOKUP(G9,lists!$B$2:$D$3,3,FALSE) -> TRUE | AB9: =VLOOKUP(F9,lists!$B:$C,2,FALSE) -> TRUE | AC9: =IF(AND(Z9>=VLOOKUP(JUMP!$I$1,lists!$Q:$R,2,FALSE),Z9<=VLOOKUP(JUMP!$I$2,lists!$Q:$R,2,FALSE)),TRUE,FALSE) -> TRUE | AD9: =VLOOKUP(Y9,lists!$B$7:$D$8,3,FALSE) -> TRUE | AE9: =VLOOKUP(SUBSTITUTE(IF(H9="","Open",H9),"Beg","Mdn"),lists!$B$27:$D$29,3,FALSE) -> TRUE | AF9: =IF(JUMP!$I$5="All",TRUE,IF(JUMP!$I$5=TEXT('Raw - J'!C9,"mmm"),TRUE,FALSE)) -> TRUE | AG9: =VLOOKUP(M9,lists!B:D,3,FALSE) -> TRUE | AH9: =VLOOKUP(T9,lists!$B$23:$D$25,3,FALSE) -> TRUE | AI9: =IF(AND(AA9=TRUE,AB9=TRUE,AC9=TRUE,AD9=TRUE,AE9=TRUE,AF9=TRUE,AG9=TRUE,AH9=TRUE),1,0) -> 1
A10: =IF(B10="",A9,B10+1) -> 10 | B10: =IF(AND(A9<1,AI10=1),1,IF(AI10=1,A9,"")) -> 9 | C10: 44317 | D10: UTTOXETER | E10: Jump | F10: Chase | G10: Hcap | H10: Open | K10: 5yo+ | L10: A | M10: 5 | O10: 0-100 | P10: 3m2y | Q10: 3m | R10: 4700 | S10: BET365 HCAP CSE | T10: Midlands | X10: 0 | Y10: =IF(L10="F",L10,"A") -> A | Z10: =VLOOKUP(Q10,lists!Q:R,2,FALSE) -> 5 | AA10: =VLOOKUP(G10,lists!$B$2:$D$3,3,FALSE) -> TRUE | AB10: =VLOOKUP(F10,lists!$B:$C,2,FALSE) -> TRUE | AC10: =IF(AND(Z10>=VLOOKUP(JUMP!$I$1,lists!$Q:$R,2,FALSE),Z10<=VLOOKUP(JUMP!$I$2,lists!$Q:$R,2,FALSE)),TRUE,FALSE) -> TRUE | AD10: =VLOOKUP(Y10,lists!$B$7:$D$8,3,FALSE) -> TRUE | AE10: =VLOOKUP(SUBSTITUTE(IF(H10="","Open",H10),"Beg","Mdn"),lists!$B$27:$D$29,3,FALSE) -> TRUE | AF10: =IF(JUMP!$I$5="All",TRUE,IF(JUMP!$I$5=TEXT('Raw - J'!C10,"mmm"),TRUE,FALSE)) -> TRUE | AG10: =VLOOKUP(M10,lists!B:D,3,FALSE) -> TRUE | AH10: =VLOOKUP(T10,lists!$B$23:$D$25,3,FALSE) -> TRUE | AI10: =IF(AND(AA10=TRUE,AB10=TRUE,AC10=TRUE,AD10=TRUE,AE10=TRUE,AF10=TRUE,AG10=TRUE,AH10=TRUE),1,0) -> 1
A11: =IF(B11="",A10,B11+1) -> 11 | B11: =IF(AND(A10<1,AI11=1),1,IF(AI11=1,A10,"")) -> 10 | C11: 44317 | D11: UTTOXETER | E11: Jump | F11: Hurdle | G11: WFA | H11: Mdn | J11: NH | K11: 4yo+ | L11: A | M11: 4 | O11: Open | P11: 1m7f168y | Q11: 2m | R11: 5400 | S11: BET365 MDN HUR | T11: Midlands | X11: 0 | Y11: =IF(L11="F",L11,"A") -> A | Z11: =VLOOKUP(Q11,lists!Q:R,2,FALSE) -> 2 | AA11: =VLOOKUP(G11,lists!$B$2:$D$3,3,FALSE) -> TRUE | AB11: =VLOOKUP(F11,lists!$B:$C,2,FALSE) -> TRUE | AC11: =IF(AND(Z11>=VLOOKUP(JUMP!$I$1,lists!$Q:$R,2,FALSE),Z11<=VLOOKUP(JUMP!$I$2,lists!$Q:$R,2,FALSE)),TRUE,FALSE) -> TRUE | AD11: =VLOOKUP(Y11,lists!$B$7:$D$8,3,FALSE) -> TRUE | AE11: =VLOOKUP(SUBSTITUTE(IF(H11="","Open",H11),"Beg","Mdn"),lists!$B$27:$D$29,3,FALSE) -> TRUE | AF11: =IF(JUMP!$I$5="All",TRUE,IF(JUMP!$I$5=TEXT('Raw - J'!C11,"mmm"),TRUE,FALSE)) -> TRUE | AG11: =VLOOKUP(M11,lists!B:D,3,FALSE) -> TRUE | AH11: =VLOOKUP(T11,lists!$B$23:$D$25,3,FALSE) -> TRUE | AI11: =IF(AND(AA11=TRUE,AB11=TRUE,AC11=TRUE,AD11=TRUE,AE11=TRUE,AF11=TRUE,AG11=TRUE,AH11=TRUE),1,0) -> 1
A12: =IF(B12="",A11,B12+1) -> 12 | B12: =IF(AND(A11<1,AI12=1),1,IF(AI12=1,A11,"")) -> 11 | C12: 44317 | D12: UTTOXETER | E12: Jump | F12: Chase | G12: WFA | H12: Beg | K12: 5yo+ | L12: A | M12: 4 | O12: Open | P12: 1m7f214y | Q12: 2m | R12: 6000 | S12: BET365 BEG CSE | T12: Midlands | X12: 0 | Y12: =IF(L12="F",L12,"A") -> A | Z12: =VLOOKUP(Q12,lists!Q:R,2,FALSE) -> 2 | AA12: =VLOOKUP(G12,lists!$B$2:$D$3,3,FALSE) -> TRUE | AB12: =VLOOKUP(F12,lists!$B:$C,2,FALSE) -> TRUE | AC12: =IF(AND(Z12>=VLOOKUP(JUMP!$I$1,lists!$Q:$R,2,FALSE),Z12<=VLOOKUP(JUMP!$I$2,lists!$Q:$R,2,FALSE)),TRUE,FALSE) -> TRUE | AD12: =VLOOKUP(Y12,lists!$B$7:$D$8,3,FALSE) -> TRUE | AE12: =VLOOKUP(SUBSTITUTE(IF(H12="","Open",H12),"Beg","Mdn"),lists!$B$27:$D$29,3,FALSE) -> TRUE | AF12: =IF(JUMP!$I$5="All",TRUE,IF(JUMP!$I$5=TEXT('Raw - J'!C12,"mmm"),TRUE,FALSE)) -> TRUE | AG12: =VLOOKUP(M12,lists!B:D,3,FALSE) -> TRUE | AH12: =VLOOKUP(T12,lists!$B$23:$D$25,3,FALSE) -> TRUE | AI12: =IF(AND(AA12=TRUE,AB12=TRUE,AC12=TRUE,AD12=TRUE,AE12=TRUE,AF12=TRUE,AG12=TRUE,AH12=TRUE),1,0) -> 1
A13: =IF(B13="",A12,B13+1) -> 13 | B13: =IF(AND(A12<1,AI13=1),1,IF(AI13=1,A12,"")) -> 12 | C13: 44317 | D13: UTTOXETER | E13: Jump | F13: Chase | G13: Hcap | H13: Nov | K13: 5yo+ | L13: A | M13: 4 | O13: 0-120 | P13: 2m6f108y | Q13: 2m 6f | R13: 6700 | S13: BET365 NOV HCAP CSE | T13: Midlands | X13: 0 | Y13: =IF(L13="F",L13,"A") -> A | Z13: =VLOOKUP(Q13,lists!Q:R,2,FALSE) -> 4 | AA13: =VLOOKUP(G13,lists!$B$2:$D$3,3,FALSE) -> TRUE | AB13: =VLOOKUP(F13,lists!$B:$C,2,FALSE) -> TRUE | AC13: =IF(AND(Z13>=VLOOKUP(JUMP!$I$1,lists!$Q:$R,2,FALSE),Z13<=VLOOKUP(JUMP!$I$2,lists!$Q:$R,2,FALSE)),TRUE,FALSE) -> TRUE | AD13: =VLOOKUP(Y13,lists!$B$7:$D$8,3,FALSE) -> TRUE | AE13: =VLOOKUP(SUBSTITUTE(IF(H13="","Open",H13),"Beg","Mdn"),lists!$B$27:$D$29,3,FALSE) -> TRUE | AF13: =IF(JUMP!$I$5="All",TRUE,IF(JUMP!$I$5=TEXT('Raw - J'!C13,"mmm"),TRUE,FALSE)) -> TRUE | AG13: =VLOOKUP(M13,lists!B:D,3,FALSE) -> TRUE | AH13: =VLOOKUP(T13,lists!$B$23:$D$25,3,FALSE) -> TRUE | AI13: =IF(AND(AA13=TRUE,AB13=TRUE,AC13=TRUE,AD13=TRUE,AE13=TRUE,AF13=TRUE,AG13=TRUE,AH13=TRUE),1,0) -> 1
A14: =IF(B14="",A13,B14+1) -> 14 | B14: =IF(AND(A13<1,AI14=1),1,IF(AI14=1,A13,"")) -> 13 | C14: 44317 | D14: UTTOXETER | E14: Jump | F14: Hurdle | G14: Hcap | H14: Open | K14: 4yo+ | L14: A | M14: 3 | O14: 0-140 | P14: 2m3f207y | Q14: 2m 4f | R14: 9200 | S14: BET365 HCAP HUR | T14: Midlands | X14: 0 | Y14: =IF(L14="F",L14,"A") -> A | Z14: =VLOOKUP(Q14,lists!Q:R,2,FALSE) -> 3 | AA14: =VLOOKUP(G14,lists!$B$2:$D$3,3,FALSE) -> TRUE | AB14: =VLOOKUP(F14,lists!$B:$C,2,FALSE) -> TRUE | AC14: =IF(AND(Z14>=VLOOKUP(JUMP!$I$1,lists!$Q:$R,2,FALSE),Z14<=VLOOKUP(JUMP!$I$2,lists!$Q:$R,2,FALSE)),TRUE,FALSE) -> TRUE | AD14: =VLOOKUP(Y14,lists!$B$7:$D$8,3,FALSE) -> TRUE | AE14: =VLOOKUP(SUBSTITUTE(IF(H14="","Open",H14),"Beg","Mdn"),lists!$B$27:$D$29,3,FALSE) -> TRUE | AF14: =IF(JUMP!$I$5="All",TRUE,IF(JUMP!$I$5=TEXT('Raw - J'!C14,"mmm"),TRUE,FALSE)) -> TRUE | AG14: =VLOOKUP(M14,lists!B:D,3,FALSE) -> TRUE | AH14: =VLOOKUP(T14,lists!$B$23:$D$25,3,FALSE) -> TRUE | AI14: =IF(AND(AA14=TRUE,AB14=TRUE,AC14=TRUE,AD14=TRUE,AE14=TRUE,AF14=TRUE,AG14=TRUE,AH14=TRUE),1,0) -> 1
A15: =IF(B15="",A14,B15+1) -> 15 | B15: =IF(AND(A14<1,AI15=1),1,IF(AI15=1,A14,"")) -> 14 | C15: 44317 | D15: UTTOXETER | E15: Jump | F15: Chase | G15: Hcap | H15: Open | K15: 5yo+ | L15: A | M15: 2 | O15: Open | P15: 3m2y | Q15: 3m | R15: 35000 | S15: STAFFORDSHIRE CSE | T15: Midlands | X15: 0 | Y15: =IF(L15="F",L15,"A") -> A | Z15: =VLOOKUP(Q15,lists!Q:R,2,FALSE) -> 5 | AA15: =VLOOKUP(G15,lists!$B$2:$D$3,3,FALSE) -> TRUE | AB15: =VLOOKUP(F15,lists!$B:$C,2,FALSE) -> TRUE | AC15: =IF(AND(Z15>=VLOOKUP(JUMP!$I$1,lists!$Q:$R,2,FALSE),Z15<=VLOOKUP(JUMP!$I$2,lists!$Q:$R,2,FALSE)),TRUE,FALSE) -> TRUE | AD15: =VLOOKUP(Y15,lists!$B$7:$D$8,3,FALSE) -> TRUE | AE15: =VLOOKUP(SUBSTITUTE(IF(H15="","Open",H15),"Beg","Mdn"),lists!$B$27:$D$29,3,FALSE) -> TRUE | AF15: =IF(JUMP!$I$5="All",TRUE,IF(JUMP!$I$5=TEXT('Raw - J'!C15,"mmm"),TRUE,FALSE)) -> TRUE | AG15: =VLOOKUP(M15,lists!B:D,3,FALSE) -> TRUE | AH15: =VLOOKUP(T15,lists!$B$23:$D$25,3,FALSE) -> TRUE | AI15: =IF(AND(AA15=TRUE,AB15=TRUE,AC15=TRUE,AD15=TRUE,AE15=TRUE,AF15=TRUE,AG15=TRUE,AH15=TRUE),1,0) -> 1
A16: =IF(B16="",A15,B16+1) -> 16 | B16: =IF(AND(A15<1,AI16=1),1,IF(AI16=1,A15,"")) -> 15 | C16: 44319 | D16: KEMPTON PARK | E16: Jump | F16: Hurdle | G16: Hcap | H16: Open | K16: 4yo+ | L16: A | M16: 4 | O16: 0-120 | P16: 2m5f | Q16: 2m 4f | R16: 5400 | S16: WISE BETTING HCP HUR | T16: South | X16: 0 | Y16: =IF(L16="F",L16,"A") -> A | Z16: =VLOOKUP(Q16,lists!Q:R,2,FALSE) -> 3 | AA16: =VLOOKUP(G16,lists!$B$2:$D$3,3,FALSE) -> TRUE | AB16: =VLOOKUP(F16,lists!$B:$C,2,FALSE) -> TRUE | AC16: =IF(AND(Z16>=VLOOKUP(JUMP!$I$1,lists!$Q:$R,2,FALSE),Z16<=VLOOKUP(JUMP!$I$2,lists!$Q:$R,2,FALSE)),TRUE,FALSE) -> TRUE | AD16: =VLOOKUP(Y16,lists!$B$7:$D$8,3,FALSE) -> TRUE | AE16: =VLOOKUP(SUBSTITUTE(IF(H16="","Open",H16),"Beg","Mdn"),lists!$B$27:$D$29,3,FALSE) -> TRUE | AF16: =IF(JUMP!$I$5="All",TRUE,IF(JUMP!$I$5=TEXT('Raw - J'!C16,"mmm"),TRUE,FALSE)) -> TRUE | AG16: =VLOOKUP(M16,lists!B:D,3,FALSE) -> TRUE | AH16: =VLOOKUP(T16,lists!$B$23:$D$25,3,FALSE) -> TRUE | AI16: =IF(AND(AA16=TRUE,AB16=TRUE,AC16=TRUE,AD16=TRUE,AE16=TRUE,AF16=TRUE,AG16=TRUE,AH16=TRUE),1,0) -> 1
A17: =IF(B17="",A16,B17+1) -> 17 | B17: =IF(AND(A16<1,AI17=1),1,IF(AI17=1,A16,"")) -> 16 | C17: 44319 | D17: KEMPTON PARK | E17: Jump | F17: Hurdle | G17: Hcap | H17: Open | K17: 4yo+ | L17: F | M17: 4 | O17: 0-120 | P17: 2m | Q17: 2m | R17: 5400 | S17: EVERY RACE HCAP HUR | T17: South | X17: 0 | Y17: =IF(L17="F",L17,"A") -> F | Z17: =VLOOKUP(Q17,lists!Q:R,2,FALSE) -> 2 | AA17: =VLOOKUP(G17,lists!$B$2:$D$3,3,FALSE) -> TRUE | AB17: =VLOOKUP(F17,lists!$B:$C,2,FALSE) -> TRUE | AC17: =IF(AND(Z17>=VLOOKUP(JUMP!$I$1,lists!$Q:$R,2,FALSE),Z17<=VLOOKUP(JUMP!$I$2,lists!$Q:$R,2,FALSE)),TRUE,FALSE) -> TRUE | AD17: =VLOOKUP(Y17,lists!$B$7:$D$8,3,FALSE) -> TRUE | AE17: =VLOOKUP(SUBSTITUTE(IF(H17="","Open",H17),"Beg","Mdn"),lists!$B$27:$D$29,3,FALSE) -> TRUE | AF17: =IF(JUMP!$I$5="All",TRUE,IF(JUMP!$I$5=TEXT('Raw - J'!C17,"mmm"),TRUE,FALSE)) -> TRUE | AG17: =VLOOKUP(M17,lists!B:D,3,FALSE) -> TRUE | AH17: =VLOOKUP(T17,lists!$B$23:$D$25,3,FALSE) -> TRUE | AI17: =IF(AND(AA17=TRUE,AB17=TRUE,AC17=TRUE,AD17=TRUE,AE17=TRUE,AF17=TRUE,AG17=TRUE,AH17=TRUE),1,0) -> 1
A18: =IF(B18="",A17,B18+1) -> 18 | B18: =IF(AND(A17<1,AI18=1),1,IF(AI18=1,A17,"")) -> 17 | C18: 44319 | D18: KEMPTON PARK | E18: Jump | F18: Hurdle | G18: WFA | H18: Mdn | K18: 4yo+ | L18: A | M18: 4 | O18: Open | P18: 2m5f | Q18: 2m 4f | R18: 5400 | S18: RACING TV MDN HUR | T18: South | X18: 0 | Y18: =IF(L18="F",L18,"A") -> A | Z18: =VLOOKUP(Q18,lists!Q:R,2,FALSE) -> 3 | AA18: =VLOOKUP(G18,lists!$B$2:$D$3,3,FALSE) -> TRUE | AB18: =VLOOKUP(F18,lists!$B:$C,2,FALSE) -> TRUE | AC18: =IF(AND(Z18>=VLOOKUP(JUMP!$I$1,lists!$Q:$R,2,FALSE),Z18<=VLOOKUP(JUMP!$I$2,lists!$Q:$R,2,FALSE)),TRUE,FALSE) -> TRUE | AD18: =VLOOKUP(Y18,lists!$B$7:$D$8,3,FALSE) -> TRUE | AE18: =VLOOKUP(SUBSTITUTE(IF(H18="","Open",H18),"Beg","Mdn"),lists!$B$27:$D$29,3,FALSE) -> TRUE | AF18: =IF(JUMP!$I$5="All",TRUE,IF(JUMP!$I$5=TEXT('Raw - J'!C18,"mmm"),TRUE,FALSE)) -> TRUE | AG18: =VLOOKUP(M18,lists!B:D,3,FALSE) -> TRUE | AH18: =VLOOKUP(T18,lists!$B$23:$D$25,3,FALSE) -> TRUE | AI18: =IF(AND(AA18=TRUE,AB18=TRUE,AC18=TRUE,AD18=TRUE,AE18=TRUE,AF18=TRUE,AG18=TRUE,AH18=TRUE),1,0) -> 1
A19: =IF(B19="",A18,B19+1) -> 19 | B19: =IF(AND(A18<1,AI19=1),1,IF(AI19=1,A18,"")) -> 18 | C19: 44319 | D19: KEMPTON PARK | E19: Jump | F19: Hurdle | G19: WFA | H19: Nov | K19: 4yo+ | L19: A | M19: 4 | O19: Open | P19: 2m | Q19: 2m | R19: 5400 | S19: RACING TV NOV HUR | T19: South | X19: 0 | Y19: =IF(L19="F",L19,"A") -> A | Z19: =VLOOKUP(Q19,lists!Q:R,2,FALSE) -> 2 | AA19: =VLOOKUP(G19,lists!$B$2:$D$3,3,FALSE) -> TRUE | AB19: =VLOOKUP(F19,lists!$B:$C,2,FALSE) -> TRUE | AC19: =IF(AND(Z19>=VLOOKUP(JUMP!$I$1,lists!$Q:$R,2,FALSE),Z19<=VLOOKUP(JUMP!$I$2,lists!$Q:$R,2,FALSE)),TRUE,FALSE) -> TRUE | AD19: =VLOOKUP(Y19,lists!$B$7:$D$8,3,FALSE) -> TRUE | AE19: =VLOOKUP(SUBSTITUTE(IF(H19="","Open",H19),"Beg","Mdn"),lists!$B$27:$D$29,3,FALSE) -> TRUE | AF19: =IF(JUMP!$I$5="All",TRUE,IF(JUMP!$I$5=TEXT('Raw - J'!C19,"mmm"),TRUE,FALSE)) -> TRUE | AG19: =VLOOKUP(M19,lists!B:D,3,FALSE) -> TRUE | AH19: =VLOOKUP(T19,lists!$B$23:$D$25,3,FALSE) -> TRUE | AI19: =IF(AND(AA19=TRUE,AB19=TRUE,AC19=TRUE,AD19=TRUE,AE19=TRUE,AF19=TRUE,AG19=TRUE,AH19=TRUE),1,0) -> 1
A20: =IF(B20="",A19,B20+1) -> 20 | B20: =IF(AND(A19<1,AI20=1),1,IF(AI20=1,A19,"")) -> 19 | C20: 44319 | D20: KEMPTON PARK | E20: Jump | F20: Chase | G20: Hcap | H20: Open | K20: 5yo+ | L20: A | M20: 3 | O20: 0-135 | P20: 3m | Q20: 3m | R20: 10400 | S20: RACING TV HCP CSE | T20: South | X20: 0 | Y20: =IF(L20="F",L20,"A") -> A | Z20: =VLOOKUP(Q20,lists!Q:R,2,FALSE) -> 5 | AA20: =VLOOKUP(G20,lists!$B$2:$D$3,3,FALSE) -> TRUE | AB20: =VLOOKUP(F20,lists!$B:$C,2,FALSE) -> TRUE | AC20: =IF(AND(Z20>=VLOOKUP(JUMP!$I$1,lists!$Q:$R,2,FALSE),Z20<=VLOOKUP(JUMP!$I$2,lists!$Q:$R,2,FALSE)),TRUE,FALSE) -> TRUE | AD20: =VLOOKUP(Y20,lists!$B$7:$D$8,3,FALSE) -> TRUE | AE20: =VLOOKUP(SUBSTITUTE(IF(H20="","Open",H20),"Beg","Mdn"),lists!$B$27:$D$29,3,FALSE) -> TRUE | AF20: =IF(JUMP!$I$5="All",TRUE,IF(JUMP!$I$5=TEXT('Raw - J'!C20,"mmm"),TRUE,FALSE)) -> TRUE | AG20: =VLOOKUP(M20,lists!B:D,3,FALSE) -> TRUE | AH20: =VLOOKUP(T20,lists!$B$23:$D$25,3,FALSE) -> TRUE | AI20: =IF(AND(AA20=TRUE,AB20=TRUE,AC20=TRUE,AD20=TRUE,AE20=TRUE,AF20=TRUE,AG20=TRUE,AH20=TRUE),1,0) -> 1
A21: =IF(B21="",A20,B21+1) -> 21 | B21: =IF(AND(A20<1,AI21=1),1,IF(AI21=1,A20,"")) -> 20 | C21: 44319 | D21: KEMPTON PARK | E21: Jump | F21: Chase | G21: WFA | H21: Beg | K21: 5yo+ | L21: A | M21: 3 | O21: Open | P21: 2m4f110y | Q21: 2m 4f | R21: 10400 | S21: RACING TV BEG CSE | T21: South | X21: 0 | Y21: =IF(L21="F",L21,"A") -> A | Z21: =VLOOKUP(Q21,lists!Q:R,2,FALSE) -> 3 | AA21: =VLOOKUP(G21,lists!$B$2:$D$3,3,FALSE) -> TRUE | AB21: =VLOOKUP(F21,lists!$B:$C,2,FALSE) -> TRUE | AC21: =IF(AND(Z21>=VLOOKUP(JUMP!$I$1,lists!$Q:$R,2,FALSE),Z21<=VLOOKUP(JUMP!$I$2,lists!$Q:$R,2,FALSE)),TRUE,FALSE) -> TRUE | AD21: =VLOOKUP(Y21,lists!$B$7:$D$8,3,FALSE) -> TRUE | AE21: =VLOOKUP(SUBSTITUTE(IF(H21="","Open",H21),"Beg","Mdn"),lists!$B$27:$D$29,3,FALSE) -> TRUE | AF21: =IF(JUMP!$I$5="All",TRUE,IF(JUMP!$I$5=TEXT('Raw - J'!C21,"mmm"),TRUE,FALSE)) -> TRUE | AG21: =VLOOKUP(M21,lists!B:D,3,FALSE) -> TRUE | AH21: =VLOOKUP(T21,lists!$B$23:$D$25,3,FALSE) -> TRUE | AI21: =IF(AND(AA21=TRUE,AB21=TRUE,AC21=TRUE,AD21=TRUE,AE21=TRUE,AF21=TRUE,AG21=TRUE,AH21=TRUE),1,0) -> 1
A22: =IF(B22="",A21,B22+1) -> 22 | B22: =IF(AND(A21<1,AI22=1),1,IF(AI22=1,A21,"")) -> 21 | C22: 44319 | D22: KEMPTON PARK | E22: Jump | F22: Chase | G22: Hcap | H22: Open | K22: 5yo+ | L22: A | M22: 2 | O22: Open | P22: 2m2f | Q22: 2m | R22: 22500 | S22: RACING TV HCAP CSE | T22: South | X22: 0 | Y22: =IF(L22="F",L22,"A") -> A | Z22: =VLOOKUP(Q22,lists!Q:R,2,FALSE) -> 2 | AA22: =VLOOKUP(G22,lists!$B$2:$D$3,3,FALSE) -> TRUE | AB22: =VLOOKUP(F22,lists!$B:$C,2,FALSE) -> TRUE | AC22: =IF(AND(Z22>=VLOOKUP(JUMP!$I$1,lists!$Q:$R,2,FALSE),Z22<=VLOOKUP(JUMP!$I$2,lists!$Q:$R,2,FALSE)),TRUE,FALSE) -> TRUE | AD22: =VLOOKUP(Y22,lists!$B$7:$D$8,3,FALSE) -> TRUE | AE22: =VLOOKUP(SUBSTITUTE(IF(H22="","Open",H22),"Beg","Mdn"),lists!$B$27:$D$29,3,FALSE) -> TRUE | AF22: =IF(JUMP!$I$5="All",TRUE,IF(JUMP!$I$5=TEXT('Raw - J'!C22,"mmm"),TRUE,FALSE)) -> TRUE | AG22: =VLOOKUP(M22,lists!B:D,3,FALSE) -> TRUE | AH22: =VLOOKUP(T22,lists!$B$23:$D$25,3,FALSE) -> TRUE | AI22: =IF(AND(AA22=TRUE,AB22=TRUE,AC22=TRUE,AD22=TRUE,AE22=TRUE,AF22=TRUE,AG22=TRUE,AH22=TRUE),1,0) -> 1
A23: =IF(B23="",A22,B23+1) -> 23 | B23: =IF(AND(A22<1,AI23=1),1,IF(AI23=1,A22,"")) -> 22 | C23: 44319 | D23: WARWICK | E23: Jump | F23: Hurdle | G23: Hcap | H23: Open | K23: 4yo+ | L23: A | M23: 5 | O23: 0-105 | P23: 3m1f | Q23: 3m | R23: 4600 | S23: FUSILIERS HCAP HUR | T23: Midlands | U23: Amtr | X23: 0 | Y23: =IF(L23="F",L23,"A") -> A | Z23: =VLOOKUP(Q23,lists!Q:R,2,FALSE) -> 5 | AA23: =VLOOKUP(G23,lists!$B$2:$D$3,3,FALSE) -> TRUE | AB23: =VLOOKUP(F23,lists!$B:$C,2,FALSE) -> TRUE | AC23: =IF(AND(Z23>=VLOOKUP(JUMP!$I$1,lists!$Q:$R,2,FALSE),Z23<=VLOOKUP(JUMP!$I$2,lists!$Q:$R,2,FALSE)),TRUE,FALSE) -> TRUE | AD23: =VLOOKUP(Y23,lists!$B$7:$D$8,3,FALSE) -> TRUE | AE23: =VLOOKUP(SUBSTITUTE(IF(H23="","Open",H23),"Beg","Mdn"),lists!$B$27:$D$29,3,FALSE) -> TRUE | AF23: =IF(JUMP!$I$5="All",TRUE,IF(JUMP!$I$5=TEXT('Raw - J'!C23,"mmm"),TRUE,FALSE)) -> TRUE | AG23: =VLOOKUP(M23,lists!B:D,3,FALSE) -> TRUE | AH23: =VLOOKUP(T23,lists!$B$23:$D$25,3,FALSE) -> TRUE | AI23: =IF(AND(AA23=TRUE,AB23=TRUE,AC23=TRUE,AD23=TRUE,AE23=TRUE,AF23=TRUE,AG23=TRUE,AH23=TRUE),1,0) -> 1
A24: =IF(B24="",A23,B24+1) -> 24 | B24: =IF(AND(A23<1,AI24=1),1,IF(AI24=1,A23,"")) -> 23 | C24: 44319 | D24: WARWICK | E24: Jump | F24: Hurdle | G24: Hcap | H24: Open | K24: 4yo+ | L24: F | M24: 4 | O24: 0-120 | P24: 2m5f | Q24: 2m 4f | R24: 6600 | S24: BEVIN BOYS HCAP HUR | T24: Midlands | X24: 0 | Y24: =IF(L24="F",L24,"A") -> F | Z24: =VLOOKUP(Q24,lists!Q:R,2,FALSE) -> 3 | AA24: =VLOOKUP(G24,lists!$B$2:$D$3,3,FALSE) -> TRUE | AB24: =VLOOKUP(F24,lists!$B:$C,2,FALSE) -> TRUE | AC24: =IF(AND(Z24>=VLOOKUP(JUMP!$I$1,lists!$Q:$R,2,FALSE),Z24<=VLOOKUP(JUMP!$I$2,lists!$Q:$R,2,FALSE)),TRUE,FALSE) -> TRUE | AD24: =VLOOKUP(Y24,lists!$B$7:$D$8,3,FALSE) -> TRUE | AE24: =VLOOKUP(SUBSTITUTE(IF(H24="","Open",H24),"Beg","Mdn"),lists!$B$27:$D$29,3,FALSE) -> TRUE | AF24: =IF(JUMP!$I$5="All",TRUE,IF(JUMP!$I$5=TEXT('Raw - J'!C24,"mmm"),TRUE,FALSE)) -> TRUE | AG24: =VLOOKUP(M24,lists!B:D,3,FALSE) -> TRUE | AH24: =VLOOKUP(T24,lists!$B$23:$D$25,3,FALSE) -> TRUE | AI24: =IF(AND(AA24=TRUE,AB24=TRUE,AC24=TRUE,AD24=TRUE,AE24=TRUE,AF24=TRUE,AG24=TRUE,AH24=TRUE),1,0) -> 1
A25: =IF(B25="",A24,B25+1) -> 25 | B25: =IF(AND(A24<1,AI25=1),1,IF(AI25=1,A24,"")) -> 24 | C25: 44319 | D25: WARWICK | E25: Jump | F25: Hurdle | G25: WFA | H25: Mdn | K25: 4yo+ | L25: A | M25: 4 | O25: Open | P25: 3m1f | Q25: 3m | R25: 6600 | S25: DESERT RATS MDN HUR | T25: Midlands | X25: 0 | Y25: =IF(L25="F",L25,"A") -> A | Z25: =VLOOKUP(Q25,lists!Q:R,2,FALSE) -> 5 | AA25: =VLOOKUP(G25,lists!$B$2:$D$3,3,FALSE) -> TRUE | AB25: =VLOOKUP(F25,lists!$B:$C,2,FALSE) -> TRUE | AC25: =IF(AND(Z25>=VLOOKUP(JUMP!$I$1,lists!$Q:$R,2,FALSE),Z25<=VLOOKUP(JUMP!$I$2,lists!$Q:$R,2,FALSE)),TRUE,FALSE) -> TRUE | AD25: =VLOOKUP(Y25,lists!$B$7:$D$8,3,FALSE) -> TRUE | AE25: =VLOOKUP(SUBSTITUTE(IF(H25="","Open",H25),"Beg","Mdn"),lists!$B$27:$D$29,3,FALSE) -> TRUE | AF25: =IF(JUMP!$I$5="All",TRUE,IF(JUMP!$I$5=TEXT('Raw - J'!C25,"mmm"),TRUE,FALSE)) -> TRUE | AG25: =VLOOKUP(M25,lists!B:D,3,FALSE) -> TRUE | AH25: =VLOOKUP(T25,lists!$B$23:$D$25,3,FALSE) -> TRUE | AI25: =IF(AND(AA25=TRUE,AB25=TRUE,AC25=TRUE,AD25=TRUE,AE25=TRUE,AF25=TRUE,AG25=TRUE,AH25=TRUE),1,0) -> 1
A26: =IF(B26="",A25,B26+1) -> 26 | B26: =IF(AND(A25<1,AI26=1),1,IF(AI26=1,A25,"")) -> 25 | C26: 44319 | D26: WARWICK | E26: Jump | F26: Hurdle | G26: Hcap | H26: Open | K26: 4yo+ | L26: A | M26: 4 | O26: 0-120 | P26: 2m | Q26: 2m | R26: 6600 | S26: HMS BULLDOG HCP HUR | T26: Midlands | X26: 0 | Y26: =IF(L26="F",L26,"A") -> A | Z26: =VLOOKUP(Q26,lists!Q:R,2,FALSE) -> 2 | AA26: =VLOOKUP(G26,lists!$B$2:$D$3,3,FALSE) -> TRUE | AB26: =VLOOKUP(F26,lists!$B:$C,2,FALSE) -> TRUE | AC26: =IF(AND(Z26>=VLOOKUP(JUMP!$I$1,lists!$Q:$R,2,FALSE),Z26<=VLOOKUP(JUMP!$I$2,lists!$Q:$R,2,FALSE)),TRUE,FALSE) -> TRUE | AD26: =VLOOKUP(Y26,lists!$B$7:$D$8,3,FALSE) -> TRUE | AE26: =VLOOKUP(SUBSTITUTE(IF(H26="","Open",H26),"Beg","Mdn"),lists!$B$27:$D$29,3,FALSE) -> TRUE | AF26: =IF(JUMP!$I$5="All",TRUE,IF(JUMP!$I$5=TEXT('Raw - J'!C26,"mmm"),TRUE,FALSE)) -> TRUE | AG26: =VLOOKUP(M26,lists!B:D,3,FALSE) -> TRUE | AH26: =VLOOKUP(T26,lists!$B$23:$D$25,3,FALSE) -> TRUE | AI26: =IF(AND(AA26=TRUE,AB26=TRUE,AC26=TRUE,AD26=TRUE,AE26=TRUE,AF26=TRUE,AG26=TRUE,AH26=TRUE),1,0) -> 1
A27: =IF(B27="",A26,B27+1) -> 27 | B27: =IF(AND(A26<1,AI27=1),1,IF(AI27=1,A26,"")) -> 26 | C27: 44319 | D27: WARWICK | E27: Jump | F27: Hurdle | G27: WFA | H27: Mdn | J27: NH | K27: 4yo+ | L27: F | M27: 4 | O27: Open | P27: 2m | Q27: 2m | R27: 6600 | S27: FIGHT MARES MDN HUR | T27: Midlands | X27: 0 | Y27: =IF(L27="F",L27,"A") -> F | Z27: =VLOOKUP(Q27,lists!Q:R,2,FALSE) -> 2 | AA27: =VLOOKUP(G27,lists!$B$2:$D$3,3,FALSE) -> TRUE | AB27: =VLOOKUP(F27,lists!$B:$C,2,FALSE) -> TRUE | AC27: =IF(AND(Z27>=VLOOKUP(JUMP!$I$1,lists!$Q:$R,2,FALSE),Z27<=VLOOKUP(JUMP!$I$2,lists!$Q:$R,2,FALSE)),TRUE,FALSE) -> TRUE | AD27: =VLOOKUP(Y27,lists!$B$7:$D$8,3,FALSE) -> TRUE | AE27: =VLOOKUP(SUBSTITUTE(IF(H27="","Open",H27),"Beg","Mdn"),lists!$B$27:$D$29,3,FALSE) -> TRUE | AF27: =IF(JUMP!$I$5="All",TRUE,IF(JUMP!$I$5=TEXT('Raw - J'!C27,"mmm"),TRUE,FALSE)) -> TRUE | AG27: =VLOOKUP(M27,lists!B:D,3,FALSE) -> TRUE | AH27: =VLOOKUP(T27,lists!$B$23:$D$25,3,FALSE) -> TRUE | AI27: =IF(AND(AA27=TRUE,AB27=TRUE,AC27=TRUE,AD27=TRUE,AE27=TRUE,AF27=TRUE,AG27=TRUE,AH27=TRUE),1,0) -> 1
A28: =IF(B28="",A27,B28+1) -> 28 | B28: =IF(AND(A27<1,AI28=1),1,IF(AI28=1,A27,"")) -> 27 | C28: 44319 | D28: WARWICK | E28: Jump | F28: Chase | G28: Hcap | H28: Nov | K28: 5yo+ | L28: A | M28: 4 | O28: 0-120 | P28: 2m54y | Q28: 2m | R28: 7600 | S28: POLISH NOV HCP CSE | T28: Midlands | X28: 0 | Y28: =IF(L28="F",L28,"A") -> A | Z28: =VLOOKUP(Q28,lists!Q:R,2,FALSE) -> 2 | AA28: =VLOOKUP(G28,lists!$B$2:$D$3,3,FALSE) -> TRUE | AB28: =VLOOKUP(F28,lists!$B:$C,2,FALSE) -> TRUE | AC28: =IF(AND(Z28>=VLOOKUP(JUMP!$I$1,lists!$Q:$R,2,FALSE),Z28<=VLOOKUP(JUMP!$I$2,lists!$Q:$R,2,FALSE)),TRUE,FALSE) -> TRUE | AD28: =VLOOKUP(Y28,lists!$B$7:$D$8,3,FALSE) -> TRUE | AE28: =VLOOKUP(SUBSTITUTE(IF(H28="","Open",H28),"Beg","Mdn"),lists!$B$27:$D$29,3,FALSE) -> TRUE | AF28: =IF(JUMP!$I$5="All",TRUE,IF(JUMP!$I$5=TEXT('Raw - J'!C28,"mmm"),TRUE,FALSE)) -> TRUE | AG28: =VLOOKUP(M28,lists!B:D,3,FALSE) -> TRUE | AH28: =VLOOKUP(T28,lists!$B$23:$D$25,3,FALSE) -> TRUE | AI28: =IF(AND(AA28=TRUE,AB28=TRUE,AC28=TRUE,AD28=TRUE,AE28=TRUE,AF28=TRUE,AG28=TRUE,AH28=TRUE),1,0) -> 1
A29: =IF(B29="",A28,B29+1) -> 29 | B29: =IF(AND(A28<1,AI29=1),1,IF(AI29=1,A28,"")) -> 28 | C29: 44319 | D29: WARWICK | E29: Jump | F29: Chase | G29: Hcap | H29: Open | K29: 5yo+ | L29: A | M29: 4 | O29: 0-120 | P29: 2m4f | Q29: 2m 4f | R29: 9600 | S29: PARACHUTE HCAP CSE | T29: Midlands | X29: 0 | Y29: =IF(L29="F",L29,"A") -> A | Z29: =VLOOKUP(Q29,lists!Q:R,2,FALSE) -> 3 | AA29: =VLOOKUP(G29,lists!$B$2:$D$3,3,FALSE) -> TRUE | AB29: =VLOOKUP(F29,lists!$B:$C,2,FALSE) -> TRUE | AC29: =IF(AND(Z29>=VLOOKUP(JUMP!$I$1,lists!$Q:$R,2,FALSE),Z29<=VLOOKUP(JUMP!$I$2,lists!$Q:$R,2,FALSE)),TRUE,FALSE) -> TRUE | AD29: =VLOOKUP(Y29,lists!$B$7:$D$8,3,FALSE) -> TRUE | AE29: =VLOOKUP(SUBSTITUTE(IF(H29="","Open",H29),"Beg","Mdn"),lists!$B$27:$D$29,3,FALSE) -> TRUE | AF29: =IF(JUMP!$I$5="All",TRUE,IF(JUMP!$I$5=TEXT('Raw - J'!C29,"mmm"),TRUE,FALSE)) -> TRUE | AG29: =VLOOKUP(M29,lists!B:D,3,FALSE) -> TRUE | AH29: =VLOOKUP(T29,lists!$B$23:$D$25,3,FALSE) -> TRUE | AI29: =IF(AND(AA29=TRUE,AB29=TRUE,AC29=TRUE,AD29=TRUE,AE29=TRUE,AF29=TRUE,AG29=TRUE,AH29=TRUE),1,0) -> 1
A30: =IF(B30="",A29,B30+1) -> 30 | B30: =IF(AND(A29<1,AI30=1),1,IF(AI30=1,A29,"")) -> 29 | C30: 44320 | D30: AYR | E30: Jump | F30: NHF | G30: WFA | H30: Open | I30: Intermediate | K30: 4-6yo | L30: A | M30: 5 | O30: Open | P30: 2m | Q30: 2m | R30: 3500 | S30: WESTERN HOUSE NHF | T30: North | X30: 0 | Y30: =IF(L30="F",L30,"A") -> A | Z30: =VLOOKUP(Q30,lists!Q:R,2,FALSE) -> 2 | AA30: =VLOOKUP(G30,lists!$B$2:$D$3,3,FALSE) -> TRUE | AB30: =VLOOKUP(F30,lists!$B:$C,2,FALSE) -> TRUE | AC30: =IF(AND(Z30>=VLOOKUP(JUMP!$I$1,lists!$Q:$R,2,FALSE),Z30<=VLOOKUP(JUMP!$I$2,lists!$Q:$R,2,FALSE)),TRUE,FALSE) -> TRUE | AD30: =VLOOKUP(Y30,lists!$B$7:$D$8,3,FALSE) -> TRUE | AE30: =VLOOKUP(SUBSTITUTE(IF(H30="","Open",H30),"Beg","Mdn"),lists!$B$27:$D$29,3,FALSE) -> TRUE | AF30: =IF(JUMP!$I$5="All",TRUE,IF(JUMP!$I$5=TEXT('Raw - J'!C30,"mmm"),TRUE,FALSE)) -> TRUE | AG30: =VLOOKUP(M30,lists!B:D,3,FALSE) -> TRUE | AH30: =VLOOKUP(T30,lists!$B$23:$D$25,3,FALSE) -> TRUE | AI30: =IF(AND(AA30=TRUE,AB30=TRUE,AC30=TRUE,AD30=TRUE,AE30=TRUE,AF30=TRUE,AG30=TRUE,AH30=TRUE),1,0) -> 1
A31: =IF(B31="",A30,B31+1) -> 31 | B31: =IF(AND(A30<1,AI31=1),1,IF(AI31=1,A30,"")) -> 30 | C31: 44320 | D31: AYR | E31: Jump | F31: Hurdle | G31: Hcap | H31: Open | K31: 4yo+ | L31: A | M31: 5 | O31: 0-105 | P31: 2m4f100y | Q31: 2m 4f | R31: 5000 | S31: RACING TV HCAP HUR | T31: North | X31: 0 | Y31: =IF(L31="F",L31,"A") -> A | Z31: =VLOOKUP(Q31,lists!Q:R,2,FALSE) -> 3 | AA31: =VLOOKUP(G31,lists!$B$2:$D$3,3,FALSE) -> TRUE | AB31: =VLOOKUP(F31,lists!$B:$C,2,FALSE) -> TRUE | AC31: =IF(AND(Z31>=VLOOKUP(JUMP!$I$1,lists!$Q:$R,2,FALSE),Z31<=VLOOKUP(JUMP!$I$2,lists!$Q:$R,2,FALSE)),TRUE,FALSE) -> TRUE | AD31: =VLOOKUP(Y31,lists!$B$7:$D$8,3,FALSE) -> TRUE | AE31: =VLOOKUP(SUBSTITUTE(IF(H31="","Open",H31),"Beg","Mdn"),lists!$B$27:$D$29,3,FALSE) -> TRUE | AF31: =IF(JUMP!$I$5="All",TRUE,IF(JUMP!$I$5=TEXT('Raw - J'!C31,"mmm"),TRUE,FALSE)) -> TRUE | AG31: =VLOOKUP(M31,lists!B:D,3,FALSE) -> TRUE | AH31: =VLOOKUP(T31,lists!$B$23:$D$25,3,FALSE) -> TRUE | AI31: =IF(AND(AA31=TRUE,AB31=TRUE,AC31=TRUE,AD31=TRUE,AE31=TRUE,AF31=TRUE,AG31=TRUE,AH31=TRUE),1,0) -> 1
A32: =IF(B32="",A31,B32+1) -> 32 | B32: =IF(AND(A31<1,AI32=1),1,IF(AI32=1,A31,"")) -> 31 | C32: 44320 | D32: AYR | E32: Jump | F32: Hurdle | G32: WFA | H32: Nov | K32: 4yo+ | L32: F | M32: 4 | O32: Open | P32: 2m4f100y | Q32: 2m 4f | R32: 5500 | S32: RACINGTV.COM NOV HUR | T32: North | X32: 0 | Y32: =IF(L32="F",L32,"A") -> F | Z32: =VLOOKUP(Q32,lists!Q:R,2,FALSE) -> 3 | AA32: =VLOOKUP(G32,lists!$B$2:$D$3,3,FALSE) -> TRUE | AB32: =VLOOKUP(F32,lists!$B:$C,2,FALSE) -> TRUE | AC32: =IF(AND(Z32>=VLOOKUP(JUMP!$I$1,lists!$Q:$R,2,FALSE),Z32<=VLOOKUP(JUMP!$I$2,lists!$Q:$R,2,FALSE)),TRUE,FALSE) -> TRUE | AD32: =VLOOKUP(Y32,lists!$B$7:$D$8,3,FALSE) -> TRUE | AE32: =VLOOKUP(SUBSTITUTE(IF(H32="","Open",H32),"Beg","Mdn"),lists!$B$27:$D$29,3,FALSE) -> TRUE | AF32: =IF(JUMP!$I$5="All",TRUE,IF(JUMP!$I$5=TEXT('Raw - J'!C32,"mmm"),TRUE,FALSE)) -> TRUE | AG32: =VLOOKUP(M32,lists!B:D,3,FALSE) -> TRUE | AH32: =VLOOKUP(T32,lists!$B$23:$D$25,3,FALSE) -> TRUE | AI32: =IF(AND(AA32=TRUE,AB32=TRUE,AC32=TRUE,AD32=TRUE,AE32=TRUE,AF32=TRUE,AG32=TRUE,AH32=TRUE),1,0) -> 1
A33: =IF(B33="",A32,B33+1) -> 33 | B33: =IF(AND(A32<1,AI33=1),1,IF(AI33=1,A32,"")) -> 32 | C33: 44320 | D33: AYR | E33: Jump | F33: Hurdle | G33: WFA | H33: Mdn | K33: 4yo+ | L33: A | M33: 4 | O33: Open | P33: 2m | Q33: 2m | R33: 6000 | S33: RACING TV MDN HUR | T33: North | X33: 0 | Y33: =IF(L33="F",L33,"A") -> A | Z33: =VLOOKUP(Q33,lists!Q:R,2,FALSE) -> 2 | AA33: =VLOOKUP(G33,lists!$B$2:$D$3,3,FALSE) -> TRUE | AB33: =VLOOKUP(F33,lists!$B:$C,2,FALSE) -> TRUE | AC33: =IF(AND(Z33>=VLOOKUP(JUMP!$I$1,lists!$Q:$R,2,FALSE),Z33<=VLOOKUP(JUMP!$I$2,lists!$Q:$R,2,FALSE)),TRUE,FALSE) -> TRUE | AD33: =VLOOKUP(Y33,lists!$B$7:$D$8,3,FALSE) -> TRUE | AE33: =VLOOKUP(SUBSTITUTE(IF(H33="","Open",H33),"Beg","Mdn"),lists!$B$27:$D$29,3,FALSE) -> TRUE | AF33: =IF(JUMP!$I$5="All",TRUE,IF(JUMP!$I$5=TEXT('Raw - J'!C33,"mmm"),TRUE,FALSE)) -> TRUE | AG33: =VLOOKUP(M33,lists!B:D,3,FALSE) -> TRUE | AH33: =VLOOKUP(T33,lists!$B$23:$D$25,3,FALSE) -> TRUE | AI33: =IF(AND(AA33=TRUE,AB33=TRUE,AC33=TRUE,AD33=TRUE,AE33=TRUE,AF33=TRUE,AG33=TRUE,AH33=TRUE),1,0) -> 1
A34: =IF(B34="",A33,B34+1) -> 34 | B34: =IF(AND(A33<1,AI34=1),1,IF(AI34=1,A33,"")) -> 33 | C34: 44320 | D34: AYR | E34: Jump | F34: Hurdle | G34: Hcap | H34: Open | K34: 4yo+ | L34: A | M34: 4 | O34: 0-120 | P34: 3m70y | Q34: 3m | R34: 6800 | S34: WATCH RTV HCAP HUR | T34: North | X34: 0 | Y34: =IF(L34="F",L34,"A") -> A | Z34: =VLOOKUP(Q34,lists!Q:R,2,FALSE) -> 5 | AA34: =VLOOKUP(G34,lists!$B$2:$D$3,3,FALSE) -> TRUE | AB34: =VLOOKUP(F34,lists!$B:$C,2,FALSE) -> TRUE | AC34: =IF(AND(Z34>=VLOOKUP(JUMP!$I$1,lists!$Q:$R,2,FALSE),Z34<=VLOOKUP(JUMP!$I$2,lists!$Q:$R,2,FALSE)),TRUE,FALSE) -> TRUE | AD34: =VLOOKUP(Y34,lists!$B$7:$D$8,3,FALSE) -> TRUE | AE34: =VLOOKUP(SUBSTITUTE(IF(H34="","Open",H34),"Beg","Mdn"),lists!$B$27:$D$29,3,FALSE) -> TRUE | AF34: =IF(JUMP!$I$5="All",TRUE,IF(JUMP!$I$5=TEXT('Raw - J'!C34,"mmm"),TRUE,FALSE)) -> TRUE | AG34: =VLOOKUP(M34,lists!B:D,3,FALSE) -> TRUE | AH34: =VLOOKUP(T34,lists!$B$23:$D$25,3,FALSE) -> TRUE | AI34: =IF(AND(AA34=TRUE,AB34=TRUE,AC34=TRUE,AD34=TRUE,AE34=TRUE,AF34=TRUE,AG34=TRUE,AH34=TRUE),1,0) -> 1
A35: =IF(B35="",A34,B35+1) -> 35 | B35: =IF(AND(A34<1,AI35=1),1,IF(AI35=1,A34,"")) -> 34 | C35: 44320 | D35: AYR | E35: Jump | F35: Chase | G35: Hcap | H35: Open | K35: 5yo+ | L35: A | M35: 4 | O35: 0-120 | P35: 2m4f110y | Q35: 2m 4f | R35: 8000 | S35: WEDDINGS HCAP CSE | T35: North | X35: 0 | Y35: =IF(L35="F",L35,"A") -> A | Z35: =VLOOKUP(Q35,lists!Q:R,2,FALSE) -> 3 | AA35: =VLOOKUP(G35,lists!$B$2:$D$3,3,FALSE) -> TRUE | AB35: =VLOOKUP(F35,lists!$B:$C,2,FALSE) -> TRUE | AC35: =IF(AND(Z35>=VLOOKUP(JUMP!$I$1,lists!$Q:$R,2,FALSE),Z35<=VLOOKUP(JUMP!$I$2,lists!$Q:$R,2,FALSE)),TRUE,FALSE) -> TRUE | AD35: =VLOOKUP(Y35,lists!$B$7:$D$8,3,FALSE) -> TRUE | AE35: =VLOOKUP(SUBSTITUTE(IF(H35="","Open",H35),"Beg","Mdn"),lists!$B$27:$D$29,3,FALSE) -> TRUE | AF35: =IF(JUMP!$I$5="All",TRUE,IF(JUMP!$I$5=TEXT('Raw - J'!C35,"mmm"),TRUE,FALSE)) -> TRUE | AG35: =VLOOKUP(M35,lists!B:D,3,FALSE) -> TRUE | AH35: =VLOOKUP(T35,lists!$B$23:$D$25,3,FALSE) -> TRUE | AI35: =IF(AND(AA35=TRUE,AB35=TRUE,AC35=TRUE,AD35=TRUE,AE35=TRUE,AF35=TRUE,AG35=TRUE,AH35=TRUE),1,0) -> 1
A36: =IF(B36="",A35,B36+1) -> 36 | B36: =IF(AND(A35<1,AI36=1),1,IF(AI36=1,A35,"")) -> 35 | C36: 44320 | D36: AYR | E36: Jump | F36: Chase | G36: Hcap | H36: Open | K36: 5yo+ | L36: A | M36: 3 | O36: 0-130 | P36: 3m20y | Q36: 3m | R36: 15500 | S36: JOIN RTV HCAP CSE | T36: North | X36: 0 | Y36: =IF(L36="F",L36,"A") -> A | Z36: =VLOOKUP(Q36,lists!Q:R,2,FALSE) -> 5 | AA36: =VLOOKUP(G36,lists!$B$2:$D$3,3,FALSE) -> TRUE | AB36: =VLOOKUP(F36,lists!$B:$C,2,FALSE) -> TRUE | AC36: =IF(AND(Z36>=VLOOKUP(JUMP!$I$1,lists!$Q:$R,2,FALSE),Z36<=VLOOKUP(JUMP!$I$2,lists!$Q:$R,2,FALSE)),TRUE,FALSE) -> TRUE | AD36: =VLOOKUP(Y36,lists!$B$7:$D$8,3,FALSE) -> TRUE | AE36: =VLOOKUP(SUBSTITUTE(IF(H36="","Open",H36),"Beg","Mdn"),lists!$B$27:$D$29,3,FALSE) -> TRUE | AF36: =IF(JUMP!$I$5="All",TRUE,IF(JUMP!$I$5=TEXT('Raw - J'!C36,"mmm"),TRUE,FALSE)) -> TRUE | AG36: =VLOOKUP(M36,lists!B:D,3,FALSE) -> TRUE | AH36: =VLOOKUP(T36,lists!$B$23:$D$25,3,FALSE) -> TRUE | AI36: =IF(AND(AA36=TRUE,AB36=TRUE,AC36=TRUE,AD36=TRUE,AE36=TRUE,AF36=TRUE,AG36=TRUE,AH36=TRUE),1,0) -> 1
A37: =IF(B37="",A36,B37+1) -> 37 | B37: =IF(AND(A36<1,AI37=1),1,IF(AI37=1,A36,"")) -> 36 | C37: 44320 | D37: FAKENHAM | E37: Jump | F37: Hunter | G37: WFA | H37: Open | K37: 6yo+ | L37: A | M37: 6 | O37: Open | P37: 3m38y | Q37: 3m | R37: 3799 | S37: T TROPHY GRASSROOTS | T37: Midlands | U37: Amtr | X37: 0 | Y37: =IF(L37="F",L37,"A") -> A | Z37: =VLOOKUP(Q37,lists!Q:R,2,FALSE) -> 5 | AA37: =VLOOKUP(G37,lists!$B$2:$D$3,3,FALSE) -> TRUE | AB37: =VLOOKUP(F37,lists!$B:$C,2,FALSE) -> TRUE | AC37: =IF(AND(Z37>=VLOOKUP(JUMP!$I$1,lists!$Q:$R,2,FALSE),Z37<=VLOOKUP(JUMP!$I$2,lists!$Q:$R,2,FALSE)),TRUE,FALSE) -> TRUE | AD37: =VLOOKUP(Y37,lists!$B$7:$D$8,3,FALSE) -> TRUE | AE37: =VLOOKUP(SUBSTITUTE(IF(H37="","Open",H37),"Beg","Mdn"),lists!$B$27:$D$29,3,FALSE) -> TRUE | AF37: =IF(JUMP!$I$5="All",TRUE,IF(JUMP!$I$5=TEXT('Raw - J'!C37,"mmm"),TRUE,FALSE)) -> TRUE | AG37: =VLOOKUP(M37,lists!B:D,3,FALSE) -> TRUE | AH37: =VLOOKUP(T37,lists!$B$23:$D$25,3,FALSE) -> TRUE | AI37: =IF(AND(AA37=TRUE,AB37=TRUE,AC37=TRUE,AD37=TRUE,AE37=TRUE,AF37=TRUE,AG37=TRUE,AH37=TRUE),1,0) -> 1
A38: =IF(B38="",A37,B38+1) -> 38 | B38: =IF(AND(A37<1,AI38=1),1,IF(AI38=1,A37,"")) -> 37 | C38: 44320 | D38: FAKENHAM | E38: Jump | F38: Hurdle | G38: Hcap | H38: Open | K38: 4yo+ | L38: A | M38: 5 | O38: Open | P38: 2m3y | Q38: 2m | R38: 6400 | S38: JARROLD SELL HUR | T38: Midlands | V38: S | X38: 0 | Y38: =IF(L38="F",L38,"A") -> A | Z38: =VLOOKUP(Q38,lists!Q:R,2,FALSE) -> 2 | AA38: =VLOOKUP(G38,lists!$B$2:$D$3,3,FALSE) -> TRUE | AB38: =VLOOKUP(F38,lists!$B:$C,2,FALSE) -> TRUE | AC38: =IF(AND(Z38>=VLOOKUP(JUMP!$I$1,lists!$Q:$R,2,FALSE),Z38<=VLOOKUP(JUMP!$I$2,lists!$Q:$R,2,FALSE)),TRUE,FALSE) -> TRUE | AD38: =VLOOKUP(Y38,lists!$B$7:$D$8,3,FALSE) -> TRUE | AE38: =VLOOKUP(SUBSTITUTE(IF(H38="","Open",H38),"Beg","Mdn"),lists!$B$27:$D$29,3,FALSE) -> TRUE | AF38: =IF(JUMP!$I$5="All",TRUE,IF(JUMP!$I$5=TEXT('Raw - J'!C38,"mmm"),TRUE,FALSE)) -> TRUE | AG38: =VLOOKUP(M38,lists!B:D,3,FALSE) -> TRUE | AH38: =VLOOKUP(T38,lists!$B$23:$D$25,3,FALSE) -> TRUE | AI38: =IF(AND(AA38=TRUE,AB38=TRUE,AC38=TRUE,AD38=TRUE,AE38=TRUE,AF38=TRUE,AG38=TRUE,AH38=TRUE),1,0) -> 1
A39: =IF(B39="",A38,B39+1) -> 39 | B39: =IF(AND(A38<1,AI39=1),1,IF(AI39=1,A38,"")) -> 38 | C39: 44320 | D39: FAKENHAM | E39: Jump | F39: Chase | G39: Hcap | H39: Open | K39: 5yo+ | L39: A | M39: 5 | O39: 0-100 | P39: 2m5f44y | Q39: 2m 4f | R39: 7000 | S39: LIGHTDOOR HCAP CSE | T39: Midlands | X39: 0 | Y39: =IF(L39="F",L39,"A") -> A | Z39: =VLOOKUP(Q39,lists!Q:R,2,FALSE) -> 3 | AA39: =VLOOKUP(G39,lists!$B$2:$D$3,3,FALSE) -> TRUE | AB39: =VLOOKUP(F39,lists!$B:$C,2,FALSE) -> TRUE | AC39: =IF(AND(Z39>=VLOOKUP(JUMP!$I$1,lists!$Q:$R,2,FALSE),Z39<=VLOOKUP(JUMP!$I$2,lists!$Q:$R,2,FALSE)),TRUE,FALSE) -> TRUE | AD39: =VLOOKUP(Y39,lists!$B$7:$D$8,3,FALSE) -> TRUE | AE39: =VLOOKUP(SUBSTITUTE(IF(H39="","Open",H39),"Beg","Mdn"),lists!$B$27:$D$29,3,FALSE) -> TRUE | AF39: =IF(JUMP!$I$5="All",TRUE,IF(JUMP!$I$5=TEXT('Raw - J'!C39,"mmm"),TRUE,FALSE)) -> TRUE | AG39: =VLOOKUP(M39,lists!B:D,3,FALSE) -> TRUE | AH39: =VLOOKUP(T39,lists!$B$23:$D$25,3,FALSE) -> TRUE | AI39: =IF(AND(AA39=TRUE,AB39=TRUE,AC39=TRUE,AD39=TRUE,AE39=TRUE,AF39=TRUE,AG39=TRUE,AH39=TRUE),1,0) -> 1
A40: =IF(B40="",A39,B40+1) -> 40 | B40: =IF(AND(A39<1,AI40=1),1,IF(AI40=1,A39,"")) -> 39 | C40: 44320 | D40: FAKENHAM | E40: Jump | F40: Hurdle | G40: WFA | H40: Mdn | K40: 4yo+ | L40: A | M40: 4 | O40: Open | P40: 2m4f1y | Q40: 2m 4f | R40: 8000 | S40: SNELLINGS MDN HUR | T40: Midlands | X40: 0 | Y40: =IF(L40="F",L40,"A") -> A | Z40: =VLOOKUP(Q40,lists!Q:R,2,FALSE) -> 3 | AA40: =VLOOKUP(G40,lists!$B$2:$D$3,3,FALSE) -> TRUE | AB40: =VLOOKUP(F40,lists!$B:$C,2,FALSE) -> TRUE | AC40: =IF(AND(Z40>=VLOOKUP(JUMP!$I$1,lists!$Q:$R,2,FALSE),Z40<=VLOOKUP(JUMP!$I$2,lists!$Q:$R,2,FALSE)),TRUE,FALSE) -> TRUE | AD40: =VLOOKUP(Y40,lists!$B$7:$D$8,3,FALSE) -> TRUE | AE40: =VLOOKUP(SUBSTITUTE(IF(H40="","Open",H40),"Beg","Mdn"),lists!$B$27:$D$29,3,FALSE) -> TRUE | AF40: =IF(JUMP!$I$5="All",TRUE,IF(JUMP!$I$5=TEXT('Raw - J'!C40,"mmm"),TRUE,FALSE)) -> TRUE | AG40: =VLOOKUP(M40,lists!B:D,3,FALSE) -> TRUE | AH40: =VLOOKUP(T40,lists!$B$23:$D$25,3,FALSE) -> TRUE | AI40: =IF(AND(AA40=TRUE,AB40=TRUE,AC40=TRUE,AD40=TRUE,AE40=TRUE,AF40=TRUE,AG40=TRUE,AH40=TRUE),1,0) -> 1
A41: =IF(B41="",A40,B41+1) -> 41 | B41: =IF(AND(A40<1,AI41=1),1,IF(AI41=1,A40,"")) -> 40 | C41: 44320 | D41: FAKENHAM | E41: Jump | F41: Hurdle | G41: Hcap | H41: Open | K41: 4yo+ | L41: F | M41: 5 | O41: 0-100 | P41: 2m3y | Q41: 2m | R41: 8000 | S41: SNELLINGS HCAP HUR | T41: Midlands | X41: 0 | Y41: =IF(L41="F",L41,"A") -> F | Z41: =VLOOKUP(Q41,lists!Q:R,2,FALSE) -> 2 | AA41: =VLOOKUP(G41,lists!$B$2:$D$3,3,FALSE) -> TRUE | AB41: =VLOOKUP(F41,lists!$B:$C,2,FALSE) -> TRUE | AC41: =IF(AND(Z41>=VLOOKUP(JUMP!$I$1,lists!$Q:$R,2,FALSE),Z41<=VLOOKUP(JUMP!$I$2,lists!$Q:$R,2,FALSE)),TRUE,FALSE) -> TRUE | AD41: =VLOOKUP(Y41,lists!$B$7:$D$8,3,FALSE) -> TRUE | AE41: =VLOOKUP(SUBSTITUTE(IF(H41="","Open",H41),"Beg","Mdn"),lists!$B$27:$D$29,3,FALSE) -> TRUE | AF41: =IF(JUMP!$I$5="All",TRUE,IF(JUMP!$I$5=TEXT('Raw - J'!C41,"mmm"),TRUE,FALSE)) -> TRUE | AG41: =VLOOKUP(M41,lists!B:D,3,FALSE) -> TRUE | AH41: =VLOOKUP(T41,lists!$B$23:$D$25,3,FALSE) -> TRUE | AI41: =IF(AND(AA41=TRUE,AB41=TRUE,AC41=TRUE,AD41=TRUE,AE41=TRUE,AF41=TRUE,AG41=TRUE,AH41=TRUE),1,0) -> 1
A42: =IF(B42="",A41,B42+1) -> 42 | B42: =IF(AND(A41<1,AI42=1),1,IF(AI42=1,A41,"")) -> 41 | C42: 44320 | D42: FAKENHAM | E42: Jump | F42: Chase | G42: Hcap | H42: Open | K42: 5yo+ | L42: A | M42: 3 | O42: 0-125 | P42: 3m5f24y | Q42: 3m 4f+ | R42: 30000 | S42: NORFOLK HCAP CSE | T42: Midlands | X42: 0 | Y42: =IF(L42="F",L42,"A") -> A | Z42: =VLOOKUP(Q42,lists!Q:R,2,FALSE) -> 6 | AA42: =VLOOKUP(G42,lists!$B$2:$D$3,3,FALSE) -> TRUE | AB42: =VLOOKUP(F42,lists!$B:$C,2,FALSE) -> TRUE | AC42: =IF(AND(Z42>=VLOOKUP(JUMP!$I$1,lists!$Q:$R,2,FALSE),Z42<=VLOOKUP(JUMP!$I$2,lists!$Q:$R,2,FALSE)),TRUE,FALSE) -> TRUE | AD42: =VLOOKUP(Y42,lists!$B$7:$D$8,3,FALSE) -> TRUE | AE42: =VLOOKUP(SUBSTITUTE(IF(H42="","Open",H42),"Beg","Mdn"),lists!$B$27:$D$29,3,FALSE) -> TRUE | AF42: =IF(JUMP!$I$5="All",TRUE,IF(JUMP!$I$5=TEXT('Raw - J'!C42,"mmm"),TRUE,FALSE)) -> TRUE | AG42: =VLOOKUP(M42,lists!B:D,3,FALSE) -> TRUE | AH42: =VLOOKUP(T42,lists!$B$23:$D$25,3,FALSE) -> TRUE | AI42: =IF(AND(AA42=TRUE,AB42=TRUE,AC42=TRUE,AD42=TRUE,AE42=TRUE,AF42=TRUE,AG42=TRUE,AH42=TRUE),1,0) -> 1
A43: =IF(B43="",A42,B43+1) -> 43 | B43: =IF(AND(A42<1,AI43=1),1,IF(AI43=1,A42,"")) -> 42 | C43: 44320 | D43: SOUTHWELL | E43: Jump | F43: NHF | G43: WFA | H43: Open | I43: Intermediate | K43: 4-6yo | L43: A | M43: 5 | O43: Open | P43: 1m7f153y | Q43: 2m | R43: 3500 | T43: Midlands | X43: 0 | Y43: =IF(L43="F",L43,"A") -> A | Z43: =VLOOKUP(Q43,lists!Q:R,2,FALSE) -> 2 | AA43: =VLOOKUP(G43,lists!$B$2:$D$3,3,FALSE) -> TRUE | AB43: =VLOOKUP(F43,lists!$B:$C,2,FALSE) -> TRUE | AC43: =IF(AND(Z43>=VLOOKUP(JUMP!$I$1,lists!$Q:$R,2,FALSE),Z43<=VLOOKUP(JUMP!$I$2,lists!$Q:$R,2,FALSE)),TRUE,FALSE) -> TRUE | AD43: =VLOOKUP(Y43,lists!$B$7:$D$8,3,FALSE) -> TRUE | AE43: =VLOOKUP(SUBSTITUTE(IF(H43="","Open",H43),"Beg","Mdn"),lists!$B$27:$D$29,3,FALSE) -> TRUE | AF43: =IF(JUMP!$I$5="All",TRUE,IF(JUMP!$I$5=TEXT('Raw - J'!C43,"mmm"),TRUE,FALSE)) -> TRUE | AG43: =VLOOKUP(M43,lists!B:D,3,FALSE) -> TRUE | AH43: =VLOOKUP(T43,lists!$B$23:$D$25,3,FALSE) -> TRUE | AI43: =IF(AND(AA43=TRUE,AB43=TRUE,AC43=TRUE,AD43=TRUE,AE43=TRUE,AF43=TRUE,AG43=TRUE,AH43=TRUE),1,0) -> 1
A44: =IF(B44="",A43,B44+1) -> 44 | B44: =IF(AND(A43<1,AI44=1),1,IF(AI44=1,A43,"")) -> 43 | C44: 44320 | D44: SOUTHWELL | E44: Jump | F44: Hurdle | G44: Hcap | H44: Open | K44: 4yo+ | L44: A | M44: 5 | O44: 0-100 | P44: 1m7f153y | Q44: 2m | R44: 3900 | T44: Midlands | X44: 0 | Y44: =IF(L44="F",L44,"A") -> A | Z44: =VLOOKUP(Q44,lists!Q:R,2,FALSE) -> 2 | AA44: =VLOOKUP(G44,lists!$B$2:$D$3,3,FALSE) -> TRUE | AB44: =VLOOKUP(F44,lists!$B:$C,2,FALSE) -> TRUE | AC44: =IF(AND(Z44>=VLOOKUP(JUMP!$I$1,lists!$Q:$R,2,FALSE),Z44<=VLOOKUP(JUMP!$I$2,lists!$Q:$R,2,FALSE)),TRUE,FALSE) -> TRUE | AD44: =VLOOKUP(Y44,lists!$B$7:$D$8,3,FALSE) -> TRUE | AE44: =VLOOKUP(SUBSTITUTE(IF(H44="","Open",H44),"Beg","Mdn"),lists!$B$27:$D$29,3,FALSE) -> TRUE | AF44: =IF(JUMP!$I$5="All",TRUE,IF(JUMP!$I$5=TEXT('Raw - J'!C44,"mmm"),TRUE,FALSE)) -> TRUE | AG44: =VLOOKUP(M44,lists!B:D,3,FALSE) -> TRUE | AH44: =VLOOKUP(T44,lists!$B$23:$D$25,3,FALSE) -> TRUE | AI44: =IF(AND(AA44=TRUE,AB44=TRUE,AC44=TRUE,AD44=TRUE,AE44=TRUE,AF44=TRUE,AG44=TRUE,AH44=TRUE),1,0) -> 1
A45: =IF(B45="",A44,B45+1) -> 45 | B45: =IF(AND(A44<1,AI45=1),1,IF(AI45=1,A44,"")) -> 44 | C45: 44320 | D45: SOUTHWELL | E45: Jump | F45: Hurdle | G45: Hcap | H45: Open | K45: 5yo+ | L45: A | M45: 5 | O45: 0-100 | P45: 2m7f209y | Q45: 3m | R45: 3900 | T45: Midlands | X45: 0 | Y45: =IF(L45="F",L45,"A") -> A | Z45: =VLOOKUP(Q45,lists!Q:R,2,FALSE) -> 5 | AA45: =VLOOKUP(G45,lists!$B$2:$D$3,3,FALSE) -> TRUE | AB45: =VLOOKUP(F45,lists!$B:$C,2,FALSE) -> TRUE | AC45: =IF(AND(Z45>=VLOOKUP(JUMP!$I$1,lists!$Q:$R,2,FALSE),Z45<=VLOOKUP(JUMP!$I$2,lists!$Q:$R,2,FALSE)),TRUE,FALSE) -> TRUE | AD45: =VLOOKUP(Y45,lists!$B$7:$D$8,3,FALSE) -> TRUE | AE45: =VLOOKUP(SUBSTITUTE(IF(H45="","Open",H45),"Beg","Mdn"),lists!$B$27:$D$29,3,FALSE) -> TRUE | AF45: =IF(JUMP!$I$5="All",TRUE,IF(JUMP!$I$5=TEXT('Raw - J'!C45,"mmm"),TRUE,FALSE)) -> TRUE | AG45: =VLOOKUP(M45,lists!B:D,3,FALSE) -> TRUE | AH45: =VLOOKUP(T45,lists!$B$23:$D$25,3,FALSE) -> TRUE | AI45: =IF(AND(AA45=TRUE,AB45=TRUE,AC45=TRUE,AD45=TRUE,AE45=TRUE,AF45=TRUE,AG45=TRUE,AH45=TRUE),1,0) -> 1
A46: =IF(B46="",A45,B46+1) -> 46 | B46: =IF(AND(A45<1,AI46=1),1,IF(AI46=1,A45,"")) -> 45 | C46: 44320 | D46: SOUTHWELL | E46: Jump | F46: Hurdle | G46: WFA | H46: Nov | K46: 4yo+ | L46: A | M46: 4 | O46: Open | P46: 2m4f62y | Q46: 2m 4f | R46: 5400 | T46: Midlands | X46: 0 | Y46: =IF(L46="F",L46,"A") -> A | Z46: =VLOOKUP(Q46,lists!Q:R,2,FALSE) -> 3 | AA46: =VLOOKUP(G46,lists!$B$2:$D$3,3,FALSE) -> TRUE | AB46: =VLOOKUP(F46,lists!$B:$C,2,FALSE) -> TRUE | AC46: =IF(AND(Z46>=VLOOKUP(JUMP!$I$1,lists!$Q:$R,2,FALSE),Z46<=VLOOKUP(JUMP!$I$2,lists!$Q:$R,2,FALSE)),TRUE,FALSE) -> TRUE | AD46: =VLOOKUP(Y46,lists!$B$7:$D$8,3,FALSE) -> TRUE | AE46: =VLOOKUP(SUBSTITUTE(IF(H46="","Open",H46),"Beg","Mdn"),lists!$B$27:$D$29,3,FALSE) -> TRUE | AF46: =IF(JUMP!$I$5="All",TRUE,IF(JUMP!$I$5=TEXT('Raw - J'!C46,"mmm"),TRUE,FALSE)) -> TRUE | AG46: =VLOOKUP(M46,lists!B:D,3,FALSE) -> TRUE | AH46: =VLOOKUP(T46,lists!$B$23:$D$25,3,FALSE) -> TRUE | AI46: =IF(AND(AA46=TRUE,AB46=TRUE,AC46=TRUE,AD46=TRUE,AE46=TRUE,AF46=TRUE,AG46=TRUE,AH46=TRUE),1,0) -> 1
A47: =IF(B47="",A46,B47+1) -> 47 | B47: =IF(AND(A46<1,AI47=1),1,IF(AI47=1,A46,"")) -> 46 | C47: 44320 | D47: SOUTHWELL | E47: Jump | F47: Hurdle | G47: Hcap | H47: Open | K47: 4yo+ | L47: A | M47: 4 | O47: 0-110 | P47: 2m4f62y | Q47: 2m 4f | R47: 5400 | T47: Midlands | X47: 0 | Y47: =IF(L47="F",L47,"A") -> A | Z47: =VLOOKUP(Q47,lists!Q:R,2,FALSE) -> 3 | AA47: =VLOOKUP(G47,lists!$B$2:$D$3,3,FALSE) -> TRUE | AB47: =VLOOKUP(F47,lists!$B:$C,2,FALSE) -> TRUE | AC47: =IF(AND(Z47>=VLOOKUP(JUMP!$I$1,lists!$Q:$R,2,FALSE),Z47<=VLOOKUP(JUMP!$I$2,lists!$Q:$R,2,FALSE)),TRUE,FALSE) -> TRUE | AD47: =VLOOKUP(Y47,lists!$B$7:$D$8,3,FALSE) -> TRUE | AE47: =VLOOKUP(SUBSTITUTE(IF(H47="","Open",H47),"Beg","Mdn"),lists!$B$27:$D$29,3,FALSE) -> TRUE | AF47: =IF(JUMP!$I$5="All",TRUE,IF(JUMP!$I$5=TEXT('Raw - J'!C47,"mmm"),TRUE,FALSE)) -> TRUE | AG47: =VLOOKUP(M47,lists!B:D,3,FALSE) -> TRUE | AH47: =VLOOKUP(T47,lists!$B$23:$D$25,3,FALSE) -> TRUE | AI47: =IF(AND(AA47=TRUE,AB47=TRUE,AC47=TRUE,AD47=TRUE,AE47=TRUE,AF47=TRUE,AG47=TRUE,AH47=TRUE),1,0) -> 1
A48: =IF(B48="",A47,B48+1) -> 48 | B48: =IF(AND(A47<1,AI48=1),1,IF(AI48=1,A47,"")) -> 47 | C48: 44320 | D48: SOUTHWELL | E48: Jump | F48: Chase | G48: Hcap | H48: Open | K48: 5yo+ | L48: A | M48: 4 | O48: 0-115 | P48: 2m4f62y | Q48: 2m 4f | R48: 6200 | T48: Midlands | X48: 0 | Y48: =IF(L48="F",L48,"A") -> A | Z48: =VLOOKUP(Q48,lists!Q:R,2,FALSE) -> 3 | AA48: =VLOOKUP(G48,lists!$B$2:$D$3,3,FALSE) -> TRUE | AB48: =VLOOKUP(F48,lists!$B:$C,2,FALSE) -> TRUE | AC48: =IF(AND(Z48>=VLOOKUP(JUMP!$I$1,lists!$Q:$R,2,FALSE),Z48<=VLOOKUP(JUMP!$I$2,lists!$Q:$R,2,FALSE)),TRUE,FALSE) -> TRUE | AD48: =VLOOKUP(Y48,lists!$B$7:$D$8,3,FALSE) -> TRUE | AE48: =VLOOKUP(SUBSTITUTE(IF(H48="","Open",H48),"Beg","Mdn"),lists!$B$27:$D$29,3,FALSE) -> TRUE | AF48: =IF(JUMP!$I$5="All",TRUE,IF(JUMP!$I$5=TEXT('Raw - J'!C48,"mmm"),TRUE,FALSE)) -> TRUE | AG48: =VLOOKUP(M48,lists!B:D,3,FALSE) -> TRUE | AH48: =VLOOKUP(T48,lists!$B$23:$D$25,3,FALSE) -> TRUE | AI48: =IF(AND(AA48=TRUE,AB48=TRUE,AC48=TRUE,AD48=TRUE,AE48=TRUE,AF48=TRUE,AG48=TRUE,AH48=TRUE),1,0) -> 1
A49: =IF(B49="",A48,B49+1) -> 49 | B49: =IF(AND(A48<1,AI49=1),1,IF(AI49=1,A48,"")) -> 48 | C49: 44320 | D49: SOUTHWELL | E49: Jump | F49: Chase | G49: Hcap | H49: Nov | K49: 5yo+ | L49: A | M49: 4 | O49: 0-120 | P49: 2m7f209y | Q49: 3m | R49: 6200 | T49: Midlands | X49: 0 | Y49: =IF(L49="F",L49,"A") -> A | Z49: =VLOOKUP(Q49,lists!Q:R,2,FALSE) -> 5 | AA49: =VLOOKUP(G49,lists!$B$2:$D$3,3,FALSE) -> TRUE | AB49: =VLOOKUP(F49,lists!$B:$C,2,FALSE) -> TRUE | AC49: =IF(AND(Z49>=VLOOKUP(JUMP!$I$1,lists!$Q:$R,2,FALSE),Z49<=VLOOKUP(JUMP!$I$2,lists!$Q:$R,2,FALSE)),TRUE,FALSE) -> TRUE | AD49: =VLOOKUP(Y49,lists!$B$7:$D$8,3,FALSE) -> TRUE | AE49: =VLOOKUP(SUBSTITUTE(IF(H49="","Open",H49),"Beg","Mdn"),lists!$B$27:$D$29,3,FALSE) -> TRUE | AF49: =IF(JUMP!$I$5="All",TRUE,IF(JUMP!$I$5=TEXT('Raw - J'!C49,"mmm"),TRUE,FALSE)) -> TRUE | AG49: =VLOOKUP(M49,lists!B:D,3,FALSE) -> TRUE | AH49: =VLOOKUP(T49,lists!$B$23:$D$25,3,FALSE) -> TRUE | AI49: =IF(AND(AA49=TRUE,AB49=TRUE,AC49=TRUE,AD49=TRUE,AE49=TRUE,AF49=TRUE,AG49=TRUE,AH49=TRUE),1,0) -> 1
A50: =IF(B50="",A49,B50+1) -> 50 | B50: =IF(AND(A49<1,AI50=1),1,IF(AI50=1,A49,"")) -> 49 | C50: 44321 | D50: FONTWELL PARK | E50: Jump | F50: NHF | G50: WFA | H50: Open | K50: 4-6yo | L50: F | M50: 5 | O50: Open | P50: 2m1f162y | Q50: 2m | R50: 3500 | S50: INDUSTRY OPEN NHF | T50: South | X50: 0 | Y50: =IF(L50="F",L50,"A") -> F | Z50: =VLOOKUP(Q50,lists!Q:R,2,FALSE) -> 2 | AA50: =VLOOKUP(G50,lists!$B$2:$D$3,3,FALSE) -> TRUE | AB50: =VLOOKUP(F50,lists!$B:$C,2,FALSE) -> TRUE | AC50: =IF(AND(Z50>=VLOOKUP(JUMP!$I$1,lists!$Q:$R,2,FALSE),Z50<=VLOOKUP(JUMP!$I$2,lists!$Q:$R,2,FALSE)),TRUE,FALSE) -> TRUE | AD50: =VLOOKUP(Y50,lists!$B$7:$D$8,3,FALSE) -> TRUE | AE50: =VLOOKUP(SUBSTITUTE(IF(H50="","Open",H50),"Beg","Mdn"),lists!$B$27:$D$29,3,FALSE) -> TRUE | AF50: =IF(JUMP!$I$5="All",TRUE,IF(JUMP!$I$5=TEXT('Raw - J'!C50,"mmm"),TRUE,FALSE)) -> TRUE | AG50: =VLOOKUP(M50,lists!B:D,3,FALSE) -> TRUE | AH50: =VLOOKUP(T50,lists!$B$23:$D$25,3,FALSE) -> TRUE | AI50: =IF(AND(AA50=TRUE,AB50=TRUE,AC50=TRUE,AD50=TRUE,AE50=TRUE,AF50=TRUE,AG50=TRUE,AH50=TRUE),1,0) -> 1
A51: =IF(B51="",A50,B51+1) -> 51 | B51: =IF(AND(A50<1,AI51=1),1,IF(AI51=1,A50,"")) -> 50 | C51: 44321 | D51: FONTWELL PARK | E51: Jump | F51: Hurdle | G51: Hcap | H51: Open | K51: 4yo+ | L51: A | M51: 5 | O51: 0-100 | P51: 2m5f164y | Q51: 2m 4f | R51: 3900 | S51: STAR SPORTS HCP HUR | T51: South | X51: 0 | Y51: =IF(L51="F",L51,"A") -> A | Z51: =VLOOKUP(Q51,lists!Q:R,2,FALSE) -> 3 | AA51: =VLOOKUP(G51,lists!$B$2:$D$3,3,FALSE) -> TRUE | AB51: =VLOOKUP(F51,lists!$B:$C,2,FALSE) -> TRUE | AC51: =IF(AND(Z51>=VLOOKUP(JUMP!$I$1,lists!$Q:$R,2,FALSE),Z51<=VLOOKUP(JUMP!$I$2,lists!$Q:$R,2,FALSE)),TRUE,FALSE) -> TRUE | AD51: =VLOOKUP(Y51,lists!$B$7:$D$8,3,FALSE) -> TRUE | AE51: =VLOOKUP(SUBSTITUTE(IF(H51="","Open",H51),"Beg","Mdn"),lists!$B$27:$D$29,3,FALSE) -> TRUE | AF51: =IF(JUMP!$I$5="All",TRUE,IF(JUMP!$I$5=TEXT('Raw - J'!C51,"mmm"),TRUE,FALSE)) -> TRUE | AG51: =VLOOKUP(M51,lists!B:D,3,FALSE) -> TRUE | AH51: =VLOOKUP(T51,lists!$B$23:$D$25,3,FALSE) -> TRUE | AI51: =IF(AND(AA51=TRUE,AB51=TRUE,AC51=TRUE,AD51=TRUE,AE51=TRUE,AF51=TRUE,AG51=TRUE,AH51=TRUE),1,0) -> 1
A52: =IF(B52="",A51,B52+1) -> 52 | B52: =IF(AND(A51<1,AI52=1),1,IF(AI52=1,A51,"")) -> 51 | C52: 44321 | D52: FONTWELL PARK | E52: Jump | F52: Hurdle | G52: Hcap | H52: Nov | K52: 4yo+ | L52: A | M52: 4 | O52: 0-115 | P52: 3m1f166y | Q52: 3m | R52: 5400 | S52: DOWNLOAD NOV HUR | T52: South | X52: 0 | Y52: =IF(L52="F",L52,"A") -> A | Z52: =VLOOKUP(Q52,lists!Q:R,2,FALSE) -> 5 | AA52: =VLOOKUP(G52,lists!$B$2:$D$3,3,FALSE) -> TRUE | AB52: =VLOOKUP(F52,lists!$B:$C,2,FALSE) -> TRUE | AC52: =IF(AND(Z52>=VLOOKUP(JUMP!$I$1,lists!$Q:$R,2,FALSE),Z52<=VLOOKUP(JUMP!$I$2,lists!$Q:$R,2,FALSE)),TRUE,FALSE) -> TRUE | AD52: =VLOOKUP(Y52,lists!$B$7:$D$8,3,FALSE) -> TRUE | AE52: =VLOOKUP(SUBSTITUTE(IF(H52="","Open",H52),"Beg","Mdn"),lists!$B$27:$D$29,3,FALSE) -> TRUE | AF52: =IF(JUMP!$I$5="All",TRUE,IF(JUMP!$I$5=TEXT('Raw - J'!C52,"mmm"),TRUE,FALSE)) -> TRUE | AG52: =VLOOKUP(M52,lists!B:D,3,FALSE) -> TRUE | AH52: =VLOOKUP(T52,lists!$B$23:$D$25,3,FALSE) -> TRUE | AI52: =IF(AND(AA52=TRUE,AB52=TRUE,AC52=TRUE,AD52=TRUE,AE52=TRUE,AF52=TRUE,AG52=TRUE,AH52=TRUE),1,0) -> 1
A53: =IF(B53="",A52,B53+1) -> 53 | B53: =IF(AND(A52<1,AI53=1),1,IF(AI53=1,A52,"")) -> 52 | C53: 44321 | D53: FONTWELL PARK | E53: Jump | F53: Hurdle | G53: WFA | H53: Nov | K53: 4yo+ | L53: A | M53: 4 | O53: Open | P53: 2m3f49y | Q53: 2m 4f | R53: 5400 | S53: SABIN NOV HUR | T53: South | X53: 0 | Y53: =IF(L53="F",L53,"A") -> A | Z53: =VLOOKUP(Q53,lists!Q:R,2,FALSE) -> 3 | AA53: =VLOOKUP(G53,lists!$B$2:$D$3,3,FALSE) -> TRUE | AB53: =VLOOKUP(F53,lists!$B:$C,2,FALSE) -> TRUE | AC53: =IF(AND(Z53>=VLOOKUP(JUMP!$I$1,lists!$Q:$R,2,FALSE),Z53<=VLOOKUP(JUMP!$I$2,lists!$Q:$R,2,FALSE)),TRUE,FALSE) -> TRUE | AD53: =VLOOKUP(Y53,lists!$B$7:$D$8,3,FALSE) -> TRUE | AE53: =VLOOKUP(SUBSTITUTE(IF(H53="","Open",H53),"Beg","Mdn"),lists!$B$27:$D$29,3,FALSE) -> TRUE | AF53: =IF(JUMP!$I$5="All",TRUE,IF(JUMP!$I$5=TEXT('Raw - J'!C53,"mmm"),TRUE,FALSE)) -> TRUE | AG53: =VLOOKUP(M53,lists!B:D,3,FALSE) -> TRUE | AH53: =VLOOKUP(T53,lists!$B$23:$D$25,3,FALSE) -> TRUE | AI53: =IF(AND(AA53=TRUE,AB53=TRUE,AC53=TRUE,AD53=TRUE,AE53=TRUE,AF53=TRUE,AG53=TRUE,AH53=TRUE),1,0) -> 1
A54: =IF(B54="",A53,B54+1) -> 54 | B54: =IF(AND(A53<1,AI54=1),1,IF(AI54=1,A53,"")) -> 53 | C54: 44321 | D54: FONTWELL PARK | E54: Jump | F54: Hurdle | G54: Hcap | H54: Open | K54: 4yo+ | L54: A | M54: 4 | O54: 0-120 | P54: 2m3f49y | Q54: 2m 4f | R54: 5400 | S54: SPORTS CDL HCP HUR | T54: South | U54: Cond | X54: 0 | Y54: =IF(L54="F",L54,"A") -> A | Z54: =VLOOKUP(Q54,lists!Q:R,2,FALSE) -> 3 | AA54: =VLOOKUP(G54,lists!$B$2:$D$3,3,FALSE) -> TRUE | AB54: =VLOOKUP(F54,lists!$B:$C,2,FALSE) -> TRUE | AC54: =IF(AND(Z54>=VLOOKUP(JUMP!$I$1,lists!$Q:$R,2,FALSE),Z54<=VLOOKUP(JUMP!$I$2,lists!$Q:$R,2,FALSE)),TRUE,FALSE) -> TRUE | AD54: =VLOOKUP(Y54,lists!$B$7:$D$8,3,FALSE) -> TRUE | AE54: =VLOOKUP(SUBSTITUTE(IF(H54="","Open",H54),"Beg","Mdn"),lists!$B$27:$D$29,3,FALSE) -> TRUE | AF54: =IF(JUMP!$I$5="All",TRUE,IF(JUMP!$I$5=TEXT('Raw - J'!C54,"mmm"),TRUE,FALSE)) -> TRUE | AG54: =VLOOKUP(M54,lists!B:D,3,FALSE) -> TRUE | AH54: =VLOOKUP(T54,lists!$B$23:$D$25,3,FALSE) -> TRUE | AI54: =IF(AND(AA54=TRUE,AB54=TRUE,AC54=TRUE,AD54=TRUE,AE54=TRUE,AF54=TRUE,AG54=TRUE,AH54=TRUE),1,0) -> 1
A55: =IF(B55="",A54,B55+1) -> 55 | B55: =IF(AND(A54<1,AI55=1),1,IF(AI55=1,A54,"")) -> 54 | C55: 44321 | D55: FONTWELL PARK | E55: Jump | F55: Chase | G55: Hcap | H55: Open | K55: 5yo+ | L55: A | M55: 4 | O55: 0-115 | P55: 3m1f210y | Q55: 3m | R55: 6200 | S55: STARSPORTS HCAP CSE | T55: South | X55: 0 | Y55: =IF(L55="F",L55,"A") -> A | Z55: =VLOOKUP(Q55,lists!Q:R,2,FALSE) -> 5 | AA55: =VLOOKUP(G55,lists!$B$2:$D$3,3,FALSE) -> TRUE | AB55: =VLOOKUP(F55,lists!$B:$C,2,FALSE) -> TRUE | AC55: =IF(AND(Z55>=VLOOKUP(JUMP!$I$1,lists!$Q:$R,2,FALSE),Z55<=VLOOKUP(JUMP!$I$2,lists!$Q:$R,2,FALSE)),TRUE,FALSE) -> TRUE | AD55: =VLOOKUP(Y55,lists!$B$7:$D$8,3,FALSE) -> TRUE | AE55: =VLOOKUP(SUBSTITUTE(IF(H55="","Open",H55),"Beg","Mdn"),lists!$B$27:$D$29,3,FALSE) -> TRUE | AF55: =IF(JUMP!$I$5="All",TRUE,IF(JUMP!$I$5=TEXT('Raw - J'!C55,"mmm"),TRUE,FALSE)) -> TRUE | AG55: =VLOOKUP(M55,lists!B:D,3,FALSE) -> TRUE | AH55: =VLOOKUP(T55,lists!$B$23:$D$25,3,FALSE) -> TRUE | AI55: =IF(AND(AA55=TRUE,AB55=TRUE,AC55=TRUE,AD55=TRUE,AE55=TRUE,AF55=TRUE,AG55=TRUE,AH55=TRUE),1,0) -> 1
A56: =IF(B56="",A55,B56+1) -> 56 | B56: =IF(AND(A55<1,AI56=1),1,IF(AI56=1,A55,"")) -> 55 | C56: 44321 | D56: FONTWELL PARK | E56: Jump | F56: Chase | G56: Hcap | H56: Open | K56: 5yo+ | L56: F | M56: 4 | O56: 0-110 | P56: 2m5f135y | Q56: 2m 6f | R56: 6200 | S56: WATCH HCAP CSE | T56: South | X56: 0 | Y56: =IF(L56="F",L56,"A") -> F | Z56: =VLOOKUP(Q56,lists!Q:R,2,FALSE) -> 4 | AA56: =VLOOKUP(G56,lists!$B$2:$D$3,3,FALSE) -> TRUE | AB56: =VLOOKUP(F56,lists!$B:$C,2,FALSE) -> TRUE | AC56: =IF(AND(Z56>=VLOOKUP(JUMP!$I$1,lists!$Q:$R,2,FALSE),Z56<=VLOOKUP(JUMP!$I$2,lists!$Q:$R,2,FALSE)),TRUE,FALSE) -> TRUE | AD56: =VLOOKUP(Y56,lists!$B$7:$D$8,3,FALSE) -> TRUE | AE56: =VLOOKUP(SUBSTITUTE(IF(H56="","Open",H56),"Beg","Mdn"),lists!$B$27:$D$29,3,FALSE) -> TRUE | AF56: =IF(JUMP!$I$5="All",TRUE,IF(JUMP!$I$5=TEXT('Raw - J'!C56,"mmm"),TRUE,FALSE)) -> TRUE | AG56: =VLOOKUP(M56,lists!B:D,3,FALSE) -> TRUE | AH56: =VLOOKUP(T56,lists!$B$23:$D$25,3,FALSE) -> TRUE | AI56: =IF(AND(AA56=TRUE,AB56=TRUE,AC56=TRUE,AD56=TRUE,AE56=TRUE,AF56=TRUE,AG56=TRUE,AH56=TRUE),1,0) -> 1
A57: =IF(B57="",A56,B57+1) -> 57 | B57: =IF(AND(A56<1,AI57=1),1,IF(AI57=1,A56,"")) -> 56 | C57: 44321 | D57: KELSO | E57: Jump | F57: NHF | G57: WFA | H57: Open | K57: 4-6yo | L57: A | M57: 5 | O57: Open | P57: 2m51y | Q57: 2m | R57: 4500 | S57: RACINGTV OPEN NHF | T57: North | X57: 0 | Y57: =IF(L57="F",L57,"A") -> A | Z57: =VLOOKUP(Q57,lists!Q:R,2,FALSE) -> 2 | AA57: =VLOOKUP(G57,lists!$B$2:$D$3,3,FALSE) -> TRUE | AB57: =VLOOKUP(F57,lists!$B:$C,2,FALSE) -> TRUE | AC57: =IF(AND(Z57>=VLOOKUP(JUMP!$I$1,lists!$Q:$R,2,FALSE),Z57<=VLOOKUP(JUMP!$I$2,lists!$Q:$R,2,FALSE)),TRUE,FALSE) -> TRUE | AD57: =VLOOKUP(Y57,lists!$B$7:$D$8,3,FALSE) -> TRUE | AE57: =VLOOKUP(SUBSTITUTE(IF(H57="","Open",H57),"Beg","Mdn"),lists!$B$27:$D$29,3,FALSE) -> TRUE | AF57: =IF(JUMP!$I$5="All",TRUE,IF(JUMP!$I$5=TEXT('Raw - J'!C57,"mmm"),TRUE,FALSE)) -> TRUE | AG57: =VLOOKUP(M57,lists!B:D,3,FALSE) -> TRUE | AH57: =VLOOKUP(T57,lists!$B$23:$D$25,3,FALSE) -> TRUE | AI57: =IF(AND(AA57=TRUE,AB57=TRUE,AC57=TRUE,AD57=TRUE,AE57=TRUE,AF57=TRUE,AG57=TRUE,AH57=TRUE),1,0) -> 1
A58: =IF(B58="",A57,B58+1) -> 58 | B58: =IF(AND(A57<1,AI58=1),1,IF(AI58=1,A57,"")) -> 57 | C58: 44321 | D58: KELSO | E58: Jump | F58: Hunter | G58: WFA | H58: Nov | K58: 5yo+ | L58: A | M58: 5 | O58: Open | P58: 2m5f133y | Q58: 2m 6f | R58: 5000 | S58: RACING NOV H.CSE | T58: North | U58: Amtr | X58: 0 | Y58: =IF(L58="F",L58,"A") -> A | Z58: =VLOOKUP(Q58,lists!Q:R,2,FALSE) -> 4 | AA58: =VLOOKUP(G58,lists!$B$2:$D$3,3,FALSE) -> TRUE | AB58: =VLOOKUP(F58,lists!$B:$C,2,FALSE) -> TRUE | AC58: =IF(AND(Z58>=VLOOKUP(JUMP!$I$1,lists!$Q:$R,2,FALSE),Z58<=VLOOKUP(JUMP!$I$2,lists!$Q:$R,2,FALSE)),TRUE,FALSE) -> TRUE | AD58: =VLOOKUP(Y58,lists!$B$7:$D$8,3,FALSE) -> TRUE | AE58: =VLOOKUP(SUBSTITUTE(IF(H58="","Open",H58),"Beg","Mdn"),lists!$B$27:$D$29,3,FALSE) -> TRUE | AF58: =IF(JUMP!$I$5="All",TRUE,IF(JUMP!$I$5=TEXT('Raw - J'!C58,"mmm"),TRUE,FALSE)) -> TRUE | AG58: =VLOOKUP(M58,lists!B:D,3,FALSE) -> TRUE | AH58: =VLOOKUP(T58,lists!$B$23:$D$25,3,FALSE) -> TRUE | AI58: =IF(AND(AA58=TRUE,AB58=TRUE,AC58=TRUE,AD58=TRUE,AE58=TRUE,AF58=TRUE,AG58=TRUE,AH58=TRUE),1,0) -> 1
A59: =IF(B59="",A58,B59+1) -> 59 | B59: =IF(AND(A58<1,AI59=1),1,IF(AI59=1,A58,"")) -> 58 | C59: 44321 | D59: KELSO | E59: Jump | F59: Hurdle | G59: Hcap | H59: Open | K59: 4yo+ | L59: A | M59: 4 | O59: 0-110 | P59: 2m6f151y | Q59: 3m | R59: 6200 | S59: VILLA SANDI HCP HUR | T59: North | X59: 0 | Y59: =IF(L59="F",L59,"A") -> A | Z59: =VLOOKUP(Q59,lists!Q:R,2,FALSE) -> 5 | AA59: =VLOOKUP(G59,lists!$B$2:$D$3,3,FALSE) -> TRUE | AB59: =VLOOKUP(F59,lists!$B:$C,2,FALSE) -> TRUE | AC59: =IF(AND(Z59>=VLOOKUP(JUMP!$I$1,lists!$Q:$R,2,FALSE),Z59<=VLOOKUP(JUMP!$I$2,lists!$Q:$R,2,FALSE)),TRUE,FALSE) -> TRUE | AD59: =VLOOKUP(Y59,lists!$B$7:$D$8,3,FALSE) -> TRUE | AE59: =VLOOKUP(SUBSTITUTE(IF(H59="","Open",H59),"Beg","Mdn"),lists!$B$27:$D$29,3,FALSE) -> TRUE | AF59: =IF(JUMP!$I$5="All",TRUE,IF(JUMP!$I$5=TEXT('Raw - J'!C59,"mmm"),TRUE,FALSE)) -> TRUE | AG59: =VLOOKUP(M59,lists!B:D,3,FALSE) -> TRUE | AH59: =VLOOKUP(T59,lists!$B$23:$D$25,3,FALSE) -> TRUE | AI59: =IF(AND(AA59=TRUE,AB59=TRUE,AC59=TRUE,AD59=TRUE,AE59=TRUE,AF59=TRUE,AG59=TRUE,AH59=TRUE),1,0) -> 1
A60: =IF(B60="",A59,B60+1) -> 60 | B60: =IF(AND(A59<1,AI60=1),1,IF(AI60=1,A59,"")) -> 59 | C60: 44321 | D60: KELSO | E60: Jump | F60: Hurdle | G60: WFA | H60: Nov | K60: 4yo+ | L60: A | M60: 4 | O60: Open | P60: 2m4f189y | Q60: 2m 4f | R60: 6500 | S60: PRINCIPAL NOV HUR | T60: North | X60: 0 | Y60: =IF(L60="F",L60,"A") -> A | Z60: =VLOOKUP(Q60,lists!Q:R,2,FALSE) -> 3 | AA60: =VLOOKUP(G60,lists!$B$2:$D$3,3,FALSE) -> TRUE | AB60: =VLOOKUP(F60,lists!$B:$C,2,FALSE) -> TRUE | AC60: =IF(AND(Z60>=VLOOKUP(JUMP!$I$1,lists!$Q:$R,2,FALSE),Z60<=VLOOKUP(JUMP!$I$2,lists!$Q:$R,2,FALSE)),TRUE,FALSE) -> TRUE | AD60: =VLOOKUP(Y60,lists!$B$7:$D$8,3,FALSE) -> TRUE | AE60: =VLOOKUP(SUBSTITUTE(IF(H60="","Open",H60),"Beg","Mdn"),lists!$B$27:$D$29,3,FALSE) -> TRUE | AF60: =IF(JUMP!$I$5="All",TRUE,IF(JUMP!$I$5=TEXT('Raw - J'!C60,"mmm"),TRUE,FALSE)) -> TRUE | AG60: =VLOOKUP(M60,lists!B:D,3,FALSE) -> TRUE | AH60: =VLOOKUP(T60,lists!$B$23:$D$25,3,FALSE) -> TRUE | AI60: =IF(AND(AA60=TRUE,AB60=TRUE,AC60=TRUE,AD60=TRUE,AE60=TRUE,AF60=TRUE,AG60=TRUE,AH60=TRUE),1,0) -> 1
A61: =IF(B61="",A60,B61+1) -> 61 | B61: =IF(AND(A60<1,AI61=1),1,IF(AI61=1,A60,"")) -> 60 | C61: 44321 | D61: KELSO | E61: Jump | F61: Chase | G61: Hcap | H61: Open | K61: 5yo+ | L61: A | M61: 4 | O61: 0-120 | P61: 3m3f189y | Q61: 3m 4f+ | R61: 6700 | S61: BEDMAX HCAP CSE | T61: North | X61: 0 | Y61: =IF(L61="F",L61,"A") -> A | Z61: =VLOOKUP(Q61,lists!Q:R,2,FALSE) -> 6 | AA61: =VLOOKUP(G61,lists!$B$2:$D$3,3,FALSE) -> TRUE | AB61: =VLOOKUP(F61,lists!$B:$C,2,FALSE) -> TRUE | AC61: =IF(AND(Z61>=VLOOKUP(JUMP!$I$1,lists!$Q:$R,2,FALSE),Z61<=VLOOKUP(JUMP!$I$2,lists!$Q:$R,2,FALSE)),TRUE,FALSE) -> TRUE | AD61: =VLOOKUP(Y61,lists!$B$7:$D$8,3,FALSE) -> TRUE | AE61: =VLOOKUP(SUBSTITUTE(IF(H61="","Open",H61),"Beg","Mdn"),lists!$B$27:$D$29,3,FALSE) -> TRUE | AF61: =IF(JUMP!$I$5="All",TRUE,IF(JUMP!$I$5=TEXT('Raw - J'!C61,"mmm"),TRUE,FALSE)) -> TRUE | AG61: =VLOOKUP(M61,lists!B:D,3,FALSE) -> TRUE | AH61: =VLOOKUP(T61,lists!$B$23:$D$25,3,FALSE) -> TRUE | AI61: =IF(AND(AA61=TRUE,AB61=TRUE,AC61=TRUE,AD61=TRUE,AE61=TRUE,AF61=TRUE,AG61=TRUE,AH61=TRUE),1,0) -> 1
A62: =IF(B62="",A61,B62+1) -> 62 | B62: =IF(AND(A61<1,AI62=1),1,IF(AI62=1,A61,"")) -> 61 | C62: 44321 | D62: KELSO | E62: Jump | F62: Chase | G62: Hcap | H62: Nov | K62: 5yo+ | L62: A | M62: 4 | O62: 0-120 | P62: 2m7f96y | Q62: 3m | R62: 11200 | S62: DOUGLAS NOV HCP CSE | T62: North | X62: 0 | Y62: =IF(L62="F",L62,"A") -> A | Z62: =VLOOKUP(Q62,lists!Q:R,2,FALSE) -> 5 | AA62: =VLOOKUP(G62,lists!$B$2:$D$3,3,FALSE) -> TRUE | AB62: =VLOOKUP(F62,lists!$B:$C,2,FALSE) -> TRUE | AC62: =IF(AND(Z62>=VLOOKUP(JUMP!$I$1,lists!$Q:$R,2,FALSE),Z62<=VLOOKUP(JUMP!$I$2,lists!$Q:$R,2,FALSE)),TRUE,FALSE) -> TRUE | AD62: =VLOOKUP(Y62,lists!$B$7:$D$8,3,FALSE) -> TRUE | AE62: =VLOOKUP(SUBSTITUTE(IF(H62="","Open",H62),"Beg","Mdn"),lists!$B$27:$D$29,3,FALSE) -> TRUE | AF62: =IF(JUMP!$I$5="All",TRUE,IF(JUMP!$I$5=TEXT('Raw - J'!C62,"mmm"),TRUE,FALSE)) -> TRUE | AG62: =VLOOKUP(M62,lists!B:D,3,FALSE) -> TRUE | AH62: =VLOOKUP(T62,lists!$B$23:$D$25,3,FALSE) -> TRUE | AI62: =IF(AND(AA62=TRUE,AB62=TRUE,AC62=TRUE,AD62=TRUE,AE62=TRUE,AF62=TRUE,AG62=TRUE,AH62=TRUE),1,0) -> 1
A63: =IF(B63="",A62,B63+1) -> 63 | B63: =IF(AND(A62<1,AI63=1),1,IF(AI63=1,A62,"")) -> 62 | C63: 44321 | D63: KELSO | E63: Jump | F63: Chase | G63: Hcap | H63: Open | K63: 5yo+ | L63: A | M63: 3 | O63: 0-135 | P63: 2m1f14y | Q63: 2m | R63: 11200 | S63: J BUDDEN HCAP CSE | T63: North | X63: 0 | Y63: =IF(L63="F",L63,"A") -> A | Z63: =VLOOKUP(Q63,lists!Q:R,2,FALSE) -> 2 | AA63: =VLOOKUP(G63,lists!$B$2:$D$3,3,FALSE) -> TRUE | AB63: =VLOOKUP(F63,lists!$B:$C,2,FALSE) -> TRUE | AC63: =IF(AND(Z63>=VLOOKUP(JUMP!$I$1,lists!$Q:$R,2,FALSE),Z63<=VLOOKUP(JUMP!$I$2,lists!$Q:$R,2,FALSE)),TRUE,FALSE) -> TRUE | AD63: =VLOOKUP(Y63,lists!$B$7:$D$8,3,FALSE) -> TRUE | AE63: =VLOOKUP(SUBSTITUTE(IF(H63="","Open",H63),"Beg","Mdn"),lists!$B$27:$D$29,3,FALSE) -> TRUE | AF63: =IF(JUMP!$I$5="All",TRUE,IF(JUMP!$I$5=TEXT('Raw - J'!C63,"mmm"),TRUE,FALSE)) -> TRUE | AG63: =VLOOKUP(M63,lists!B:D,3,FALSE) -> TRUE | AH63: =VLOOKUP(T63,lists!$B$23:$D$25,3,FALSE) -> TRUE | AI63: =IF(AND(AA63=TRUE,AB63=TRUE,AC63=TRUE,AD63=TRUE,AE63=TRUE,AF63=TRUE,AG63=TRUE,AH63=TRUE),1,0) -> 1
A64: =IF(B64="",A63,B64+1) -> 64 | B64: =IF(AND(A63<1,AI64=1),1,IF(AI64=1,A63,"")) -> 63 | C64: 44321 | D64: NEWTON ABBOT | E64: Jump | F64: Hurdle | G64: Hcap | H64: Open | K64: 4yo+ | L64: F | M64: 5 | O64: 0-105 | P64: 2m2f110y | Q64: 2m 4f | R64: 7071 | S64: J SOUTHCOMBE HCP HUR | T64: South | X64: 0 | Y64: =IF(L64="F",L64,"A") -> F | Z64: =VLOOKUP(Q64,lists!Q:R,2,FALSE) -> 3 | AA64: =VLOOKUP(G64,lists!$B$2:$D$3,3,FALSE) -> TRUE | AB64: =VLOOKUP(F64,lists!$B:$C,2,FALSE) -> TRUE | AC64: =IF(AND(Z64>=VLOOKUP(JUMP!$I$1,lists!$Q:$R,2,FALSE),Z64<=VLOOKUP(JUMP!$I$2,lists!$Q:$R,2,FALSE)),TRUE,FALSE) -> TRUE | AD64: =VLOOKUP(Y64,lists!$B$7:$D$8,3,FALSE) -> TRUE | AE64: =VLOOKUP(SUBSTITUTE(IF(H64="","Open",H64),"Beg","Mdn"),lists!$B$27:$D$29,3,FALSE) -> TRUE | AF64: =IF(JUMP!$I$5="All",TRUE,IF(JUMP!$I$5=TEXT('Raw - J'!C64,"mmm"),TRUE,FALSE)) -> TRUE | AG64: =VLOOKUP(M64,lists!B:D,3,FALSE) -> TRUE | AH64: =VLOOKUP(T64,lists!$B$23:$D$25,3,FALSE) -> TRUE | AI64: =IF(AND(AA64=TRUE,AB64=TRUE,AC64=TRUE,AD64=TRUE,AE64=TRUE,AF64=TRUE,AG64=TRUE,AH64=TRUE),1,0) -> 1
A65: =IF(B65="",A64,B65+1) -> 65 | B65: =IF(AND(A64<1,AI65=1),1,IF(AI65=1,A64,"")) -> 64 | C65: 44321 | D65: NEWTON ABBOT | E65: Jump | F65: Hurdle | G65: Hcap | H65: Open | K65: 4yo+ | L65: A | M65: 3 | O65: 0-140 | P65: 2m167y | Q65: 2m | R65: 9950 | S65: ST AUSTELL HCAP HUR | T65: South | X65: 0 | Y65: =IF(L65="F",L65,"A") -> A | Z65: =VLOOKUP(Q65,lists!Q:R,2,FALSE) -> 2 | AA65: =VLOOKUP(G65,lists!$B$2:$D$3,3,FALSE) -> TRUE | AB65: =VLOOKUP(F65,lists!$B:$C,2,FALSE) -> TRUE | AC65: =IF(AND(Z65>=VLOOKUP(JUMP!$I$1,lists!$Q:$R,2,FALSE),Z65<=VLOOKUP(JUMP!$I$2,lists!$Q:$R,2,FALSE)),TRUE,FALSE) -> TRUE | AD65: =VLOOKUP(Y65,lists!$B$7:$D$8,3,FALSE) -> TRUE | AE65: =VLOOKUP(SUBSTITUTE(IF(H65="","Open",H65),"Beg","Mdn"),lists!$B$27:$D$29,3,FALSE) -> TRUE | AF65: =IF(JUMP!$I$5="All",TRUE,IF(JUMP!$I$5=TEXT('Raw - J'!C65,"mmm"),TRUE,FALSE)) -> TRUE | AG65: =VLOOKUP(M65,lists!B:D,3,FALSE) -> TRUE | AH65: =VLOOKUP(T65,lists!$B$23:$D$25,3,FALSE) -> TRUE | AI65: =IF(AND(AA65=TRUE,AB65=TRUE,AC65=TRUE,AD65=TRUE,AE65=TRUE,AF65=TRUE,AG65=TRUE,AH65=TRUE),1,0) -> 1
A66: =IF(B66="",A65,B66+1) -> 66 | B66: =IF(AND(A65<1,AI66=1),1,IF(AI66=1,A65,"")) -> 65 | C66: 44321 | D66: NEWTON ABBOT | E66: Jump | F66: Chase | G66: Hcap | H66: Open | K66: 5yo+ | L66: A | M66: 3 | O66: 0-140 | P66: 3m1f170y | Q66: 3m | R66: 10800 | S66: New Race | T66: South | X66: 0 | Y66: =IF(L66="F",L66,"A") -> A | Z66: =VLOOKUP(Q66,lists!Q:R,2,FALSE) -> 5 | AA66: =VLOOKUP(G66,lists!$B$2:$D$3,3,FALSE) -> TRUE | AB66: =VLOOKUP(F66,lists!$B:$C,2,FALSE) -> TRUE | AC66: =IF(AND(Z66>=VLOOKUP(JUMP!$I$1,lists!$Q:$R,2,FALSE),Z66<=VLOOKUP(JUMP!$I$2,lists!$Q:$R,2,FALSE)),TRUE,FALSE) -> TRUE | AD66: =VLOOKUP(Y66,lists!$B$7:$D$8,3,FALSE) -> TRUE | AE66: =VLOOKUP(SUBSTITUTE(IF(H66="","Open",H66),"Beg","Mdn"),lists!$B$27:$D$29,3,FALSE) -> TRUE | AF66: =IF(JUMP!$I$5="All",TRUE,IF(JUMP!$I$5=TEXT('Raw - J'!C66,"mmm"),TRUE,FALSE)) -> TRUE | AG66: =VLOOKUP(M66,lists!B:D,3,FALSE) -> TRUE | AH66: =VLOOKUP(T66,lists!$B$23:$D$25,3,FALSE) -> TRUE | AI66: =IF(AND(AA66=TRUE,AB66=TRUE,AC66=TRUE,AD66=TRUE,AE66=TRUE,AF66=TRUE,AG66=TRUE,AH66=TRUE),1,0) -> 1
A67: =IF(B67="",A66,B67+1) -> 67 | B67: =IF(AND(A66<1,AI67=1),1,IF(AI67=1,A66,"")) -> 66 | C67: 44321 | D67: NEWTON ABBOT | E67: Jump | F67: Hurdle | G67: WFA | H67: Nov | K67: 4yo+ | L67: F | M67: 3 | O67: Open | P67: 2m5f122y | Q67: 2m 4f | R67: 10850 | S67: SKY 415 NOV HUR | T67: South | X67: 0 | Y67: =IF(L67="F",L67,"A") -> F | Z67: =VLOOKUP(Q67,lists!Q:R,2,FALSE) -> 3 | AA67: =VLOOKUP(G67,lists!$B$2:$D$3,3,FALSE) -> TRUE | AB67: =VLOOKUP(F67,lists!$B:$C,2,FALSE) -> TRUE | AC67: =IF(AND(Z67>=VLOOKUP(JUMP!$I$1,lists!$Q:$R,2,FALSE),Z67<=VLOOKUP(JUMP!$I$2,lists!$Q:$R,2,FALSE)),TRUE,FALSE) -> TRUE | AD67: =VLOOKUP(Y67,lists!$B$7:$D$8,3,FALSE) -> TRUE | AE67: =VLOOKUP(SUBSTITUTE(IF(H67="","Open",H67),"Beg","Mdn"),lists!$B$27:$D$29,3,FALSE) -> TRUE | AF67: =IF(JUMP!$I$5="All",TRUE,IF(JUMP!$I$5=TEXT('Raw - J'!C67,"mmm"),TRUE,FALSE)) -> TRUE | AG67: =VLOOKUP(M67,lists!B:D,3,FALSE) -> TRUE | AH67: =VLOOKUP(T67,lists!$B$23:$D$25,3,FALSE) -> TRUE | AI67: =IF(AND(AA67=TRUE,AB67=TRUE,AC67=TRUE,AD67=TRUE,AE67=TRUE,AF67=TRUE,AG67=TRUE,AH67=TRUE),1,0) -> 1
A68: =IF(B68="",A67,B68+1) -> 68 | B68: =IF(AND(A67<1,AI68=1),1,IF(AI68=1,A67,"")) -> 67 | C68: 44321 | D68: NEWTON ABBOT | E68: Jump | F68: Hurdle | G68: WFA | H68: Nov | K68: 4yo+ | L68: A | M68: 3 | O68: Open | P68: 2m167y | Q68: 2m | R68: 10950 | S68: ACTUATE NOV HUR | T68: South | X68: 0 | Y68: =IF(L68="F",L68,"A") -> A | Z68: =VLOOKUP(Q68,lists!Q:R,2,FALSE) -> 2 | AA68: =VLOOKUP(G68,lists!$B$2:$D$3,3,FALSE) -> TRUE | AB68: =VLOOKUP(F68,lists!$B:$C,2,FALSE) -> TRUE | AC68: =IF(AND(Z68>=VLOOKUP(JUMP!$I$1,lists!$Q:$R,2,FALSE),Z68<=VLOOKUP(JUMP!$I$2,lists!$Q:$R,2,FALSE)),TRUE,FALSE) -> TRUE | AD68: =VLOOKUP(Y68,lists!$B$7:$D$8,3,FALSE) -> TRUE | AE68: =VLOOKUP(SUBSTITUTE(IF(H68="","Open",H68),"Beg","Mdn"),lists!$B$27:$D$29,3,FALSE) -> TRUE | AF68: =IF(JUMP!$I$5="All",TRUE,IF(JUMP!$I$5=TEXT('Raw - J'!C68,"mmm"),TRUE,FALSE)) -> TRUE | AG68: =VLOOKUP(M68,lists!B:D,3,FALSE) -> TRUE | AH68: =VLOOKUP(T68,lists!$B$23:$D$25,3,FALSE) -> TRUE | AI68: =IF(AND(AA68=TRUE,AB68=TRUE,AC68=TRUE,AD68=TRUE,AE68=TRUE,AF68=TRUE,AG68=TRUE,AH68=TRUE),1,0) -> 1
A69: =IF(B69="",A68,B69+1) -> 69 | B69: =IF(AND(A68<1,AI69=1),1,IF(AI69=1,A68,"")) -> 68 | C69: 44321 | D69: NEWTON ABBOT | E69: Jump | F69: Chase | G69: WFA | H69: Beg | K69: 5yo+ | L69: A | M69: 3 | O69: Open | P69: 3m1f170y | Q69: 3m | R69: 12950 | S69: TWITTER BEG CSE | T69: South | X69: 0 | Y69: =IF(L69="F",L69,"A") -> A | Z69: =VLOOKUP(Q69,lists!Q:R,2,FALSE) -> 5 | AA69: =VLOOKUP(G69,lists!$B$2:$D$3,3,FALSE) -> TRUE | AB69: =VLOOKUP(F69,lists!$B:$C,2,FALSE) -> TRUE | AC69: =IF(AND(Z69>=VLOOKUP(JUMP!$I$1,lists!$Q:$R,2,FALSE),Z69<=VLOOKUP(JUMP!$I$2,lists!$Q:$R,2,FALSE)),TRUE,FALSE) -> TRUE | AD69: =VLOOKUP(Y69,lists!$B$7:$D$8,3,FALSE) -> TRUE | AE69: =VLOOKUP(SUBSTITUTE(IF(H69="","Open",H69),"Beg","Mdn"),lists!$B$27:$D$29,3,FALSE) -> TRUE | AF69: =IF(JUMP!$I$5="All",TRUE,IF(JUMP!$I$5=TEXT('Raw - J'!C69,"mmm"),TRUE,FALSE)) -> TRUE | AG69: =VLOOKUP(M69,lists!B:D,3,FALSE) -> TRUE | AH69: =VLOOKUP(T69,lists!$B$23:$D$25,3,FALSE) -> TRUE | AI69: =IF(AND(AA69=TRUE,AB69=TRUE,AC69=TRUE,AD69=TRUE,AE69=TRUE,AF69=TRUE,AG69=TRUE,AH69=TRUE),1,0) -> 1
A70: =IF(B70="",A69,B70+1) -> 70 | B70: =IF(AND(A69<1,AI70=1),1,IF(AI70=1,A69,"")) -> 69 | C70: 44321 | D70: NEWTON ABBOT | E70: Jump | F70: Chase | G70: Hcap | H70: Open | K70: 5yo+ | L70: A | M70: 2 | O70: Open | P70: 2m4f216y | Q70: 2m 4f | R70: 23250 | S70: PARTNERSHIP HCAP CSE | T70: South | X70: 0 | Y70: =IF(L70="F",L70,"A") -> A | Z70: =VLOOKUP(Q70,lists!Q:R,2,FALSE) -> 3 | AA70: =VLOOKUP(G70,lists!$B$2:$D$3,3,FALSE) -> TRUE | AB70: =VLOOKUP(F70,lists!$B:$C,2,FALSE) -> TRUE | AC70: =IF(AND(Z70>=VLOOKUP(JUMP!$I$1,lists!$Q:$R,2,FALSE),Z70<=VLOOKUP(JUMP!$I$2,lists!$Q:$R,2,FALSE)),TRUE,FALSE) -> TRUE | AD70: =VLOOKUP(Y70,lists!$B$7:$D$8,3,FALSE) -> TRUE | AE70: =VLOOKUP(SUBSTITUTE(IF(H70="","Open",H70),"Beg","Mdn"),lists!$B$27:$D$29,3,FALSE) -> TRUE | AF70: =IF(JUMP!$I$5="All",TRUE,IF(JUMP!$I$5=TEXT('Raw - J'!C70,"mmm"),TRUE,FALSE)) -> TRUE | AG70: =VLOOKUP(M70,lists!B:D,3,FALSE) -> TRUE | AH70: =VLOOKUP(T70,lists!$B$23:$D$25,3,FALSE) -> TRUE | AI70: =IF(AND(AA70=TRUE,AB70=TRUE,AC70=TRUE,AD70=TRUE,AE70=TRUE,AF70=TRUE,AG70=TRUE,AH70=TRUE),1,0) -> 1
A71: =IF(B71="",A70,B71+1) -> 71 | B71: =IF(AND(A70<1,AI71=1),1,IF(AI71=1,A70,"")) -> 70 | C71: 44322 | D71: HUNTINGDON | E71: Jump | F71: NHF | G71: WFA | H71: Mdn | K71: 4-6yo | L71: A | M71: 5 | O71: Open | P71: 1m7f171y | Q71: 2m | R71: 3500 | S71: MANSIONBET NHF | T71: Midlands | X71: 0 | Y71: =IF(L71="F",L71,"A") -> A | Z71: =VLOOKUP(Q71,lists!Q:R,2,FALSE) -> 2 | AA71: =VLOOKUP(G71,lists!$B$2:$D$3,3,FALSE) -> TRUE | AB71: =VLOOKUP(F71,lists!$B:$C,2,FALSE) -> TRUE | AC71: =IF(AND(Z71>=VLOOKUP(JUMP!$I$1,lists!$Q:$R,2,FALSE),Z71<=VLOOKUP(JUMP!$I$2,lists!$Q:$R,2,FALSE)),TRUE,FALSE) -> TRUE | AD71: =VLOOKUP(Y71,lists!$B$7:$D$8,3,FALSE) -> TRUE | AE71: =VLOOKUP(SUBSTITUTE(IF(H71="","Open",H71),"Beg","Mdn"),lists!$B$27:$D$29,3,FALSE) -> TRUE | AF71: =IF(JUMP!$I$5="All",TRUE,IF(JUMP!$I$5=TEXT('Raw - J'!C71,"mmm"),TRUE,FALSE)) -> TRUE | AG71: =VLOOKUP(M71,lists!B:D,3,FALSE) -> TRUE | AH71: =VLOOKUP(T71,lists!$B$23:$D$25,3,FALSE) -> TRUE | AI71: =IF(AND(AA71=TRUE,AB71=TRUE,AC71=TRUE,AD71=TRUE,AE71=TRUE,AF71=TRUE,AG71=TRUE,AH71=TRUE),1,0) -> 1
A72: =IF(B72="",A71,B72+1) -> 72 | B72: =IF(AND(A71<1,AI72=1),1,IF(AI72=1,A71,"")) -> 71 | C72: 44322 | D72: HUNTINGDON | E72: Jump | F72: Hurdle | G72: WFA | H72: Mdn | J72: NH | K72: 4yo+ | L72: A | M72: 4 | O72: Open | P72: 2m4f145y | Q72: 2m 4f | R72: 5400 | S72: MANSIONBET MDN HUR | T72: Midlands | X72: 0 | Y72: =IF(L72="F",L72,"A") -> A | Z72: =VLOOKUP(Q72,lists!Q:R,2,FALSE) -> 3 | AA72: =VLOOKUP(G72,lists!$B$2:$D$3,3,FALSE) -> TRUE | AB72: =VLOOKUP(F72,lists!$B:$C,2,FALSE) -> TRUE | AC72: =IF(AND(Z72>=VLOOKUP(JUMP!$I$1,lists!$Q:$R,2,FALSE),Z72<=VLOOKUP(JUMP!$I$2,lists!$Q:$R,2,FALSE)),TRUE,FALSE) -> TRUE | AD72: =VLOOKUP(Y72,lists!$B$7:$D$8,3,FALSE) -> TRUE | AE72: =VLOOKUP(SUBSTITUTE(IF(H72="","Open",H72),"Beg","Mdn"),lists!$B$27:$D$29,3,FALSE) -> TRUE | AF72: =IF(JUMP!$I$5="All",TRUE,IF(JUMP!$I$5=TEXT('Raw - J'!C72,"mmm"),TRUE,FALSE)) -> TRUE | AG72: =VLOOKUP(M72,lists!B:D,3,FALSE) -> TRUE | AH72: =VLOOKUP(T72,lists!$B$23:$D$25,3,FALSE) -> TRUE | AI72: =IF(AND(AA72=TRUE,AB72=TRUE,AC72=TRUE,AD72=TRUE,AE72=TRUE,AF72=TRUE,AG72=TRUE,AH72=TRUE),1,0) -> 1
A73: =IF(B73="",A72,B73+1) -> 73 | B73: =IF(AND(A72<1,AI73=1),1,IF(AI73=1,A72,"")) -> 72 | C73: 44322 | D73: HUNTINGDON | E73: Jump | F73: Hurdle | G73: Hcap | H73: Open | K73: 4yo+ | L73: F | M73: 5 | O73: 0-100 | P73: 3m1f10y | Q73: 3m | R73: 5600 | S73: MANSIONBET HCAP HUR | T73: Midlands | X73: 0 | Y73: =IF(L73="F",L73,"A") -> F | Z73: =VLOOKUP(Q73,lists!Q:R,2,FALSE) -> 5 | AA73: =VLOOKUP(G73,lists!$B$2:$D$3,3,FALSE) -> TRUE | AB73: =VLOOKUP(F73,lists!$B:$C,2,FALSE) -> TRUE | AC73: =IF(AND(Z73>=VLOOKUP(JUMP!$I$1,lists!$Q:$R,2,FALSE),Z73<=VLOOKUP(JUMP!$I$2,lists!$Q:$R,2,FALSE)),TRUE,FALSE) -> TRUE | AD73: =VLOOKUP(Y73,lists!$B$7:$D$8,3,FALSE) -> TRUE | AE73: =VLOOKUP(SUBSTITUTE(IF(H73="","Open",H73),"Beg","Mdn"),lists!$B$27:$D$29,3,FALSE) -> TRUE | AF73: =IF(JUMP!$I$5="All",TRUE,IF(JUMP!$I$5=TEXT('Raw - J'!C73,"mmm"),TRUE,FALSE)) -> TRUE | AG73: =VLOOKUP(M73,lists!B:D,3,FALSE) -> TRUE | AH73: =VLOOKUP(T73,lists!$B$23:$D$25,3,FALSE) -> TRUE | AI73: =IF(AND(AA73=TRUE,AB73=TRUE,AC73=TRUE,AD73=TRUE,AE73=TRUE,AF73=TRUE,AG73=TRUE,AH73=TRUE),1,0) -> 1
A74: =IF(B74="",A73,B74+1) -> 74 | B74: =IF(AND(A73<1,AI74=1),1,IF(AI74=1,A73,"")) -> 73 | C74: 44322 | D74: HUNTINGDON | E74: Jump | F74: Hurdle | G74: Hcap | H74: Nov | K74: 4yo+ | L74: A | M74: 4 | O74: 0-120 | P74: 1m7f171y | Q74: 2m | R74: 6100 | S74: MANSION NOV HCP HUR | T74: Midlands | X74: 0 | Y74: =IF(L74="F",L74,"A") -> A | Z74: =VLOOKUP(Q74,lists!Q:R,2,FALSE) -> 2 | AA74: =VLOOKUP(G74,lists!$B$2:$D$3,3,FALSE) -> TRUE | AB74: =VLOOKUP(F74,lists!$B:$C,2,FALSE) -> TRUE | AC74: =IF(AND(Z74>=VLOOKUP(JUMP!$I$1,lists!$Q:$R,2,FALSE),Z74<=VLOOKUP(JUMP!$I$2,lists!$Q:$R,2,FALSE)),TRUE,FALSE) -> TRUE | AD74: =VLOOKUP(Y74,lists!$B$7:$D$8,3,FALSE) -> TRUE | AE74: =VLOOKUP(SUBSTITUTE(IF(H74="","Open",H74),"Beg","Mdn"),lists!$B$27:$D$29,3,FALSE) -> TRUE | AF74: =IF(JUMP!$I$5="All",TRUE,IF(JUMP!$I$5=TEXT('Raw - J'!C74,"mmm"),TRUE,FALSE)) -> TRUE | AG74: =VLOOKUP(M74,lists!B:D,3,FALSE) -> TRUE | AH74: =VLOOKUP(T74,lists!$B$23:$D$25,3,FALSE) -> TRUE | AI74: =IF(AND(AA74=TRUE,AB74=TRUE,AC74=TRUE,AD74=TRUE,AE74=TRUE,AF74=TRUE,AG74=TRUE,AH74=TRUE),1,0) -> 1
A75: =IF(B75="",A74,B75+1) -> 75 | B75: =IF(AND(A74<1,AI75=1),1,IF(AI75=1,A74,"")) -> 74 | C75: 44322 | D75: HUNTINGDON | E75: Jump | F75: Chase | G75: Hcap | H75: Nov | K75: 5yo+ | L75: A | M75: 5 | O75: 0-105 | P75: 2m7f129y | Q75: 3m | R75: 6700 | S75: MANSION NOV HCP CSE | T75: Midlands | X75: 0 | Y75: =IF(L75="F",L75,"A") -> A | Z75: =VLOOKUP(Q75,lists!Q:R,2,FALSE) -> 5 | AA75: =VLOOKUP(G75,lists!$B$2:$D$3,3,FALSE) -> TRUE | AB75: =VLOOKUP(F75,lists!$B:$C,2,FALSE) -> TRUE | AC75: =IF(AND(Z75>=VLOOKUP(JUMP!$I$1,lists!$Q:$R,2,FALSE),Z75<=VLOOKUP(JUMP!$I$2,lists!$Q:$R,2,FALSE)),TRUE,FALSE) -> TRUE | AD75: =VLOOKUP(Y75,lists!$B$7:$D$8,3,FALSE) -> TRUE | AE75: =VLOOKUP(SUBSTITUTE(IF(H75="","Open",H75),"Beg","Mdn"),lists!$B$27:$D$29,3,FALSE) -> TRUE | AF75: =IF(JUMP!$I$5="All",TRUE,IF(JUMP!$I$5=TEXT('Raw - J'!C75,"mmm"),TRUE,FALSE)) -> TRUE | AG75: =VLOOKUP(M75,lists!B:D,3,FALSE) -> TRUE | AH75: =VLOOKUP(T75,lists!$B$23:$D$25,3,FALSE) -> TRUE | AI75: =IF(AND(AA75=TRUE,AB75=TRUE,AC75=TRUE,AD75=TRUE,AE75=TRUE,AF75=TRUE,AG75=TRUE,AH75=TRUE),1,0) -> 1
A76: =IF(B76="",A75,B76+1) -> 76 | B76: =IF(AND(A75<1,AI76=1),1,IF(AI76=1,A75,"")) -> 75 | C76: 44322 | D76: HUNTINGDON | E76: Jump | F76: Hurdle | G76: Hcap | H76: Open | K76: 4yo+ | L76: A | M76: 4 | O76: 0-110 | P76: 2m3f137y | Q76: 2m 4f | R76: 7600 | S76: MANSIONBET HCP HUR | T76: Midlands | X76: 0 | Y76: =IF(L76="F",L76,"A") -> A | Z76: =VLOOKUP(Q76,lists!Q:R,2,FALSE) -> 3 | AA76: =VLOOKUP(G76,lists!$B$2:$D$3,3,FALSE) -> TRUE | AB76: =VLOOKUP(F76,lists!$B:$C,2,FALSE) -> TRUE | AC76: =IF(AND(Z76>=VLOOKUP(JUMP!$I$1,lists!$Q:$R,2,FALSE),Z76<=VLOOKUP(JUMP!$I$2,lists!$Q:$R,2,FALSE)),TRUE,FALSE) -> TRUE | AD76: =VLOOKUP(Y76,lists!$B$7:$D$8,3,FALSE) -> TRUE | AE76: =VLOOKUP(SUBSTITUTE(IF(H76="","Open",H76),"Beg","Mdn"),lists!$B$27:$D$29,3,FALSE) -> TRUE | AF76: =IF(JUMP!$I$5="All",TRUE,IF(JUMP!$I$5=TEXT('Raw - J'!C76,"mmm"),TRUE,FALSE)) -> TRUE | AG76: =VLOOKUP(M76,lists!B:D,3,FALSE) -> TRUE | AH76: =VLOOKUP(T76,lists!$B$23:$D$25,3,FALSE) -> TRUE | AI76: =IF(AND(AA76=TRUE,AB76=TRUE,AC76=TRUE,AD76=TRUE,AE76=TRUE,AF76=TRUE,AG76=TRUE,AH76=TRUE),1,0) -> 1
A77: =IF(B77="",A76,B77+1) -> 77 | B77: =IF(AND(A76<1,AI77=1),1,IF(AI77=1,A76,"")) -> 76 | C77: 44322 | D77: HUNTINGDON | E77: Jump | F77: Chase | G77: Hcap | H77: Open | K77: 5yo+ | L77: A | M77: 4 | O77: 0-110 | P77: 2m104y | Q77: 2m | R77: 9600 | S77: MANSIONBET HCAP CSE | T77: Midlands | X77: 0 | Y77: =IF(L77="F",L77,"A") -> A | Z77: =VLOOKUP(Q77,lists!Q:R,2,FALSE) -> 2 | AA77: =VLOOKUP(G77,lists!$B$2:$D$3,3,FALSE) -> TRUE | AB77: =VLOOKUP(F77,lists!$B:$C,2,FALSE) -> TRUE | AC77: =IF(AND(Z77>=VLOOKUP(JUMP!$I$1,lists!$Q:$R,2,FALSE),Z77<=VLOOKUP(JUMP!$I$2,lists!$Q:$R,2,FALSE)),TRUE,FALSE) -> TRUE | AD77: =VLOOKUP(Y77,lists!$B$7:$D$8,3,FALSE) -> TRUE | AE77: =VLOOKUP(SUBSTITUTE(IF(H77="","Open",H77),"Beg","Mdn"),lists!$B$27:$D$29,3,FALSE) -> TRUE | AF77: =IF(JUMP!$I$5="All",TRUE,IF(JUMP!$I$5=TEXT('Raw - J'!C77,"mmm"),TRUE,FALSE)) -> TRUE | AG77: =VLOOKUP(M77,lists!B:D,3,FALSE) -> TRUE | AH77: =VLOOKUP(T77,lists!$B$23:$D$25,3,FALSE) -> TRUE | AI77: =IF(AND(AA77=TRUE,AB77=TRUE,AC77=TRUE,AD77=TRUE,AE77=TRUE,AF77=TRUE,AG77=TRUE,AH77=TRUE),1,0) -> 1
A78: =IF(B78="",A77,B78+1) -> 78 | B78: =IF(AND(A77<1,AI78=1),1,IF(AI78=1,A77,"")) -> 77 | C78: 44322 | D78: WINCANTON | E78: Jump | F78: Hurdle | G78: Hcap | H78: Open | K78: 4yo+ | L78: A | M78: 5 | O78: 0-100 | P78: 2m5f82y | Q78: 2m 4f | R78: 4600 | S78: BEWISER HCAP HUR | T78: South | X78: 0 | Y78: =IF(L78="F",L78,"A") -> A | Z78: =VLOOKUP(Q78,lists!Q:R,2,FALSE) -> 3 | AA78: =VLOOKUP(G78,lists!$B$2:$D$3,3,FALSE) -> TRUE | AB78: =VLOOKUP(F78,lists!$B:$C,2,FALSE) -> TRUE | AC78: =IF(AND(Z78>=VLOOKUP(JUMP!$I$1,lists!$Q:$R,2,FALSE),Z78<=VLOOKUP(JUMP!$I$2,lists!$Q:$R,2,FALSE)),TRUE,FALSE) -> TRUE | AD78: =VLOOKUP(Y78,lists!$B$7:$D$8,3,FALSE) -> TRUE | AE78: =VLOOKUP(SUBSTITUTE(IF(H78="","Open",H78),"Beg","Mdn"),lists!$B$27:$D$29,3,FALSE) -> TRUE | AF78: =IF(JUMP!$I$5="All",TRUE,IF(JUMP!$I$5=TEXT('Raw - J'!C78,"mmm"),TRUE,FALSE)) -> TRUE | AG78: =VLOOKUP(M78,lists!B:D,3,FALSE) -> TRUE | AH78: =VLOOKUP(T78,lists!$B$23:$D$25,3,FALSE) -> TRUE | AI78: =IF(AND(AA78=TRUE,AB78=TRUE,AC78=TRUE,AD78=TRUE,AE78=TRUE,AF78=TRUE,AG78=TRUE,AH78=TRUE),1,0) -> 1
A79: =IF(B79="",A78,B79+1) -> 79 | B79: =IF(AND(A78<1,AI79=1),1,IF(AI79=1,A78,"")) -> 78 | C79: 44322 | D79: WINCANTON | E79: Jump | F79: Hurdle | G79: WFA | H79: Mdn | K79: 4yo+ | L79: A | M79: 4 | O79: Open | P79: 1m7f65y | Q79: 2m | R79: 5400 | S79: RACINGTV MDN HUR | T79: South | X79: 0 | Y79: =IF(L79="F",L79,"A") -> A | Z79: =VLOOKUP(Q79,lists!Q:R,2,FALSE) -> 2 | AA79: =VLOOKUP(G79,lists!$B$2:$D$3,3,FALSE) -> TRUE | AB79: =VLOOKUP(F79,lists!$B:$C,2,FALSE) -> TRUE | AC79: =IF(AND(Z79>=VLOOKUP(JUMP!$I$1,lists!$Q:$R,2,FALSE),Z79<=VLOOKUP(JUMP!$I$2,lists!$Q:$R,2,FALSE)),TRUE,FALSE) -> TRUE | AD79: =VLOOKUP(Y79,lists!$B$7:$D$8,3,FALSE) -> TRUE | AE79: =VLOOKUP(SUBSTITUTE(IF(H79="","Open",H79),"Beg","Mdn"),lists!$B$27:$D$29,3,FALSE) -> TRUE | AF79: =IF(JUMP!$I$5="All",TRUE,IF(JUMP!$I$5=TEXT('Raw - J'!C79,"mmm"),TRUE,FALSE)) -> TRUE | AG79: =VLOOKUP(M79,lists!B:D,3,FALSE) -> TRUE | AH79: =VLOOKUP(T79,lists!$B$23:$D$25,3,FALSE) -> TRUE | AI79: =IF(AND(AA79=TRUE,AB79=TRUE,AC79=TRUE,AD79=TRUE,AE79=TRUE,AF79=TRUE,AG79=TRUE,AH79=TRUE),1,0) -> 1
A80: =IF(B80="",A79,B80+1) -> 80 | B80: =IF(AND(A79<1,AI80=1),1,IF(AI80=1,A79,"")) -> 79 | C80: 44322 | D80: WINCANTON | E80: Jump | F80: Chase | G80: Hcap | H80: Open | K80: 5yo+ | L80: A | M80: 5 | O80: 0-100 | P80: 3m1f30y | Q80: 3m | R80: 5600 | S80: RACING TV HCAP CSE | T80: South | X80: 0 | Y80: =IF(L80="F",L80,"A") -> A | Z80: =VLOOKUP(Q80,lists!Q:R,2,FALSE) -> 5 | AA80: =VLOOKUP(G80,lists!$B$2:$D$3,3,FALSE) -> TRUE | AB80: =VLOOKUP(F80,lists!$B:$C,2,FALSE) -> TRUE | AC80: =IF(AND(Z80>=VLOOKUP(JUMP!$I$1,lists!$Q:$R,2,FALSE),Z80<=VLOOKUP(JUMP!$I$2,lists!$Q:$R,2,FALSE)),TRUE,FALSE) -> TRUE | AD80: =VLOOKUP(Y80,lists!$B$7:$D$8,3,FALSE) -> TRUE | AE80: =VLOOKUP(SUBSTITUTE(IF(H80="","Open",H80),"Beg","Mdn"),lists!$B$27:$D$29,3,FALSE) -> TRUE | AF80: =IF(JUMP!$I$5="All",TRUE,IF(JUMP!$I$5=TEXT('Raw - J'!C80,"mmm"),TRUE,FALSE)) -> TRUE | AG80: =VLOOKUP(M80,lists!B:D,3,FALSE) -> TRUE | AH80: =VLOOKUP(T80,lists!$B$23:$D$25,3,FALSE) -> TRUE | AI80: =IF(AND(AA80=TRUE,AB80=TRUE,AC80=TRUE,AD80=TRUE,AE80=TRUE,AF80=TRUE,AG80=TRUE,AH80=TRUE),1,0) -> 1
A81: =IF(B81="",A80,B81+1) -> 81 | B81: =IF(AND(A80<1,AI81=1),1,IF(AI81=1,A80,"")) -> 80 | C81: 44322 | D81: WINCANTON | E81: Jump | F81: Hurdle | G81: Hcap | H81: Open | K81: 4yo+ | L81: A | M81: 4 | O81: 0-110 | P81: 1m7f65y | Q81: 2m | R81: 5900 | S81: RACE LIVE HCAP HUR | T81: South | X81: 0 | Y81: =IF(L81="F",L81,"A") -> A | Z81: =VLOOKUP(Q81,lists!Q:R,2,FALSE) -> 2 | AA81: =VLOOKUP(G81,lists!$B$2:$D$3,3,FALSE) -> TRUE | AB81: =VLOOKUP(F81,lists!$B:$C,2,FALSE) -> TRUE | AC81: =IF(AND(Z81>=VLOOKUP(JUMP!$I$1,lists!$Q:$R,2,FALSE),Z81<=VLOOKUP(JUMP!$I$2,lists!$Q:$R,2,FALSE)),TRUE,FALSE) -> TRUE | AD81: =VLOOKUP(Y81,lists!$B$7:$D$8,3,FALSE) -> TRUE | AE81: =VLOOKUP(SUBSTITUTE(IF(H81="","Open",H81),"Beg","Mdn"),lists!$B$27:$D$29,3,FALSE) -> TRUE | AF81: =IF(JUMP!$I$5="All",TRUE,IF(JUMP!$I$5=TEXT('Raw - J'!C81,"mmm"),TRUE,FALSE)) -> TRUE | AG81: =VLOOKUP(M81,lists!B:D,3,FALSE) -> TRUE | AH81: =VLOOKUP(T81,lists!$B$23:$D$25,3,FALSE) -> TRUE | AI81: =IF(AND(AA81=TRUE,AB81=TRUE,AC81=TRUE,AD81=TRUE,AE81=TRUE,AF81=TRUE,AG81=TRUE,AH81=TRUE),1,0) -> 1
A82: =IF(B82="",A81,B82+1) -> 82 | B82: =IF(AND(A81<1,AI82=1),1,IF(AI82=1,A81,"")) -> 81 | C82: 44322 | D82: WINCANTON | E82: Jump | F82: Chase | G82: Hcap | H82: Nov | K82: 5yo+ | L82: A | M82: 5 | O82: 0-105 | P82: 1m7f149y | Q82: 2m | R82: 6400 | S82: BEWISER NOV CSE | T82: South | X82: 0 | Y82: =IF(L82="F",L82,"A") -> A | Z82: =VLOOKUP(Q82,lists!Q:R,2,FALSE) -> 2 | AA82: =VLOOKUP(G82,lists!$B$2:$D$3,3,FALSE) -> TRUE | AB82: =VLOOKUP(F82,lists!$B:$C,2,FALSE) -> TRUE | AC82: =IF(AND(Z82>=VLOOKUP(JUMP!$I$1,lists!$Q:$R,2,FALSE),Z82<=VLOOKUP(JUMP!$I$2,lists!$Q:$R,2,FALSE)),TRUE,FALSE) -> TRUE | AD82: =VLOOKUP(Y82,lists!$B$7:$D$8,3,FALSE) -> TRUE | AE82: =VLOOKUP(SUBSTITUTE(IF(H82="","Open",H82),"Beg","Mdn"),lists!$B$27:$D$29,3,FALSE) -> TRUE | AF82: =IF(JUMP!$I$5="All",TRUE,IF(JUMP!$I$5=TEXT('Raw - J'!C82,"mmm"),TRUE,FALSE)) -> TRUE | AG82: =VLOOKUP(M82,lists!B:D,3,FALSE) -> TRUE | AH82: =VLOOKUP(T82,lists!$B$23:$D$25,3,FALSE) -> TRUE | AI82: =IF(AND(AA82=TRUE,AB82=TRUE,AC82=TRUE,AD82=TRUE,AE82=TRUE,AF82=TRUE,AG82=TRUE,AH82=TRUE),1,0) -> 1
A83: =IF(B83="",A82,B83+1) -> 83 | B83: =IF(AND(A82<1,AI83=1),1,IF(AI83=1,A82,"")) -> 82 | C83: 44322 | D83: WINCANTON | E83: Jump | F83: Hurdle | G83: Hcap | H83: Open | K83: 4yo+ | L83: A | M83: 3 | O83: 0-130 | P83: 2m3f166y | Q83: 2m 4f | R83: 9800 | S83: WESSEX HCAP HUR | T83: South | X83: 0 | Y83: =IF(L83="F",L83,"A") -> A | Z83: =VLOOKUP(Q83,lists!Q:R,2,FALSE) -> 3 | AA83: =VLOOKUP(G83,lists!$B$2:$D$3,3,FALSE) -> TRUE | AB83: =VLOOKUP(F83,lists!$B:$C,2,FALSE) -> TRUE | AC83: =IF(AND(Z83>=VLOOKUP(JUMP!$I$1,lists!$Q:$R,2,FALSE),Z83<=VLOOKUP(JUMP!$I$2,lists!$Q:$R,2,FALSE)),TRUE,FALSE) -> TRUE | AD83: =VLOOKUP(Y83,lists!$B$7:$D$8,3,FALSE) -> TRUE | AE83: =VLOOKUP(SUBSTITUTE(IF(H83="","Open",H83),"Beg","Mdn"),lists!$B$27:$D$29,3,FALSE) -> TRUE | AF83: =IF(JUMP!$I$5="All",TRUE,IF(JUMP!$I$5=TEXT('Raw - J'!C83,"mmm"),TRUE,FALSE)) -> TRUE | AG83: =VLOOKUP(M83,lists!B:D,3,FALSE) -> TRUE | AH83: =VLOOKUP(T83,lists!$B$23:$D$25,3,FALSE) -> TRUE | AI83: =IF(AND(AA83=TRUE,AB83=TRUE,AC83=TRUE,AD83=TRUE,AE83=TRUE,AF83=TRUE,AG83=TRUE,AH83=TRUE),1,0) -> 1
A84: =IF(B84="",A83,B84+1) -> 84 | B84: =IF(AND(A83<1,AI84=1),1,IF(AI84=1,A83,"")) -> 83 | C84: 44322 | D84: WINCANTON | E84: Jump | F84: Chase | G84: Hcap | H84: Open | K84: 5yo+ | L84: A | M84: 3 | O84: 0-125 | P84: 3m1f30y | Q84: 3m | R84: 11000 | S84: INSURANCE HCP CSE | T84: South | X84: 0 | Y84: =IF(L84="F",L84,"A") -> A | Z84: =VLOOKUP(Q84,lists!Q:R,2,FALSE) -> 5 | AA84: =VLOOKUP(G84,lists!$B$2:$D$3,3,FALSE) -> TRUE | AB84: =VLOOKUP(F84,lists!$B:$C,2,FALSE) -> TRUE | AC84: =IF(AND(Z84>=VLOOKUP(JUMP!$I$1,lists!$Q:$R,2,FALSE),Z84<=VLOOKUP(JUMP!$I$2,lists!$Q:$R,2,FALSE)),TRUE,FALSE) -> TRUE | AD84: =VLOOKUP(Y84,lists!$B$7:$D$8,3,FALSE) -> TRUE | AE84: =VLOOKUP(SUBSTITUTE(IF(H84="","Open",H84),"Beg","Mdn"),lists!$B$27:$D$29,3,FALSE) -> TRUE | AF84: =IF(JUMP!$I$5="All",TRUE,IF(JUMP!$I$5=TEXT('Raw - J'!C84,"mmm"),TRUE,FALSE)) -> TRUE | AG84: =VLOOKUP(M84,lists!B:D,3,FALSE) -> TRUE | AH84: =VLOOKUP(T84,lists!$B$23:$D$25,3,FALSE) -> TRUE | AI84: =IF(AND(AA84=TRUE,AB84=TRUE,AC84=TRUE,AD84=TRUE,AE84=TRUE,AF84=TRUE,AG84=TRUE,AH84=TRUE),1,0) -> 1
